Workbook
Name Rentabilidad: 'Base de Datos'!$AS:$AS
Name Publicar: 'Base de Datos'!$AG$1
Name Precio: 'Base de Datos'!$F:$F

Sheet Info general barrios
A1: Barrio | B1: Amenidades | C1: Links amenidades | D1: Fotos amenidades | E1: Precio más bajo | F1: Precio promedio | G1: Habitaciones promedio | H1: Baños promedio | I1: Área promedio | J1: Estrato
A2: Las Granjas | B2: Gimnasio Comfamiliar CAPF, Iglesia San Judas Tadeo, Colegio Maria Cristina Arango, Aeropuerto Benito Salas , Centro comercial San Pedro Plaza , Centro comercial San Juan Plaza , Centro de salud Carmen Emilia Ospina , | C2: https://gimnasioscomfamiliar.com/sede-cambulos/ , https://diocesisdeneiva.org/directorio/parroquias/San-Judas-Tadeo-Neiva , https://www.iemariacristinaarango.edu.co/, https://www.aerocivil.gov.co/aeropuertos/Pages/Benito-Salas.aspx , https://sanpedroplazacomercial.com.co/ , https://sanjuanplazacc.com/ , https://esecarmenemiliaospina.gov.co/ | D2: https://i.imgur.com/uvF7ybU.jpeg , https://i.imgur.com/4UFnHhg.jpeg , https://i.imgur.com/dpY74R2.jpeg , https://imgur.com/yBDIUKl.jpeg , https://i.imgur.com/0McV52E.jpeg , https://i.imgur.com/ZfvQIV4.jpeg , | E2: =IFERROR(MINIFS('Inventario barrios'!F:F,'Inventario barrios'!D:D,TRIM(A2),'Inventario barrios'!F:F,">0"),0) -> 130000000 | F2: =IFERROR(AVERAGEIFS('Inventario barrios'!F:F,'Inventario barrios'!D:D,TRIM(A2),'Inventario barrios'!F:F,">0"),0) -> 5.9255102e+08 | G2: =IFERROR(AVERAGEIFS('Inventario barrios'!J:J,'Inventario barrios'!D:D,TRIM(A2),'Inventario barrios'!J:J,">0"),0) -> 0 | H2: =IFERROR(AVERAGEIFS('Inventario barrios'!K:K,'Inventario barrios'!D:D,TRIM(A2),'Inventario barrios'!K:K,">0"),0) -> 0 | I2: =IFERROR(AVERAGEIFS('Inventario barrios'!N:N,'Inventario barrios'!D:D,TRIM(A2),'Inventario barrios'!N:N,">0"),0) -> 3.1458333 | J2: 2
A3: Los Cámbulos II | B3: Gimnasio Comfamiliar CAPF, Iglesia San Judas Tadeo, Aeropuerto Benito Salas , Centro comercial San Pedro Plaza , Centro comercial San Juan Plaza , Centro de salud Carmen Emilia Ospina , | C3: https://gimnasioscomfamiliar.com/sede-cambulos/ , https://diocesisdeneiva.org/directorio/parroquias/San-Judas-Tadeo-Neiva , https://www.aerocivil.gov.co/aeropuertos/Pages/Benito-Salas.aspx , https://sanpedroplazacomercial.com.co/ , https://sanjuanplazacc.com/ , https://esecarmenemiliaospina.gov.co/ , | D3: https://i.imgur.com/uvF7ybU.jpeg , https://i.imgur.com/4UFnHhg.jpeg , https://imgur.com/yBDIUKl.jpeg, https://i.imgur.com/0McV52E.jpeg , https://i.imgur.com/ZfvQIV4.jpeg , https://imgur.com/US4kxwg.jpeg | E3: =IFERROR(MINIFS('Inventario barrios'!F:F,'Inventario barrios'!D:D,TRIM(A3),'Inventario barrios'!F:F,">0"),0) -> 153000000 | F3: =IFERROR(AVERAGEIFS('Inventario barrios'!F:F,'Inventario barrios'!D:D,TRIM(A3),'Inventario barrios'!F:F,">0"),0) -> 309720000 | G3: =IFERROR(AVERAGEIFS('Inventario barrios'!J:J,'Inventario barrios'!D:D,TRIM(A3),'Inventario barrios'!J:J,">0"),0) -> 0 | H3: =IFERROR(AVERAGEIFS('Inventario barrios'!K:K,'Inventario barrios'!D:D,TRIM(A3),'Inventario barrios'!K:K,">0"),0) -> 0 | I3: =IFERROR(AVERAGEIFS('Inventario barrios'!N:N,'Inventario barrios'!D:D,TRIM(A3),'Inventario barrios'!N:N,">0"),0) -> 2.76 | J3: 3
A4: Los Molinos | B4: Gimnasio Comfamiliar CAPF, Iglesia San Judas Tadeo, Aeropuerto Benito Salas , Centro comercial San Pedro Plaza , Centro comercial San Juan Plaza , Centro de salud Carmen Emilia Ospina , | C4: https://gimnasioscomfamiliar.com/sede-cambulos/ , https://diocesisdeneiva.org/directorio/parroquias/San-Judas-Tadeo-Neiva , https://www.aerocivil.gov.co/aeropuertos/Pages/Benito-Salas.aspx , https://sanpedroplazacomercial.com.co/ , https://sanjuanplazacc.com/ , https://esecarmenemiliaospina.gov.co/ , | D4: https://i.imgur.com/uvF7ybU.jpeg , https://i.imgur.com/4UFnHhg.jpeg , https://imgur.com/yBDIUKl.jpeg, https://i.imgur.com/0McV52E.jpeg , https://i.imgur.com/ZfvQIV4.jpeg , https://imgur.com/US4kxwg.jpeg | E4: =IFERROR(MINIFS('Inventario barrios'!F:F,'Inventario barrios'!D:D,TRIM(A4),'Inventario barrios'!F:F,">0"),0) -> 260000000 | F4: =IFERROR(AVERAGEIFS('Inventario barrios'!F:F,'Inventario barrios'!D:D,TRIM(A4),'Inventario barrios'!F:F,">0"),0) -> 3.1857143e+08 | G4: =IFERROR(AVERAGEIFS('Inventario barrios'!J:J,'Inventario barrios'!D:D,TRIM(A4),'Inventario barrios'!J:J,">0"),0) -> 0 | H4: =IFERROR(AVERAGEIFS('Inventario barrios'!K:K,'Inventario barrios'!D:D,TRIM(A4),'Inventario barrios'!K:K,">0"),0) -> 0 | I4: =IFERROR(AVERAGEIFS('Inventario barrios'!N:N,'Inventario barrios'!D:D,TRIM(A4),'Inventario barrios'!N:N,">0"),0) -> 3 | J4: 4
A5: Villa Carolina | B5: Centro comercial San Pedro Plaza , Centro comercial San Juan Plaza , Supermercado Olímpica , Homecenter , Parroquia Santa María de la Paz , Centro de atención integral materno infantil CAIMI , | C5: https://sanpedroplazacomercial.com.co/ , https://sanjuanplazacc.com/ , https://www.olimpica.com/nuestras-tiendas/ , https://www.homecenter.com.co/homecenter-co/ , https://diocesisdeneiva.org/directorio/parroquias/Santa-Maria-de-la-Paz-Neiva , https://esecarmenemiliaospina.gov.co/el-corazon-del-caimi-ya-esta-listo/ , | D5: https://i.imgur.com/0McV52E.jpeg , https://i.imgur.com/NqTPCOW.jpeg , https://i.imgur.com/LTJ6cm8.jpeg , https://i.imgur.com/ZfvQIV4.jpeg , https://i.imgur.com/2jLDNZK.jpeg , https://i.imgur.com/6K5qkDD.jpeg , https://i.imgur.com/2CK2QZ7.jpeg , https://i.imgur.com/5wEmeiL.jpeg , | E5: =IFERROR(MINIFS('Inventario barrios'!F:F,'Inventario barrios'!D:D,TRIM(A5),'Inventario barrios'!F:F,">0"),0) -> 120000000 | F5: =IFERROR(AVERAGEIFS('Inventario barrios'!F:F,'Inventario barrios'!D:D,TRIM(A5),'Inventario barrios'!F:F,">0"),0) -> 3.3333333e+08 | G5: =IFERROR(AVERAGEIFS('Inventario barrios'!J:J,'Inventario barrios'!D:D,TRIM(A5),'Inventario barrios'!J:J,">0"),0) -> 0 | H5: =IFERROR(AVERAGEIFS('Inventario barrios'!K:K,'Inventario barrios'!D:D,TRIM(A5),'Inventario barrios'!K:K,">0"),0) -> 0 | I5: =IFERROR(AVERAGEIFS('Inventario barrios'!N:N,'Inventario barrios'!D:D,TRIM(A5),'Inventario barrios'!N:N,">0"),0) -> 3.1428571 | J5: 5
A6: Villa Urbe | B6: Centro comercial San Pedro Plaza , Centro comercial San Juan Plaza , Supermercado Olímpica , Homecenter , Parroquia Santa María de la Paz , Centro de atención integral materno infantil CAIMI , | C6: https://sanpedroplazacomercial.com.co/ , https://sanjuanplazacc.com/ , https://www.olimpica.com/nuestras-tiendas/ , https://www.homecenter.com.co/homecenter-co/ , https://diocesisdeneiva.org/directorio/parroquias/Santa-Maria-de-la-Paz-Neiva , https://esecarmenemiliaospina.gov.co/el-corazon-del-caimi-ya-esta-listo/ , | D6: https://i.imgur.com/0McV52E.jpeg , https://i.imgur.com/NqTPCOW.jpeg , https://i.imgur.com/LTJ6cm8.jpeg , https://i.imgur.com/ZfvQIV4.jpeg , https://i.imgur.com/2jLDNZK.jpeg , https://i.imgur.com/6K5qkDD.jpeg , https://i.imgur.com/2CK2QZ7.jpeg , https://i.imgur.com/5wEmeiL.jpeg , | E6: =IFERROR(MINIFS('Inventario barrios'!F:F,'Inventario barrios'!D:D,TRIM(A6),'Inventario barrios'!F:F,">0"),0) -> 240000000 | F6: =IFERROR(AVERAGEIFS('Inventario barrios'!F:F,'Inventario barrios'!D:D,TRIM(A6),'Inventario barrios'!F:F,">0"),0) -> 280000000 | G6: =IFERROR(AVERAGEIFS('Inventario barrios'!J:J,'Inventario barrios'!D:D,TRIM(A6),'Inventario barrios'!J:J,">0"),0) -> 0 | H6: =IFERROR(AVERAGEIFS('Inventario barrios'!K:K,'Inventario barrios'!D:D,TRIM(A6),'Inventario barrios'!K:K,">0"),0) -> 0 | I6: =IFERROR(AVERAGEIFS('Inventario barrios'!N:N,'Inventario barrios'!D:D,TRIM(A6),'Inventario barrios'!N:N,">0"),0) -> 3.5 | J6: 2
A7: Alamos Norte | B7: Centro comercial San Pedro Plaza , Centrocomercial San Juan Plaza , Homecenter , Parroquia Santa María de la Paz , Centro de atención integral materno infantil CAIMI , | C7: https://sanpedroplazacomercial.com.co/ , https://sanjuanplazacc.com/ , https://www.olimpica.com/nuestras-tiendas/ , https://www.homecenter.com.co/homecenter-co/ , https://diocesisdeneiva.org/directorio/parroquias/Santa-Maria-de-la-Paz-Neiva , https://esecarmenemiliaospina.gov.co/el-corazon-del-caimi-ya-esta-listo/ , | D7: https://i.imgur.com/0McV52E.jpeg , https://i.imgur.com/NqTPCOW.jpeg , https://i.imgur.com/LTJ6cm8.jpeg , https://i.imgur.com/ZfvQIV4.jpeg , https://i.imgur.com/6K5qkDD.jpeg , https://i.imgur.com/2CK2QZ7.jpeg , https://i.imgur.com/5wEmeiL.jpeg , | E7: =IFERROR(MINIFS('Inventario barrios'!F:F,'Inventario barrios'!D:D,TRIM(A7),'Inventario barrios'!F:F,">0"),0) -> 140000000 | F7: =IFERROR(AVERAGEIFS('Inventario barrios'!F:F,'Inventario barrios'!D:D,TRIM(A7),'Inventario barrios'!F:F,">0"),0) -> 390000000 | G7: =IFERROR(AVERAGEIFS('Inventario barrios'!J:J,'Inventario barrios'!D:D,TRIM(A7),'Inventario barrios'!J:J,">0"),0) -> 0 | H7: =IFERROR(AVERAGEIFS('Inventario barrios'!K:K,'Inventario barrios'!D:D,TRIM(A7),'Inventario barrios'!K:K,">0"),0) -> 0 | I7: =IFERROR(AVERAGEIFS('Inventario barrios'!N:N,'Inventario barrios'!D:D,TRIM(A7),'Inventario barrios'!N:N,">0"),0) -> 4.2 | J7: 3
A8: Santa Librada | B8: Estadio Guillermo Plazas Alcid , INDER , Batallón Tenerife , Comando Policia Nacional , Hospital Universitario Hernando Moncaleano Perdomo , Colegio Santa Librada , | C8: https://clubatleticohuila.com.co/ , https://inderhuila.gov.co/crd/ , https://www.cgfm.mil.co/es/taxonomy/term/13625 , https://www.policia.gov.co/neiva , https://hospitalneiva.gov.co/ , https://www.santalibradaneiva.edu.co/ , | D8: https://imgur.com/hN630gp.jpeg , https://imgur.com/PNtFJ9l.jpeg , https://imgur.com/Vg1js9v.jpeg , https://imgur.com/t2uszmF.jpeg , https://imgur.com/DoTgP2s.jpeg , https://imgur.com/fcJveEr.jpeg | E8: =IFERROR(MINIFS('Inventario barrios'!F:F,'Inventario barrios'!D:D,TRIM(A8),'Inventario barrios'!F:F,">0"),0) -> 130000000 | F8: =IFERROR(AVERAGEIFS('Inventario barrios'!F:F,'Inventario barrios'!D:D,TRIM(A8),'Inventario barrios'!F:F,">0"),0) -> 373000000 | G8: =IFERROR(AVERAGEIFS('Inventario barrios'!J:J,'Inventario barrios'!D:D,TRIM(A8),'Inventario barrios'!J:J,">0"),0) -> 0 | H8: =IFERROR(AVERAGEIFS('Inventario barrios'!K:K,'Inventario barrios'!D:D,TRIM(A8),'Inventario barrios'!K:K,">0"),0) -> 0 | I8: =IFERROR(AVERAGEIFS('Inventario barrios'!N:N,'Inventario barrios'!D:D,TRIM(A8),'Inventario barrios'!N:N,">0"),0) -> 3.5 | J8: 4
A9: Chapinero | B9: Estadio Guillermo Plazas Alcid , INDER , Batallón Tenerife , Comando Policia Nacional , Hospital Universitario Hernando Moncaleano Perdomo , Colegio Santa Librada , | C9: https://clubatleticohuila.com.co/ , https://inderhuila.gov.co/crd/ , https://www.cgfm.mil.co/es/taxonomy/term/13625 , https://www.policia.gov.co/neiva , https://hospitalneiva.gov.co/ , https://www.santalibradaneiva.edu.co/ , | D9: https://imgur.com/hN630gp.jpeg , https://imgur.com/PNtFJ9l.jpeg , https://imgur.com/Vg1js9v.jpeg , https://imgur.com/t2uszmF.jpeg , https://imgur.com/DoTgP2s.jpeg , https://imgur.com/fcJveEr.jpeg , | E9: =IFERROR(MINIFS('Inventario barrios'!F:F,'Inventario barrios'!D:D,TRIM(A9),'Inventario barrios'!F:F,">0"),0) -> 130000000 | F9: =IFERROR(AVERAGEIFS('Inventario barrios'!F:F,'Inventario barrios'!D:D,TRIM(A9),'Inventario barrios'!F:F,">0"),0) -> 4.6934783e+08 | G9: =IFERROR(AVERAGEIFS('Inventario barrios'!J:J,'Inventario barrios'!D:D,TRIM(A9),'Inventario barrios'!J:J,">0"),0) -> 0 | H9: =IFERROR(AVERAGEIFS('Inventario barrios'!K:K,'Inventario barrios'!D:D,TRIM(A9),'Inventario barrios'!K:K,">0"),0) -> 0 | I9: =IFERROR(AVERAGEIFS('Inventario barrios'!N:N,'Inventario barrios'!D:D,TRIM(A9),'Inventario barrios'!N:N,">0"),0) -> 2.65 | J9: 3
A10: Campo Nuñez | B10: Parroquia Nuestra Señora del Perpetuo Socorro , Panadería Peter Pan , Bomberos , Supermercado Popular , Batallón Tenerife , Comando Policia Nacional | C10: https://diocesisdeneiva.org/directorio/parroquias/Nuestra-Senora-del-Perpetuo-Socorro-Neiva , https://peterpan24horas.com/ , https://cbvn.com.co/ , https://www.instagram.com/supermercados_popular/?hl=es , https://www.cgfm.mil.co/es/taxonomy/term/13625 , https://www.policia.gov.co/neiva | D10: https://imgur.com/C5ubqD4.jpeg , https://imgur.com/lx4imr6.jpeg , https://imgur.com/7H6c5V3.jpeg , https://imgur.com/bEUf3pk.jpeg , https://imgur.com/Vg1js9v.jpeg , https://imgur.com/t2uszmF.jpeg | E10: =IFERROR(MINIFS('Inventario barrios'!F:F,'Inventario barrios'!D:D,TRIM(A10),'Inventario barrios'!F:F,">0"),0) -> 260000000 | F10: =IFERROR(AVERAGEIFS('Inventario barrios'!F:F,'Inventario barrios'!D:D,TRIM(A10),'Inventario barrios'!F:F,">0"),0) -> 4.8954545e+08 | G10: =IFERROR(AVERAGEIFS('Inventario barrios'!J:J,'Inventario barrios'!D:D,TRIM(A10),'Inventario barrios'!J:J,">0"),0) -> 0 | H10: =IFERROR(AVERAGEIFS('Inventario barrios'!K:K,'Inventario barrios'!D:D,TRIM(A10),'Inventario barrios'!K:K,">0"),0) -> 0 | I10: =IFERROR(AVERAGEIFS('Inventario barrios'!N:N,'Inventario barrios'!D:D,TRIM(A10),'Inventario barrios'!N:N,">0"),0) -> 2.5 | J10: 2
A11: La Toma | B11: Parroquia Nuestra Señora del Perpetuo Socorro , Panadería Peter Pan , Bomberos , Hospital Universitario Hernando Moncaleano Perdomo , Batallón Tenerife , Comando Policia Nacional | C11: https://diocesisdeneiva.org/directorio/parroquias/Nuestra-Senora-del-Perpetuo-Socorro-Neiva , https://peterpan24horas.com/ , https://cbvn.com.co/ , https://hospitalneiva.gov.co/ , https://www.cgfm.mil.co/es/taxonomy/term/13625 , https://www.policia.gov.co/neiva | D11: https://imgur.com/C5ubqD4.jpeg , https://imgur.com/lx4imr6.jpeg , https://imgur.com/7H6c5V3.jpeg , https://imgur.com/DoTgP2s.jpeg , https://imgur.com/Vg1js9v.jpeg , https://imgur.com/t2uszmF.jpeg | E11: =IFERROR(MINIFS('Inventario barrios'!F:F,'Inventario barrios'!D:D,TRIM(A11),'Inventario barrios'!F:F,">0"),0) -> 140000000 | F11: =IFERROR(AVERAGEIFS('Inventario barrios'!F:F,'Inventario barrios'!D:D,TRIM(A11),'Inventario barrios'!F:F,">0"),0) -> 7.6193543e+08 | G11: =IFERROR(AVERAGEIFS('Inventario barrios'!J:J,'Inventario barrios'!D:D,TRIM(A11),'Inventario barrios'!J:J,">0"),0) -> 0 | H11: =IFERROR(AVERAGEIFS('Inventario barrios'!K:K,'Inventario barrios'!D:D,TRIM(A11),'Inventario barrios'!K:K,">0"),0) -> 0 | I11: =IFERROR(AVERAGEIFS('Inventario barrios'!N:N,'Inventario barrios'!D:D,TRIM(A11),'Inventario barrios'!N:N,">0"),0) -> 2.5862069 | J11: 2
A12: Quirinal | B12: Centro de convenciones José Eustacio Rivera, Clínica UROS, Universidad CORHUILA, Supermercado Olímpica, Supermercado Metro, Servicio Nacional de Aprendizaje (SENA) | C12: https://www.huila.gov.co/publicaciones/12480/el-centro-de-convenciones-jose-eustasio-rivera-y-el-recinto-ferial-la-voragine-epicentros-de-la-programacion-del-san-pedro/ , https://clinicauros.com/ , https://corhuila.edu.co/ , https://www.olimpica.com/nuestras-tiendas/ , https://ofertas.tiendasmetro.co/ubicaciones/ , https://www.sena.edu.co/es-co/Paginas/default.aspx | D12: https://imgur.com/QoxdRse.jpeg , https://imgur.com/wuiOM6H.jpeg , https://imgur.com/zVU1my4.jpeg , https://imgur.com/o1FG3ZC.jpeg , https://imgur.com/lWTCCyb.jpeg , https://imgur.com/bgMDBtx.jpeg | E12: =IFERROR(MINIFS('Inventario barrios'!F:F,'Inventario barrios'!D:D,TRIM(A12),'Inventario barrios'!F:F,">0"),0) -> 300000000 | F12: =IFERROR(AVERAGEIFS('Inventario barrios'!F:F,'Inventario barrios'!D:D,TRIM(A12),'Inventario barrios'!F:F,">0"),0) -> 8.0138889e+08 | G12: =IFERROR(AVERAGEIFS('Inventario barrios'!J:J,'Inventario barrios'!D:D,TRIM(A12),'Inventario barrios'!J:J,">0"),0) -> 0 | H12: =IFERROR(AVERAGEIFS('Inventario barrios'!K:K,'Inventario barrios'!D:D,TRIM(A12),'Inventario barrios'!K:K,">0"),0) -> 0 | I12: =IFERROR(AVERAGEIFS('Inventario barrios'!N:N,'Inventario barrios'!D:D,TRIM(A12),'Inventario barrios'!N:N,">0"),0) -> 4.2941176 | J12: 4
A13: Sevilla | B13: Centro de convenciones José Eustacio Rivera, Clínica UROS, Universidad CORHUILA, Supermercado Olímpica, Supermercado Metro, Panadería Peter Pan | C13: https://www.huila.gov.co/publicaciones/12480/el-centro-de-convenciones-jose-eustasio-rivera-y-el-recinto-ferial-la-voragine-epicentros-de-la-programacion-del-san-pedro/ , https://clinicauros.com/ , https://corhuila.edu.co/ , https://www.olimpica.com/nuestras-tiendas/ , https://ofertas.tiendasmetro.co/ubicaciones/ , https://peterpan24horas.com/ | D13: https://imgur.com/QoxdRse.jpeg , https://imgur.com/wuiOM6H.jpeg , https://imgur.com/zVU1my4.jpeg , https://imgur.com/o1FG3ZC.jpeg , https://imgur.com/lWTCCyb.jpeg , https://imgur.com/lx4imr6.jpeg | E13: =IFERROR(MINIFS('Inventario barrios'!F:F,'Inventario barrios'!D:D,TRIM(A13),'Inventario barrios'!F:F,">0"),0) -> 250000000 | F13: =IFERROR(AVERAGEIFS('Inventario barrios'!F:F,'Inventario barrios'!D:D,TRIM(A13),'Inventario barrios'!F:F,">0"),0) -> 6.1631579e+08 | G13: =IFERROR(AVERAGEIFS('Inventario barrios'!J:J,'Inventario barrios'!D:D,TRIM(A13),'Inventario barrios'!J:J,">0"),0) -> 0 | H13: =IFERROR(AVERAGEIFS('Inventario barrios'!K:K,'Inventario barrios'!D:D,TRIM(A13),'Inventario barrios'!K:K,">0"),0) -> 0 | I13: =IFERROR(AVERAGEIFS('Inventario barrios'!N:N,'Inventario barrios'!D:D,TRIM(A13),'Inventario barrios'!N:N,">0"),0) -> 3.7777778 | J13: 5
G36: =IF(TRIM(H18)=TRIM($A18), D18, )
G37: =IF(TRIM(H19)=TRIM($A19), D19, )
G38: =IF(TRIM(H20)=TRIM($A20), D20, )
G39: =IF(TRIM(H21)=TRIM($A21), D21, )
G40: =IF(TRIM(H22)=TRIM($A22), D22, )
G41: =IF(TRIM(H23)=TRIM($A23), D23, )

Sheet Inventario barrios
A1: =IFERROR(__xludf.DUMMYFUNCTION("FILTER('Base de Datos'!A1:BF3379, 'Base de Datos'!AH1:AH3379=""Inventario"")"),"Código") -> Código | B1: =IFERROR(__xludf.DUMMYFUNCTION("""COMPUTED_VALUE"""),"Nombre") -> Nombre | C1: =IFERROR(__xludf.DUMMYFUNCTION("""COMPUTED_VALUE"""),"Tipo de inmueble") -> Tipo de inmueble | D1: =IFERROR(__xludf.DUMMYFUNCTION("""COMPUTED_VALUE"""),"Barrio") -> Barrio | E1: =IFERROR(__xludf.DUMMYFUNCTION("""COMPUTED_VALUE"""),"Conjunto") -> Conjunto | F1: =IFERROR(__xludf.DUMMYFUNCTION("""COMPUTED_VALUE"""),"Precio") -> Precio | G1: =IFERROR(__xludf.DUMMYFUNCTION("""COMPUTED_VALUE"""),"Rango de precio") -> Rango de precio | H1: =IFERROR(__xludf.DUMMYFUNCTION("""COMPUTED_VALUE"""),"Hipoteca") -> Hipoteca | I1: =IFERROR(__xludf.DUMMYFUNCTION("""COMPUTED_VALUE"""),"Permuta") -> Permuta | J1: =IFERROR(__xludf.DUMMYFUNCTION("""COMPUTED_VALUE"""),"Zona") -> Zona | K1: =IFERROR(__xludf.DUMMYFUNCTION("""COMPUTED_VALUE"""),"Comuna") -> Comuna | L1: =IFERROR(__xludf.DUMMYFUNCTION("""COMPUTED_VALUE"""),"Habitaciones") -> Habitaciones | M1: =IFERROR(__xludf.DUMMYFUNCTION("""COMPUTED_VALUE"""),"Habitacion en 1er piso") -> Habitacion en 1er piso | N1: =IFERROR(__xludf.DUMMYFUNCTION("""COMPUTED_VALUE"""),"Baños") -> Baños | O1: =IFERROR(__xludf.DUMMYFUNCTION("""COMPUTED_VALUE"""),"Garaje") -> Garaje | P1: =IFERROR(__xludf.DUMMYFUNCTION("""COMPUTED_VALUE"""),"Pisos") -> Pisos | Q1: =IFERROR(__xludf.DUMMYFUNCTION("""COMPUTED_VALUE"""),"Área Construida") -> Área Construida | R1: =IFERROR(__xludf.DUMMYFUNCTION("""COMPUTED_VALUE"""),"Área lote") -> Área lote | S1: =IFERROR(__xludf.DUMMYFUNCTION("""COMPUTED_VALUE"""),"Rentabilidad") -> Rentabilidad | T1: =IFERROR(__xludf.DUMMYFUNCTION("""COMPUTED_VALUE"""),"Ciudad") -> Ciudad | U1: =IFERROR(__xludf.DUMMYFUNCTION("""COMPUTED_VALUE"""),"Estrato") -> Estrato | V1: =IFERROR(__xludf.DUMMYFUNCTION("""COMPUTED_VALUE"""),"Ubicación") -> Ubicación | W1: =IFERROR(__xludf.DUMMYFUNCTION("""COMPUTED_VALUE"""),"Vía") -> Vía | X1: =IFERROR(__xludf.DUMMYFUNCTION("""COMPUTED_VALUE"""),"Closet") -> Closet | Y1: =IFERROR(__xludf.DUMMYFUNCTION("""COMPUTED_VALUE"""),"Piscina") -> Piscina | Z1: =IFERROR(__xludf.DUMMYFUNCTION("""COMPUTED_VALUE"""),"Administración") -> Administración | AA1: =IFERROR(__xludf.DUMMYFUNCTION("""COMPUTED_VALUE"""),"Retorno de la Inversión") -> Retorno de la Inversión | AB1: =IFERROR(__xludf.DUMMYFUNCTION("""COMPUTED_VALUE"""),"Google Fotos") -> Google Fotos | AC1: =IFERROR(__xludf.DUMMYFUNCTION("""COMPUTED_VALUE"""),"Descripción") -> Descripción | AD1: =IFERROR(__xludf.DUMMYFUNCTION("""COMPUTED_VALUE"""),"Puntos Clave") -> Puntos Clave | AE1: =IFERROR(__xludf.DUMMYFUNCTION("""COMPUTED_VALUE"""),"Buscar") -> Buscar | AF1: =IFERROR(__xludf.DUMMYFUNCTION("""COMPUTED_VALUE"""),"Cocina") -> Cocina | AG1: =IFERROR(__xludf.DUMMYFUNCTION("""COMPUTED_VALUE"""),"Publicar") -> Publicar | AH1: =IFERROR(__xludf.DUMMYFUNCTION("""COMPUTED_VALUE"""),"Inventario") -> Inventario | AI1: =IFERROR(__xludf.DUMMYFUNCTION("""COMPUTED_VALUE"""),"Contrato") -> Contrato | AJ1: =IFERROR(__xludf.DUMMYFUNCTION("""COMPUTED_VALUE"""),"Inmobiliaria") -> Inmobiliaria | AK1: =IFERROR(__xludf.DUMMYFUNCTION("""COMPUTED_VALUE"""),"Estado del contrato Firmados - para imprimir - sin contrato") -> Estado del contrato Firmados - para imprimir - sin contrato | AL1: =IFERROR(__xludf.DUMMYFUNCTION("""COMPUTED_VALUE"""),"TIENE FOTOS - CODIGOS DISPONIBLES-NO TIENE FOTOS-NUEVOS ULTIMOS BARRIDOS - FIRMO CONTRATO ICDE") -> TIENE FOTOS - CODIGOS DISPONIBLES-NO TIENE FOTOS-NUEVOS ULTIMOS BARRIDOS - FIRMO CONTRATO ICDE | AM1: =IFERROR(__xludf.DUMMYFUNCTION("""COMPUTED_VALUE"""),"CELULAR") -> CELULAR | AN1: =IFERROR(__xludf.DUMMYFUNCTION("""COMPUTED_VALUE"""),"CELULAR 2") -> CELULAR 2 | AO1: =IFERROR(__xludf.DUMMYFUNCTION("""COMPUTED_VALUE"""),"PROPIETARIO") -> PROPIETARIO | AP1: =IFERROR(__xludf.DUMMYFUNCTION("""COMPUTED_VALUE"""),"DIRECCIÓN") -> DIRECCIÓN | AQ1: =IFERROR(__xludf.DUMMYFUNCTION("""COMPUTED_VALUE"""),"LATITUD") -> LATITUD | AR1: =IFERROR(__xludf.DUMMYFUNCTION("""COMPUTED_VALUE"""),"LONGITUD") -> LONGITUD | AS1: =IFERROR(__xludf.DUMMYFUNCTION("""COMPUTED_VALUE"""),"RENTAB.") -> RENTAB. | AT1: =IFERROR(__xludf.DUMMYFUNCTION("""COMPUTED_VALUE"""),"ASCENSOR") -> ASCENSOR | AU1: =IFERROR(__xludf.DUMMYFUNCTION("""COMPUTED_VALUE"""),"CORTINAS") -> CORTINAS | AV1: =IFERROR(__xludf.DUMMYFUNCTION("""COMPUTED_VALUE"""),"AIRE ACONDICIONADO") -> AIRE ACONDICIONADO | AW1: =IFERROR(__xludf.DUMMYFUNCTION("""COMPUTED_VALUE"""),"REJA/ ANTEJARDIN") -> REJA/ ANTEJARDIN | AX1: =IFERROR(__xludf.DUMMYFUNCTION("""COMPUTED_VALUE"""),"ANTIGÜEDAD") -> ANTIGÜEDAD | AY1: =IFERROR(__xludf.DUMMYFUNCTION("""COMPUTED_VALUE"""),"PATIO") -> PATIO | AZ1: =IFERROR(__xludf.DUMMYFUNCTION("""COMPUTED_VALUE"""),"DIMENSIONES") -> DIMENSIONES | BC1: =IFERROR(__xludf.DUMMYFUNCTION("""COMPUTED_VALUE"""),"LEADS ASIGNADOS") -> LEADS ASIGNADOS | BD1: =IFERROR(__xludf.DUMMYFUNCTION("""COMPUTED_VALUE"""),"g0f") -> g0f | BE1: =IFERROR(__xludf.DUMMYFUNCTION("""COMPUTED_VALUE"""),"PROPUESTAS SUGERIDAS POR IA") -> PROPUESTAS SUGERIDAS POR IA | BF1: =IFERROR(__xludf.DUMMYFUNCTION("""COMPUTED_VALUE"""),"Imagenes") -> Imagenes
A2: =IFERROR(__xludf.DUMMYFUNCTION("""COMPUTED_VALUE"""),"7064") -> 7064 | B2: =IFERROR(__xludf.DUMMYFUNCTION("""COMPUTED_VALUE"""),"Casa en barrio La Toma") -> Casa en barrio La Toma | C2: =IFERROR(__xludf.DUMMYFUNCTION("""COMPUTED_VALUE"""),"Casa") -> Casa | D2: =IFERROR(__xludf.DUMMYFUNCTION("""COMPUTED_VALUE"""),"La Toma") -> La Toma | F2: =IFERROR(__xludf.DUMMYFUNCTION("""COMPUTED_VALUE"""),2.5E8) -> 250000000 | G2: =IFERROR(__xludf.DUMMYFUNCTION("""COMPUTED_VALUE"""),"$200'000.000 a $300'000.000") -> $200'000.000 a $300'000.000 | J2: =IFERROR(__xludf.DUMMYFUNCTION("""COMPUTED_VALUE"""),"Centro") -> Centro | K2: =IFERROR(__xludf.DUMMYFUNCTION("""COMPUTED_VALUE"""),"3") -> 3 | L2: =IFERROR(__xludf.DUMMYFUNCTION("""COMPUTED_VALUE"""),4.0) -> 4 | N2: =IFERROR(__xludf.DUMMYFUNCTION("""COMPUTED_VALUE"""),2.0) -> 2 | O2: =IFERROR(__xludf.DUMMYFUNCTION("""COMPUTED_VALUE"""),0.0) -> 0 | P2: =IFERROR(__xludf.DUMMYFUNCTION("""COMPUTED_VALUE"""),1.0) -> 1 | Q2: =IFERROR(__xludf.DUMMYFUNCTION("""COMPUTED_VALUE"""),117.0) -> 117 | R2: =IFERROR(__xludf.DUMMYFUNCTION("""COMPUTED_VALUE"""),146.0) -> 146 | S2: =IFERROR(__xludf.DUMMYFUNCTION("""COMPUTED_VALUE"""),"Rentabilidad $950,000") -> Rentabilidad $950,000 | T2: =IFERROR(__xludf.DUMMYFUNCTION("""COMPUTED_VALUE"""),"Neiva") -> Neiva | U2: =IFERROR(__xludf.DUMMYFUNCTION("""COMPUTED_VALUE"""),"3") -> 3 | V2: =IFERROR(__xludf.DUMMYFUNCTION("""COMPUTED_VALUE"""),"Medianera") -> Medianera | X2: =IFERROR(__xludf.DUMMYFUNCTION("""COMPUTED_VALUE"""),0.0) -> 0 | Y2: =IFERROR(__xludf.DUMMYFUNCTION("""COMPUTED_VALUE"""),"No tiene") -> No tiene | Z2: =IFERROR(__xludf.DUMMYFUNCTION("""COMPUTED_VALUE"""),"No aplica") -> No aplica | AA2: =IFERROR(__xludf.DUMMYFUNCTION("""COMPUTED_VALUE"""),"22 años") -> 22 años | AF2: =IFERROR(__xludf.DUMMYFUNCTION("""COMPUTED_VALUE"""),"básica") -> básica | AH2: =IFERROR(__xludf.DUMMYFUNCTION("""COMPUTED_VALUE"""),"Inventario") -> Inventario | AJ2: =IFERROR(__xludf.DUMMYFUNCTION("""COMPUTED_VALUE""")," F/$250") -> F/$250 | AK2: =IFERROR(__xludf.DUMMYFUNCTION("""COMPUTED_VALUE"""),"No aplica") -> No aplica | AL2: =IFERROR(__xludf.DUMMYFUNCTION("""COMPUTED_VALUE"""),"NO FOTOS + DESCRIPCION") -> NO FOTOS + DESCRIPCION | AM2: =IFERROR(__xludf.DUMMYFUNCTION("""COMPUTED_VALUE"""),3.183955563E9) -> 3183955563 | AP2: =IFERROR(__xludf.DUMMYFUNCTION("""COMPUTED_VALUE"""),"CARRERA 7 A No. 13 - 20") -> CARRERA 7 A No. 13 - 20 | AS2: =IFERROR(__xludf.DUMMYFUNCTION("""COMPUTED_VALUE"""),950000.0) -> 950000 | AT2: =IFERROR(__xludf.DUMMYFUNCTION("""COMPUTED_VALUE"""),0.0) -> 0 | AU2: =IFERROR(__xludf.DUMMYFUNCTION("""COMPUTED_VALUE"""),0.0) -> 0 | AV2: =IFERROR(__xludf.DUMMYFUNCTION("""COMPUTED_VALUE"""),0.0) -> 0 | AW2: =IFERROR(__xludf.DUMMYFUNCTION("""COMPUTED_VALUE"""),"NO") -> NO | AX2: =IFERROR(__xludf.DUMMYFUNCTION("""COMPUTED_VALUE"""),0.0) -> 0 | AY2: =IFERROR(__xludf.DUMMYFUNCTION("""COMPUTED_VALUE"""),0.0) -> 0 | AZ2: =IFERROR(__xludf.DUMMYFUNCTION("""COMPUTED_VALUE"""),0.0) -> 0 | BA2: =IFERROR(__xludf.DUMMYFUNCTION("""COMPUTED_VALUE"""),"X") -> X | BB2: =IFERROR(__xludf.DUMMYFUNCTION("""COMPUTED_VALUE"""),0.0) -> 0 | BC2: =IFERROR(__xludf.DUMMYFUNCTION("""COMPUTED_VALUE"""),"20 - SAMADHI RODRIGUEZ") -> 20 - SAMADHI RODRIGUEZ
A3: =IFERROR(__xludf.DUMMYFUNCTION("""COMPUTED_VALUE"""),"3084") -> 3084 | B3: =IFERROR(__xludf.DUMMYFUNCTION("""COMPUTED_VALUE"""),"Casa en barrio Campo Nuñez") -> Casa en barrio Campo Nuñez | C3: =IFERROR(__xludf.DUMMYFUNCTION("""COMPUTED_VALUE"""),"Casa") -> Casa | D3: =IFERROR(__xludf.DUMMYFUNCTION("""COMPUTED_VALUE"""),"Campo Nuñez") -> Campo Nuñez | F3: =IFERROR(__xludf.DUMMYFUNCTION("""COMPUTED_VALUE"""),7.0E8) -> 700000000 | G3: =IFERROR(__xludf.DUMMYFUNCTION("""COMPUTED_VALUE"""),"$500'000.000 a $1.000'000.000") -> $500'000.000 a $1.000'000.000 | J3: =IFERROR(__xludf.DUMMYFUNCTION("""COMPUTED_VALUE"""),"Centro") -> Centro | K3: =IFERROR(__xludf.DUMMYFUNCTION("""COMPUTED_VALUE"""),"3") -> 3 | L3: =IFERROR(__xludf.DUMMYFUNCTION("""COMPUTED_VALUE"""),4.0) -> 4 | N3: =IFERROR(__xludf.DUMMYFUNCTION("""COMPUTED_VALUE"""),3.0) -> 3 | O3: =IFERROR(__xludf.DUMMYFUNCTION("""COMPUTED_VALUE"""),1.0) -> 1 | P3: =IFERROR(__xludf.DUMMYFUNCTION("""COMPUTED_VALUE"""),1.0) -> 1 | Q3: =IFERROR(__xludf.DUMMYFUNCTION("""COMPUTED_VALUE"""),210.0) -> 210 | R3: =IFERROR(__xludf.DUMMYFUNCTION("""COMPUTED_VALUE"""),210.0) -> 210 | S3: =IFERROR(__xludf.DUMMYFUNCTION("""COMPUTED_VALUE""")," ") | T3: =IFERROR(__xludf.DUMMYFUNCTION("""COMPUTED_VALUE"""),"Neiva") -> Neiva | U3: =IFERROR(__xludf.DUMMYFUNCTION("""COMPUTED_VALUE"""),"4") -> 4 | V3: =IFERROR(__xludf.DUMMYFUNCTION("""COMPUTED_VALUE"""),"Medianera") -> Medianera | X3: =IFERROR(__xludf.DUMMYFUNCTION("""COMPUTED_VALUE"""),4.0) -> 4 | Y3: =IFERROR(__xludf.DUMMYFUNCTION("""COMPUTED_VALUE"""),"No tiene") -> No tiene | Z3: =IFERROR(__xludf.DUMMYFUNCTION("""COMPUTED_VALUE"""),"No aplica") -> No aplica | AA3: =IFERROR(__xludf.DUMMYFUNCTION("""COMPUTED_VALUE"""),"No aplica") -> No aplica | AB3: =IFERROR(__xludf.DUMMYFUNCTION("""COMPUTED_VALUE"""),"https://photos.app.goo.gl/zwhNZsro4YC2YDY28") -> https://photos.app.goo.gl/zwhNZsro4YC2YDY28 | AF3: =IFERROR(__xludf.DUMMYFUNCTION("""COMPUTED_VALUE"""),"semi-integral") -> semi-integral | AH3: =IFERROR(__xludf.DUMMYFUNCTION("""COMPUTED_VALUE"""),"Inventario") -> Inventario | AJ3: =IFERROR(__xludf.DUMMYFUNCTION("""COMPUTED_VALUE"""),"B-Inventario Campo Nuñez") -> B-Inventario Campo Nuñez | AL3: =IFERROR(__xludf.DUMMYFUNCTION("""COMPUTED_VALUE"""),"TIENE FOTOS") -> TIENE FOTOS | AM3: =IFERROR(__xludf.DUMMYFUNCTION("""COMPUTED_VALUE"""),3.212323681E9) -> 3212323681 | AN3: =IFERROR(__xludf.DUMMYFUNCTION("""COMPUTED_VALUE"""),3.135781638E9) -> 3135781638 | AP3: =IFERROR(__xludf.DUMMYFUNCTION("""COMPUTED_VALUE"""),"CARRERA 7A NO. 16-30") -> CARRERA 7A NO. 16-30 | AS3: =IFERROR(__xludf.DUMMYFUNCTION("""COMPUTED_VALUE"""),0.0) -> 0 | AT3: =IFERROR(__xludf.DUMMYFUNCTION("""COMPUTED_VALUE"""),0.0) -> 0 | AU3: =IFERROR(__xludf.DUMMYFUNCTION("""COMPUTED_VALUE"""),0.0) -> 0 | AV3: =IFERROR(__xludf.DUMMYFUNCTION("""COMPUTED_VALUE"""),0.0) -> 0 | AW3: =IFERROR(__xludf.DUMMYFUNCTION("""COMPUTED_VALUE"""),"NO") -> NO | AX3: =IFERROR(__xludf.DUMMYFUNCTION("""COMPUTED_VALUE"""),0.0) -> 0 | AY3: =IFERROR(__xludf.DUMMYFUNCTION("""COMPUTED_VALUE"""),0.0) -> 0 | AZ3: =IFERROR(__xludf.DUMMYFUNCTION("""COMPUTED_VALUE"""),0.0) -> 0 | BA3: =IFERROR(__xludf.DUMMYFUNCTION("""COMPUTED_VALUE"""),"X") -> X | BB3: =IFERROR(__xludf.DUMMYFUNCTION("""COMPUTED_VALUE"""),0.0) -> 0 | BF3: =IFERROR(__xludf.DUMMYFUNCTION("""COMPUTED_VALUE"""),"https://lh3.googleusercontent.com/pw/AP1GczM_q4YkeTMYSuUBWqqYdzZYkAC3FlC98d-y3b-Dx0lH7xec5m3GKCiMT3HyIGewfaeqjPMlkcPCbqyf9DOisePdzXfQ0uGd63iytM9TyJhAC4OhHWsI=w1200|https://lh3.googleusercontent.com/pw/AP1GczObcfnIuRHJEzsPXoEx4-mxe1p0-lcx2AALgAFjDcsd1siefk"&"9XT0EJ_WGP2t-ZwTXBN1E0rdsKqe3UK_7UOLqNLNNyeyCozcj1rChnQVOPNfPPvmZc=w1200|https://lh3.googleusercontent.com/pw/AP1GczNwECtrsa10y7rYCW7TPXNTwuig3Hu2iT9oQd34hd7PLreqOwQXOjz5HmVU2rr8h1XJfzONC8G_UPS4rALEMJOVKh3J-CBjj57LqRpOB95lNZTUQS87=w1200|https://lh3.google"&"usercontent.com/pw/AP1GczNKlgzMJuRgq68zknZTaklmxyVzawGcGGo8LqkqkncShaAPtO5MqLAyLJkrEqRSDnZ3Yt_c3z7NT5PIc1jMtb_T0lyKnrHW_ECk_cltmYbUZpVtWHow=w1200|https://lh3.googleusercontent.com/pw/AP1GczMdrPdD7s1bwof_7j0nRdJPKOEO_9KsDtHFMytNWX1eUYm_20huVfmW2l5CnWQVjYJo"&"yvQPSBN7ldIXkcuUOdiI64rj1WjhHJyIWR7JmtY8C_UCDSCQ=w1200|https://lh3.googleusercontent.com/pw/AP1GczOdAw75Pq4jnUqYpjqGoCI6Cram8907QZSDG175wPpYKIpYV-AvPYhmhMPpHs9ydM7DirObUReMJcXHb82kHOjGhKaZn5mvaKz5OTB-Vq9F9XKL11oy=w1200|https://lh3.googleusercontent.com/pw"&"/AP1GczN-cAD5LXmcicIOsdS1CPjvkCu1BopVQDyva-DehdTRxLyVNlGzrMOooj1wed2kwGxsm06zDPrNmqB9hTnqGzITQOArzi7whyJYF1matwc9zRf-9dH_=w1200|https://lh3.googleusercontent.com/pw/AP1GczNM_VjlEnV_fZCEWBs5qKgQqyzl54gqE5y8cbIYJkPYGqC05ul8D4YKwwOOxAtCzXTHgPRJy0Ie5tYMWJpjHr"&"SBJAg2PfRF5oHhfi2AeXXbixY4zSE7=w1200|https://lh3.googleusercontent.com/pw/AP1GczOozep_ElfpR77cAt2x2VNC6V0pIvCEaN0NRf18Q6NgXEfrUaGNFdVNefXu0GD7fA1lkuLK9o03-saz8IZeYe0PpL3niUR27EzF5jRx5KPq_8TevjHx=w1200|https://lh3.googleusercontent.com/pw/AP1GczM9ZLiKiO4fH"&"LZgea-iXR_KLPYulpe82VX6ZUZiHXiVLVvkp2BUb7jdbDAZYwz5zXS2ETgA-CmaVahxAd3HPcZe0By9lCLvippFZPs7VtQEUOVcRknO=w1200|https://lh3.googleusercontent.com/pw/AP1GczMu9dpvklZNNCDR3D0VItJFrW79NYF5upGnvOHJ5tkXRWmkGF9uwWFIV3lp9xKl6VSe7sR7Fpp21-pIYcoyyGYmQgtKF7N6vb3YXOJ4"&"mdfvSO18CghG=w1200|https://lh3.googleusercontent.com/pw/AP1GczPgb1Tbbxnqbi9-MiryvQ_45vxSnucSLN-EZpx1IzJsHjALiOlsTahw5w8oCshTCFLxK7Oar5k7mZaYVvXRmfQlZN2Horrs39uSMV3MLA--C101qHvC=w1200|https://lh3.googleusercontent.com/pw/AP1GczM9HE6nqOX2z3taUL-lXsItMNPj1PU"&"R6EbIHrPNK1RKxArKCi_yaX0zwpka7BWP3cJNGbk6wcBAB20Wwa5ynfuHs96j_vG9hLLQvo1r3_SOSKiZliML=w1200|https://lh3.googleusercontent.com/pw/AP1GczOofwiF-WFaC_9dWjhQtiUAKY_s8Uj1kuE9R5hqWc5l6aU2sEqDhOvL9vEhMWJfQgCUGzPEXVMFzcxFUjehtK7qeYemr5ECjIIDg7lSTb0tvfpT77vd=w1200"&"|https://lh3.googleusercontent.com/pw/AP1GczMxybDpjdsGE9lTGj1SC6_HBx8wASok0kRN2Mh8KT3CujwqTQsgUAXgv8S-XBHjwr2LYLWK2zvK-bD0ugxNxr8KQLD0YDqJdprZuXafGFuX_szQz4b9=w1200|https://lh3.googleusercontent.com/pw/AP1GczM4fNGtZ5skDT6kCIkR0ETNb7LG75DoAFlHP3Ki5CB7iaSGy"&"w5nN5LhaL2wXBnZ8VpGh9KHDXxUfPFR0oDdNDkVcyClcJ0ANPYECcD-_srowcDS-x80=w1200|https://lh3.googleusercontent.com/pw/AP1GczOeyzjIvWQl4Kh9tRuABHpSryYyQGLgL4Rkc5MRZ0VuhacnqqQ0gqF_6z6iOJvZyQwdEPmJ7kUy-_6UgjKAsBn1HKCD6mRh449Wd2T5zWHq08So3y9l=w1200|https://lh3.googl"&"eusercontent.com/pw/AP1GczPdT3tAmx7u0kTbY3JSvEzr4iLC2p9pky68ZTg1s4wwE9A03Koi7VLAiGmkTZVfYEXN_M6uVMxOpBikinflS9WFGaewR_josBtOyRnpY_9NMv5lmAx8=w1200|https://lh3.googleusercontent.com/pw/AP1GczMINMau5TM_f0_KXnV_4TWUU2lpYvgTczVrcTt5AYx-BJ-qJi_CPiI2kwVUdcXxMeB"&"0mCsT3K20ufY5TA4uFVj-yUruLvL9M24Gv4MgKkaO_0pUfxRP=w1200|https://lh3.googleusercontent.com/pw/AP1GczMu2kUh8u1pjOGGa1sCN7UM-GERUZxc9XAqpSSl09A4jMk5R7BoHWOF_VRYyNrJkrQzfSUk--fRwH1R3YkXxqrd7n4WiIKHeK0riX9CTB6Zg4lSSQf4=w1200|https://lh3.googleusercontent.com/p"&"w/AP1GczOca9e-Z7erZR73ga76_rnzoHcFYlPXhbnNtzDWud0oPMdJEQoxj-KZ1o7LlaFHJtX4jQL1H4FTwy3GQ_ChvdsARR-cpDTPLxbRmvgzO0ck-r1oJb77=w1200|https://lh3.googleusercontent.com/pw/AP1GczOoqcTA7Elg-8HYseVZ5V2z8FMJ4jv4UhV9Kh7Ci_8fQNlDCnD3DpKVF2nmexRq1lqCaSrJkJxNgSfVKzf1B"&"ucpve-cWbDySSUhYCVSgXgcRi2gk4ou=w1200|https://lh3.googleusercontent.com/pw/AP1GczOZyikEqhxenI-O0LmST7RMv_Wzw4g41Vf5Xpktl2zuGpyD_YpZGKfTqn3C63J1zL9oehpYgCQmc_Ry_iEhY1TYqofw6tha2EjndNFtaNSyJM4wjYWp=w1200|https://lh3.googleusercontent.com/pw/AP1GczO36Zy1EHB-"&"O1SvGcI50nz6BYJ70mVZ00hDk2Qm1dosPu4cOdzucLOPq1vtwwgBUcwKLDSb4OBAz-3xsYfZx1wllPxof0lehos40gM-ehM3SdfaVzeT=w1200|https://lh3.googleusercontent.com/pw/AP1GczNtKyAm_fQx_WJhVw-kMk1_q5912KxhSiW6pQfmyWh7HInIURo0aWuFhabc8cMEVoCuORI3gaaL9aPAT6zWcNCsTeKoLq0TNIyeAJH"&"d__Q0yDSG7Kg3=w1200") -> https://lh3.googleusercontent.com/pw/AP1GczM_q4YkeTMYSuUBWqqYdzZYkAC3FlC98d-y3b-Dx0lH7xec5m3GKCiMT3HyIGewfaeqjPMlkcPCbqyf9DOisePdzXfQ0uGd63iytM9TyJhAC4OhHWsI=w1200|https://lh3.googleusercontent.com/pw/AP1GczObcfnIuRHJEzsPXoEx4-mxe1p0-lcx2AALgAFjDcsd1siefk9XT0EJ_WGP2t-ZwTXBN1E0rdsKqe3UK_7UOLqNLNNyeyCozcj1rChnQVOPNfPPvmZc=w1200|https://lh3.googleusercontent.com/pw/AP1GczNwECtrsa10y7rYCW7TPXNTwuig3Hu2iT9oQd34hd7PLreqOwQXOjz5HmVU2rr8h1XJfzONC8G_UPS4rALEMJOVKh3J-CBjj57LqRpOB95lNZTUQS87=w1200|https://lh3.googleusercontent.com/pw/AP1GczNKlgzMJuRgq68zknZTaklmxyVzawGcGGo8LqkqkncShaAPtO5MqLAyLJkrEqRSDnZ3Yt_c3z7NT5PIc1jMtb_T0lyKnrHW_ECk_cltmYbUZpVtWHow=w1200|https://lh3.googleusercontent.com/pw/AP1GczMdrPdD7s1bwof_7j0nRdJPKOEO_9KsDtHFMytNWX1eUYm_20huVfmW2l5CnWQVjYJoyvQPSBN7ldIXkcuUOdiI64rj1WjhHJyIWR7JmtY8C_UCDSCQ=w1200|https://lh3.googleusercontent.com/pw/AP1GczOdAw75Pq4jnUqYpjqGoCI6Cram8907QZSDG175wPpYKIpYV-AvPYhmhMPpHs9ydM7DirObUReMJcXHb82kHOjGhKaZn5mvaKz5OTB-Vq9F9XKL11oy=w1200|https://lh3.googleusercontent.com/pw/AP1GczN-cAD5LXmcicIOsdS1CPjvkCu1BopVQDyva-DehdTRxLyVNlGzrMOooj1wed2kwGxsm06zDPrNmqB9hTnqGzITQOArzi7whyJYF1matwc9zRf-9dH_=w1200|https://lh3.googleusercontent.com/pw/AP1GczNM_VjlEnV_fZCEWBs5qKgQqyzl54gqE5y8cbIYJkPYGqC05ul8D4YKwwOOxAtCzXTHgPRJy0Ie5tYMWJpjHrSBJAg2PfRF5oHhfi2AeXXbixY4zSE7=w1200|https://lh3.googleusercontent.com/pw/AP1GczOozep_ElfpR77cAt2x2VNC6V0pIvCEaN0NRf18Q6NgXEfrUaGNFdVNefXu0GD7fA1lkuLK9o03-saz8IZeYe0PpL3niUR27EzF5jRx5KPq_8TevjHx=w1200|https://lh3.googleusercontent.com/pw/AP1GczM9ZLiKiO4fHLZgea-iXR_KLPYulpe82VX6ZUZiHXiVLVvkp2BUb7jdbDAZYwz5zXS2ETgA-CmaVahxAd3HPcZe0By9lCLvippFZPs7VtQEUOVcRknO=w1200|https://lh3.googleusercontent.com/pw/AP1GczMu9dpvklZNNCDR3D0VItJFrW79NYF5upGnvOHJ5tkXRWmkGF9uwWFIV3lp9xKl6VSe7sR7Fpp21-pIYcoyyGYmQgtKF7N6vb3YXOJ4mdfvSO18CghG=w1200|https://lh3.googleusercontent.com/pw/AP1GczPgb1Tbbxnqbi9-MiryvQ_45vxSnucSLN-EZpx1IzJsHjALiOlsTahw5w8oCshTCFLxK7Oar5k7mZaYVvXRmfQlZN2Horrs39uSMV3MLA--C101qHvC=w1200|https://lh3.googleusercontent.com/pw/AP1GczM9HE6nqOX2z3taUL-lXsItMNPj1PUR6EbIHrPNK1RKxArKCi_yaX0zwpka7BWP3cJNGbk6wcBAB20Wwa5ynfuHs96j_vG9hLLQvo1r3_SOSKiZliML=w1200|https://lh3.googleusercontent.com/pw/AP1GczOofwiF-WFaC_9dWjhQtiUAKY_s8Uj1kuE9R5hqWc5l6aU2sEqDhOvL9vEhMWJfQgCUGzPEXVMFzcxFUjehtK7qeYemr5ECjIIDg7lSTb0tvfpT77vd=w1200|https://lh3.googleusercontent.com/pw/AP1GczMxybDpjdsGE9lTGj1SC6_HBx8wASok0kRN2Mh8KT3CujwqTQsgUAXgv8S-XBHjwr2LYLWK2zvK-bD0ugxNxr8KQLD0YDqJdprZuXafGFuX_szQz4b9=w1200|https://lh3.googleusercontent.com/pw/AP1GczM4fNGtZ5skDT6kCIkR0ETNb7LG75DoAFlHP3Ki5CB7iaSGyw5nN5LhaL2wXBnZ8VpGh9KHDXxUfPFR0oDdNDkVcyClcJ0ANPYECcD-_srowcDS-x80=w1200|https://lh3.googleusercontent.com/pw/AP1GczOeyzjIvWQl4Kh9tRuABHpSryYyQGLgL4Rkc5MRZ0VuhacnqqQ0gqF_6z6iOJvZyQwdEPmJ7kUy-_6UgjKAsBn1HKCD6mRh449Wd2T5zWHq08So3y9l=w1200|https://lh3.googleusercontent.com/pw/AP1GczPdT3tAmx7u0kTbY3JSvEzr4iLC2p9pky68ZTg1s4wwE9A03Koi7VLAiGmkTZVfYEXN_M6uVMxOpBikinflS9WFGaewR_josBtOyRnpY_9NMv5lmAx8=w1200|https://lh3.googleusercontent.com/pw/AP1GczMINMau5TM_f0_KXnV_4TWUU2lpYvgTczVrcTt5AYx-BJ-qJi_CPiI2kwVUdcXxMeB0mCsT3K20ufY5TA4uFVj-yUruLvL9M24Gv4MgKkaO_0pUfxRP=w1200|https://lh3.googleusercontent.com/pw/AP1GczMu2kUh8u1pjOGGa1sCN7UM-GERUZxc9XAqpSSl09A4jMk5R7BoHWOF_VRYyNrJkrQzfSUk--fRwH1R3YkXxqrd7n4WiIKHeK0riX9CTB6Zg4lSSQf4=w1200|https://lh3.googleusercontent.com/pw/AP1GczOca9e-Z7erZR73ga76_rnzoHcFYlPXhbnNtzDWud0oPMdJEQoxj-KZ1o7LlaFHJtX4jQL1H4FTwy3GQ_ChvdsARR-cpDTPLxbRmvgzO0ck-r1oJb77=w1200|https://lh3.googleusercontent.com/pw/AP1GczOoqcTA7Elg-8HYseVZ5V2z8FMJ4jv4UhV9Kh7Ci_8fQNlDCnD3DpKVF2nmexRq1lqCaSrJkJxNgSfVKzf1Bucpve-cWbDySSUhYCVSgXgcRi2gk4ou=w1200|https://lh3.googleusercontent.com/pw/AP1GczOZyikEqhxenI-O0LmST7RMv_Wzw4g41Vf5Xpktl2zuGpyD_YpZGKfTqn3C63J1zL9oehpYgCQmc_Ry_iEhY1TYqofw6tha2EjndNFtaNSyJM4wjYWp=w1200|https://lh3.googleusercontent.com/pw/AP1GczO36Zy1EHB-O1SvGcI50nz6BYJ70mVZ00hDk2Qm1dosPu4cOdzucLOPq1vtwwgBUcwKLDSb4OBAz-3xsYfZx1wllPxof0lehos40gM-ehM3SdfaVzeT=w1200|https://lh3.googleusercontent.com/pw/AP1GczNtKyAm_fQx_WJhVw-kMk1_q5912KxhSiW6pQfmyWh7HInIURo0aWuFhabc8cMEVoCuORI3gaaL9aPAT6zWcNCsTeKoLq0TNIyeAJHd__Q0yDSG7Kg3=w1200
A4: =IFERROR(__xludf.DUMMYFUNCTION("""COMPUTED_VALUE"""),"2025") -> 2025 | B4: =IFERROR(__xludf.DUMMYFUNCTION("""COMPUTED_VALUE"""),"Casa en barrio Los Cámbulos II") -> Casa en barrio Los Cámbulos II | C4: =IFERROR(__xludf.DUMMYFUNCTION("""COMPUTED_VALUE"""),"Casa") -> Casa | D4: =IFERROR(__xludf.DUMMYFUNCTION("""COMPUTED_VALUE"""),"Los Cámbulos II") -> Los Cámbulos II | E4: =IFERROR(__xludf.DUMMYFUNCTION("""COMPUTED_VALUE""")," ") | F4: =IFERROR(__xludf.DUMMYFUNCTION("""COMPUTED_VALUE"""),3.0E8) -> 300000000 | G4: =IFERROR(__xludf.DUMMYFUNCTION("""COMPUTED_VALUE"""),"$300'000.000 a $400'000.000") -> $300'000.000 a $400'000.000 | J4: =IFERROR(__xludf.DUMMYFUNCTION("""COMPUTED_VALUE"""),"Norte") -> Norte | K4: =IFERROR(__xludf.DUMMYFUNCTION("""COMPUTED_VALUE"""),"2") -> 2 | L4: =IFERROR(__xludf.DUMMYFUNCTION("""COMPUTED_VALUE"""),6.0) -> 6 | N4: =IFERROR(__xludf.DUMMYFUNCTION("""COMPUTED_VALUE"""),2.0) -> 2 | O4: =IFERROR(__xludf.DUMMYFUNCTION("""COMPUTED_VALUE"""),1.0) -> 1 | P4: =IFERROR(__xludf.DUMMYFUNCTION("""COMPUTED_VALUE"""),2.0) -> 2 | Q4: =IFERROR(__xludf.DUMMYFUNCTION("""COMPUTED_VALUE"""),140.0) -> 140 | R4: =IFERROR(__xludf.DUMMYFUNCTION("""COMPUTED_VALUE"""),90.0) -> 90 | S4: =IFERROR(__xludf.DUMMYFUNCTION("""COMPUTED_VALUE""")," ") | T4: =IFERROR(__xludf.DUMMYFUNCTION("""COMPUTED_VALUE"""),"Neiva") -> Neiva | U4: =IFERROR(__xludf.DUMMYFUNCTION("""COMPUTED_VALUE"""),"3") -> 3 | V4: =IFERROR(__xludf.DUMMYFUNCTION("""COMPUTED_VALUE"""),"Medianera") -> Medianera | X4: =IFERROR(__xludf.DUMMYFUNCTION("""COMPUTED_VALUE"""),4.0) -> 4 | Y4: =IFERROR(__xludf.DUMMYFUNCTION("""COMPUTED_VALUE"""),"No tiene") -> No tiene | Z4: =IFERROR(__xludf.DUMMYFUNCTION("""COMPUTED_VALUE"""),"No aplica") -> No aplica | AA4: =IFERROR(__xludf.DUMMYFUNCTION("""COMPUTED_VALUE"""),"No aplica") -> No aplica | AB4: =IFERROR(__xludf.DUMMYFUNCTION("""COMPUTED_VALUE"""),"https://photos.app.goo.gl/5fGWK8Q6FdVAQXw98") -> https://photos.app.goo.gl/5fGWK8Q6FdVAQXw98 | AF4: =IFERROR(__xludf.DUMMYFUNCTION("""COMPUTED_VALUE"""),"semi-integral") -> semi-integral | AH4: =IFERROR(__xludf.DUMMYFUNCTION("""COMPUTED_VALUE"""),"Inventario") -> Inventario | AJ4: =IFERROR(__xludf.DUMMYFUNCTION("""COMPUTED_VALUE"""),"B-Inventario Los Cambulos II") -> B-Inventario Los Cambulos II | AL4: =IFERROR(__xludf.DUMMYFUNCTION("""COMPUTED_VALUE"""),"TIENE FOTOS") -> TIENE FOTOS | AM4: =IFERROR(__xludf.DUMMYFUNCTION("""COMPUTED_VALUE"""),3.212323681E9) -> 3212323681 | AN4: =IFERROR(__xludf.DUMMYFUNCTION("""COMPUTED_VALUE"""),3.135781638E9) -> 3135781638 | AP4: =IFERROR(__xludf.DUMMYFUNCTION("""COMPUTED_VALUE"""),"Carrera 12 # 33-24") -> Carrera 12 # 33-24 | AS4: =IFERROR(__xludf.DUMMYFUNCTION("""COMPUTED_VALUE"""),0.0) -> 0 | AT4: =IFERROR(__xludf.DUMMYFUNCTION("""COMPUTED_VALUE"""),0.0) -> 0 | AU4: =IFERROR(__xludf.DUMMYFUNCTION("""COMPUTED_VALUE"""),0.0) -> 0 | AV4: =IFERROR(__xludf.DUMMYFUNCTION("""COMPUTED_VALUE"""),0.0) -> 0 | AW4: =IFERROR(__xludf.DUMMYFUNCTION("""COMPUTED_VALUE"""),"NO") -> NO | AX4: =IFERROR(__xludf.DUMMYFUNCTION("""COMPUTED_VALUE"""),0.0) -> 0 | AY4: =IFERROR(__xludf.DUMMYFUNCTION("""COMPUTED_VALUE"""),0.0) -> 0 | AZ4: =IFERROR(__xludf.DUMMYFUNCTION("""COMPUTED_VALUE"""),6.0) -> 6 | BA4: =IFERROR(__xludf.DUMMYFUNCTION("""COMPUTED_VALUE"""),"X") -> X | BB4: =IFERROR(__xludf.DUMMYFUNCTION("""COMPUTED_VALUE"""),15.0) -> 15 | BC4: =IFERROR(__xludf.DUMMYFUNCTION("""COMPUTED_VALUE"""),"8 - ERNESTO POLANCO, 9 - ALBEIRO TOVAR") -> 8 - ERNESTO POLANCO, 9 - ALBEIRO TOVAR | BF4: =IFERROR(__xludf.DUMMYFUNCTION("""COMPUTED_VALUE"""),"https://lh3.googleusercontent.com/pw/AP1GczNiJ2WTMAT7mE7Vvqt81Bwzfk6FVv9tlijaYncZFHZYNHmwlHmb5HXAzBgCtiBLWoRNqJLrfBEAGtGC5CpQFJTxOfggFexN_mCIasqxrTumVvFn6gPO=w1200|https://lh3.googleusercontent.com/pw/AP1GczMoTaZSPGlIilMcMBR67uSopPBxjCVXWyrNfJ2--8roH3txtT"&"JZQLSBIPlidqR7L4cDRF69OI89VoToWoXpVvffIk-DhecGj-mZixgy0Qwb4S3dhh1D=w1200|https://lh3.googleusercontent.com/pw/AP1GczP7pR3aj8il8QzAyxGiKlwebH9w-cayYMlvB3CKBP3vJnrQy_CgbNdidTV0LYzhjVREtP8irAiGobXSUclt164Z_0kKlNRl1p7TlMnq034jTpBKAnap=w1200|https://lh3.google"&"usercontent.com/pw/AP1GczOqBG6RMa4UmToalEBdiGVEyxiwpHAuyHtdwLgrEGvB5E6BL7I0IqP18Fp87H4qYLGZxmOo0_o0Nk5IwL7hp_saiI5U18J40W6rjHwL2AesEyvZK7Pf=w1200|https://lh3.googleusercontent.com/pw/AP1GczOYDpophPphjZ_XOQhxrYdkgb1ULcEIo2OaCHdNR2ja_w3FXvygiKZTc-s107TLIl-F"&"K7lcRSZGcxyQMKomdtXnd1iRl7vzAXE2p1cQq5GdcKNxtVOm=w1200|https://lh3.googleusercontent.com/pw/AP1GczN5Ax_pur40sKfULmPIO7IotMe4ysxNGMl942q6T8L55tiKlvjj3z94nQ2EPqZ0nyUnWZzJ_fZq36Z7Rve1TNFlwJ0ynwKaeoYJMKNv7SDSGvk1R1Wq=w1200|https://lh3.googleusercontent.com/pw"&"/AP1GczP6kkquiOYs0oBn1zyKCk2AZ6IozTPgv-ZtNd1gPGExaIYdTa3jo0bc9kbivnRVMow7dL_ihev3bKLPJp4tTj7ZEDSnT-XcRmMN6MyOEgkzoZ5wKL7E=w1200|https://lh3.googleusercontent.com/pw/AP1GczNynOzf5U7dTYuEug5wKhTQ08OEBkiRlSnf4SJVZ5dBY5FJ6xeUoo_Ncnz1l8uoaGBD5tkmvgxV_PC737V-h1"&"7Fv5Q8Y9XwkL_cTF1nKTIHsnddv5x9=w1200|https://lh3.googleusercontent.com/pw/AP1GczMLtgappbFoKeYzn32a4bXk3Q-EzbxqCWEkY1XLAuqjb-u6VfVHNQwuME3L46WAsqf0zHOEhalZjDAE5FcJomOmxJMOH3lFwgA1L6E2U99dfbHOtcSm=w1200|https://lh3.googleusercontent.com/pw/AP1GczOxVjiI4IvHA"&"4wmH4gcvCwiD5lEoueyDdP7soOxQnkaA02sBO99ADzKeqYdmC8kuIpElz_sfyBP2GTdtj9Wm_reHcfaDi7UXFg3vR_M8CisAdELXZbE=w1200|https://lh3.googleusercontent.com/pw/AP1GczMAhyIiYQFKsssrY5sCRY9yGsiNR5zLP6G2VV2uveNq4LgVpZgUKmXkkEauKlyj2xkRvRQp3FYGdTVdontozmAR0T_ciaM4HgIaB8wS"&"yEsRG7A7O_G1=w1200|https://lh3.googleusercontent.com/pw/AP1GczP5ki9OojRO8-ZCn-HvC-AAM513WY_A9l8U9rT8eJM0jLDVxTuNJbuw8zSTeVOvTA5sGdA2O34nSrPWk_5rjz5f-WBjDEyMsRb6bh2CLFYdNqdB4V-5=w1200|https://lh3.googleusercontent.com/pw/AP1GczOImcZyGYskcTR-9D3SdTr1vmFfm0D"&"lzRZUakOKhcb8fph7N0u4j-X_HvEm0Cdwn-G0DENWLFAAEal8yPXyFJGmwmgRkP-xfV9b_-4EISuSXxXGchTV=w1200|https://lh3.googleusercontent.com/pw/AP1GczMWQJonWZufNMfmyRCFTMG9zKakEwaJe31q1jCqgj7Kbi-k4qERsgdl7FYEukrqJe9HKyBbnN5JT4azbr-xnIoWo4tWD4m9Lwlk8HZG_XcZRzZOzEn_=w1200"&"|https://lh3.googleusercontent.com/pw/AP1GczMxEUS1DQcCvPN4UOpcOv3PGoJmq8X5dGCd1gm07Pv7XpGYfqiOSdGG2mKWt4OWooa5yorM0v4C727CizzcTv7nELMampFm-uv7IJsTp5OpKxCNtUy9=w1200") -> https://lh3.googleusercontent.com/pw/AP1GczNiJ2WTMAT7mE7Vvqt81Bwzfk6FVv9tlijaYncZFHZYNHmwlHmb5HXAzBgCtiBLWoRNqJLrfBEAGtGC5CpQFJTxOfggFexN_mCIasqxrTumVvFn6gPO=w1200|https://lh3.googleusercontent.com/pw/AP1GczMoTaZSPGlIilMcMBR67uSopPBxjCVXWyrNfJ2--8roH3txtTJZQLSBIPlidqR7L4cDRF69OI89VoToWoXpVvffIk-DhecGj-mZixgy0Qwb4S3dhh1D=w1200|https://lh3.googleusercontent.com/pw/AP1GczP7pR3aj8il8QzAyxGiKlwebH9w-cayYMlvB3CKBP3vJnrQy_CgbNdidTV0LYzhjVREtP8irAiGobXSUclt164Z_0kKlNRl1p7TlMnq034jTpBKAnap=w1200|https://lh3.googleusercontent.com/pw/AP1GczOqBG6RMa4UmToalEBdiGVEyxiwpHAuyHtdwLgrEGvB5E6BL7I0IqP18Fp87H4qYLGZxmOo0_o0Nk5IwL7hp_saiI5U18J40W6rjHwL2AesEyvZK7Pf=w1200|https://lh3.googleusercontent.com/pw/AP1GczOYDpophPphjZ_XOQhxrYdkgb1ULcEIo2OaCHdNR2ja_w3FXvygiKZTc-s107TLIl-FK7lcRSZGcxyQMKomdtXnd1iRl7vzAXE2p1cQq5GdcKNxtVOm=w1200|https://lh3.googleusercontent.com/pw/AP1GczN5Ax_pur40sKfULmPIO7IotMe4ysxNGMl942q6T8L55tiKlvjj3z94nQ2EPqZ0nyUnWZzJ_fZq36Z7Rve1TNFlwJ0ynwKaeoYJMKNv7SDSGvk1R1Wq=w1200|https://lh3.googleusercontent.com/pw/AP1GczP6kkquiOYs0oBn1zyKCk2AZ6IozTPgv-ZtNd1gPGExaIYdTa3jo0bc9kbivnRVMow7dL_ihev3bKLPJp4tTj7ZEDSnT-XcRmMN6MyOEgkzoZ5wKL7E=w1200|https://lh3.googleusercontent.com/pw/AP1GczNynOzf5U7dTYuEug5wKhTQ08OEBkiRlSnf4SJVZ5dBY5FJ6xeUoo_Ncnz1l8uoaGBD5tkmvgxV_PC737V-h17Fv5Q8Y9XwkL_cTF1nKTIHsnddv5x9=w1200|https://lh3.googleusercontent.com/pw/AP1GczMLtgappbFoKeYzn32a4bXk3Q-EzbxqCWEkY1XLAuqjb-u6VfVHNQwuME3L46WAsqf0zHOEhalZjDAE5FcJomOmxJMOH3lFwgA1L6E2U99dfbHOtcSm=w1200|https://lh3.googleusercontent.com/pw/AP1GczOxVjiI4IvHA4wmH4gcvCwiD5lEoueyDdP7soOxQnkaA02sBO99ADzKeqYdmC8kuIpElz_sfyBP2GTdtj9Wm_reHcfaDi7UXFg3vR_M8CisAdELXZbE=w1200|https://lh3.googleusercontent.com/pw/AP1GczMAhyIiYQFKsssrY5sCRY9yGsiNR5zLP6G2VV2uveNq4LgVpZgUKmXkkEauKlyj2xkRvRQp3FYGdTVdontozmAR0T_ciaM4HgIaB8wSyEsRG7A7O_G1=w1200|https://lh3.googleusercontent.com/pw/AP1GczP5ki9OojRO8-ZCn-HvC-AAM513WY_A9l8U9rT8eJM0jLDVxTuNJbuw8zSTeVOvTA5sGdA2O34nSrPWk_5rjz5f-WBjDEyMsRb6bh2CLFYdNqdB4V-5=w1200|https://lh3.googleusercontent.com/pw/AP1GczOImcZyGYskcTR-9D3SdTr1vmFfm0DlzRZUakOKhcb8fph7N0u4j-X_HvEm0Cdwn-G0DENWLFAAEal8yPXyFJGmwmgRkP-xfV9b_-4EISuSXxXGchTV=w1200|https://lh3.googleusercontent.com/pw/AP1GczMWQJonWZufNMfmyRCFTMG9zKakEwaJe31q1jCqgj7Kbi-k4qERsgdl7FYEukrqJe9HKyBbnN5JT4azbr-xnIoWo4tWD4m9Lwlk8HZG_XcZRzZOzEn_=w1200|https://lh3.googleusercontent.com/pw/AP1GczMxEUS1DQcCvPN4UOpcOv3PGoJmq8X5dGCd1gm07Pv7XpGYfqiOSdGG2mKWt4OWooa5yorM0v4C727CizzcTv7nELMampFm-uv7IJsTp5OpKxCNtUy9=w1200
A5: =IFERROR(__xludf.DUMMYFUNCTION("""COMPUTED_VALUE"""),"3118") -> 3118 | B5: =IFERROR(__xludf.DUMMYFUNCTION("""COMPUTED_VALUE"""),"Casa en barrio Quirinal") -> Casa en barrio Quirinal | C5: =IFERROR(__xludf.DUMMYFUNCTION("""COMPUTED_VALUE"""),"Casa") -> Casa | D5: =IFERROR(__xludf.DUMMYFUNCTION("""COMPUTED_VALUE"""),"Quirinal") -> Quirinal | F5: =IFERROR(__xludf.DUMMYFUNCTION("""COMPUTED_VALUE"""),9.0E8) -> 900000000 | G5: =IFERROR(__xludf.DUMMYFUNCTION("""COMPUTED_VALUE"""),"$500'000.000 a $1.000'000.000") -> $500'000.000 a $1.000'000.000 | J5: =IFERROR(__xludf.DUMMYFUNCTION("""COMPUTED_VALUE"""),"Centro") -> Centro | K5: =IFERROR(__xludf.DUMMYFUNCTION("""COMPUTED_VALUE"""),"3") -> 3 | L5: =IFERROR(__xludf.DUMMYFUNCTION("""COMPUTED_VALUE"""),6.0) -> 6 | N5: =IFERROR(__xludf.DUMMYFUNCTION("""COMPUTED_VALUE"""),3.0) -> 3 | O5: =IFERROR(__xludf.DUMMYFUNCTION("""COMPUTED_VALUE"""),1.0) -> 1 | P5: =IFERROR(__xludf.DUMMYFUNCTION("""COMPUTED_VALUE"""),2.0) -> 2 | R5: =IFERROR(__xludf.DUMMYFUNCTION("""COMPUTED_VALUE"""),323.0) -> 323 | S5: =IFERROR(__xludf.DUMMYFUNCTION("""COMPUTED_VALUE""")," ") | T5: =IFERROR(__xludf.DUMMYFUNCTION("""COMPUTED_VALUE"""),"Neiva") -> Neiva | U5: =IFERROR(__xludf.DUMMYFUNCTION("""COMPUTED_VALUE"""),"4") -> 4 | V5: =IFERROR(__xludf.DUMMYFUNCTION("""COMPUTED_VALUE"""),"Esquinera") -> Esquinera | X5: =IFERROR(__xludf.DUMMYFUNCTION("""COMPUTED_VALUE"""),5.0) -> 5 | Y5: =IFERROR(__xludf.DUMMYFUNCTION("""COMPUTED_VALUE"""),"No tiene") -> No tiene | Z5: =IFERROR(__xludf.DUMMYFUNCTION("""COMPUTED_VALUE"""),"No aplica") -> No aplica | AA5: =IFERROR(__xludf.DUMMYFUNCTION("""COMPUTED_VALUE"""),"No aplica") -> No aplica | AB5: =IFERROR(__xludf.DUMMYFUNCTION("""COMPUTED_VALUE"""),"https://photos.app.goo.gl/JsmPogvXQAzJjipm7") -> https://photos.app.goo.gl/JsmPogvXQAzJjipm7 | AF5: =IFERROR(__xludf.DUMMYFUNCTION("""COMPUTED_VALUE"""),"semi-integral") -> semi-integral | AH5: =IFERROR(__xludf.DUMMYFUNCTION("""COMPUTED_VALUE"""),"Inventario") -> Inventario | AJ5: =IFERROR(__xludf.DUMMYFUNCTION("""COMPUTED_VALUE"""),"B-Inventario Quirinal") -> B-Inventario Quirinal | AL5: =IFERROR(__xludf.DUMMYFUNCTION("""COMPUTED_VALUE"""),"TIENE FOTOS") -> TIENE FOTOS | AM5: =IFERROR(__xludf.DUMMYFUNCTION("""COMPUTED_VALUE"""),3.212323681E9) -> 3212323681 | AN5: =IFERROR(__xludf.DUMMYFUNCTION("""COMPUTED_VALUE"""),3.135781638E9) -> 3135781638 | AP5: =IFERROR(__xludf.DUMMYFUNCTION("""COMPUTED_VALUE"""),"Calle 17 A No. 7-73") -> Calle 17 A No. 7-73 | AS5: =IFERROR(__xludf.DUMMYFUNCTION("""COMPUTED_VALUE"""),0.0) -> 0 | AT5: =IFERROR(__xludf.DUMMYFUNCTION("""COMPUTED_VALUE"""),0.0) -> 0 | AU5: =IFERROR(__xludf.DUMMYFUNCTION("""COMPUTED_VALUE"""),0.0) -> 0 | AV5: =IFERROR(__xludf.DUMMYFUNCTION("""COMPUTED_VALUE"""),0.0) -> 0 | AW5: =IFERROR(__xludf.DUMMYFUNCTION("""COMPUTED_VALUE"""),"NO") -> NO | AX5: =IFERROR(__xludf.DUMMYFUNCTION("""COMPUTED_VALUE"""),0.0) -> 0 | AY5: =IFERROR(__xludf.DUMMYFUNCTION("""COMPUTED_VALUE"""),0.0) -> 0 | AZ5: =IFERROR(__xludf.DUMMYFUNCTION("""COMPUTED_VALUE"""),0.0) -> 0 | BA5: =IFERROR(__xludf.DUMMYFUNCTION("""COMPUTED_VALUE"""),"X") -> X | BB5: =IFERROR(__xludf.DUMMYFUNCTION("""COMPUTED_VALUE"""),0.0) -> 0 | BC5: =IFERROR(__xludf.DUMMYFUNCTION("""COMPUTED_VALUE"""),"2 - JAIRO DIAZ, 39 - JHONATHA, 39 - JHONATHAN") -> 2 - JAIRO DIAZ, 39 - JHONATHA, 39 - JHONATHAN | BF5: =IFERROR(__xludf.DUMMYFUNCTION("""COMPUTED_VALUE"""),"https://lh3.googleusercontent.com/pw/AP1GczNg2rwgsskmo-_A3mKJ-dyYpYRdYtkQTk_wN_XnpGymgQBxUvht_vICWWXt5UdWMjuQf089l5hSPaLJw0x0PLnhTLcugkJJUgjCvm6zL-pt7Ex8VE2z=w1200|https://lh3.googleusercontent.com/pw/AP1GczOzH2Pj3Qg3vdO1_DqlyU6j1VC7Z8J4heGwAq5ohoRcXo8eCS"&"QTguDEAL6tq9VT2Kzpdt5WTXqKiZXluRo1GCnDxhslObSfp17ab9b80MynXhPu9FGS=w1200|https://lh3.googleusercontent.com/pw/AP1GczM0reGmmBkst7N_xJ6UETL55bBv5GtzYYrqWQ8OzB48W2vwY7UQHJbSDo9K-c3NOQypz962fqvljXmChjvafe1sK8fHtIHgke5Z5dYn7kwgKe_nIhY2=w1200|https://lh3.google"&"usercontent.com/pw/AP1GczMq93394K4U1GY9tfsZiz01XOoVyDCQunpS2IZu1tr2M_pEZLNUJL_vcBIuRqyXwBfl7etkAv5tJOoQkngw6JjDm46dzh6kuHvvJmkQwgSdnyg2ouwD=w1200|https://lh3.googleusercontent.com/pw/AP1GczM-tCnQduwmrt9kPzVxV8UnBeNOd-XLv_4pXGe2HXihFVwZaYm0HxPXaHEmXgW885ZI"&"7_JIDZgMbFjg6_SYBKgcSXfFKOO_gELQx_nWmlRp1Lf4nDvY=w1200|https://lh3.googleusercontent.com/pw/AP1GczPIuI7Vg7XAU6QAP_obauw49fTpvXND8CuOW9x12PYKkWd2ubiV0M0TiYJhzGn0lCt38dXziLC2f3TJoOxh-4f_oGlUKKMLI6lEd7VyQ-2Eni9we0bw=w1200|https://lh3.googleusercontent.com/pw"&"/AP1GczOAmjmjTHnEt12WNlc0w5BT1YvvpVW4QEfmxNMR8slJN2_D529fJFlxRelfKp4F0fY1jpLx50va0x-Sr32YWizLkaHDROF2A3HtvtTPKMi5d8pG8AXA=w1200|https://lh3.googleusercontent.com/pw/AP1GczOZhd_dKfATMRSVw9mLTSf2MNcZzGkiP3gWtJoi8cWyDuZGs6GDUUA66FvmJ49DInR2DdSFfpITvR_By0w1R0"&"ESzkfqAGPgmIy6RntcY8ZI-i0sDCMv=w1200|https://lh3.googleusercontent.com/pw/AP1GczNmlOHjHOOz_8v1eLcUkxJuAVX3iCWw__VfQE8kbzH7UVUm4KEj66cPSb3RDuwe9Xho8EVkyy51DjcZmz7AFcEBsrckJS3unQ9g1sh8Nrp1pvCoUckS=w1200|https://lh3.googleusercontent.com/pw/AP1GczO5gbayHS-EB"&"fX0mE1adstUpQ_ZIROAG6dlPuGoafBSwzpV9L2JwyH6NjHvIivYgKvqnGpVie9b8zth_5PVzHNdtN3CcYX8XkKqCLImbplETybZGjH4=w1200|https://lh3.googleusercontent.com/pw/AP1GczNLrUp3o3JgaWjBtOWz7_eHixafJuv0xDgp5YYDl28_fil2piaUnjEbJuRMylo83PEQl4CbISGlR6liWGMlNp8oyVVm41-LABgCIAEp"&"uqGYboqPxIOM=w1200|https://lh3.googleusercontent.com/pw/AP1GczNpemxJ7zfjZ4pgnwcfK7ZMHyiS8meImxAS_BWPLziHSKytwflVsx9RqDNmezJygSe_wdne82pLDMy_EPFKP6a_Kph9ty7WAvIGo1kFxpIY6y_XT2QY=w1200|https://lh3.googleusercontent.com/pw/AP1GczNAmJ35ntXvSBHuCyAYvc_8U7qZDxz"&"pE4UcLlEyLdhOkm7-xo_1jTmmR6bFT595yHqtD2fvIu4X2tnaA-C9e1mEJstr4gZ485EXcRo6KsCm9yE-giiC=w1200|https://lh3.googleusercontent.com/pw/AP1GczMhco40CNWULWuDdBoNOJgoziHx0H3rmUDAx1fh0f7CjvTLCt-RiA4UFkcjvoFMDlXCZYB2UPWJ6Y93oAmEKbS0lwY4HfrfH6lb_BpbaVlcAaTRMrmy=w1200"&"|https://lh3.googleusercontent.com/pw/AP1GczNhiDKbPW9zrX1-A2OFKsTq6NhgrPZIDC5qHcysEh90srBZ-hiaHfN2PWAEACcZvlDqXBrELC4pl_9UJ04bzcXlOqHzfLO10R1H5tu4qSfiJSlcyTU8=w1200|https://lh3.googleusercontent.com/pw/AP1GczPH1PC7MoAB9ZlO2YZ5QlrKv8GheVVa1UX_Dr8Dkb0TEczdb"&"MA0fIImqc0TS3hloDRjJWG0mYuTKGy7-i6B2_lT6ag3-cMLc6odgFRGNamTICegg_-Y=w1200|https://lh3.googleusercontent.com/pw/AP1GczPp-h9J0CIzgLW7_6Hlao-NIwJBol5_YGJRQqbZRn3TUxgW5t-nJByW3dnaIJEyGOMOguGsTOGRzFFtk50nBUxjwx0J4ypSMJCsqwG9rNjzRXM0m2Bx=w1200|https://lh3.googl"&"eusercontent.com/pw/AP1GczMXiMMdrkJ1QmsHO_pfZxQkqMgn7KKIffOB6MhyR79KPG4hpEIj77jx3gEqs-Qpi06lCp3GXqFdzThJrSRrSZ4Flvt6YS8Tp87ClXNV0_ctym68OzzV=w1200|https://lh3.googleusercontent.com/pw/AP1GczPx1RrMeOhIr10rahDjBDrF8G5wnRmmDLSW-BqOcyVzQZZcNiVo8McZ_vE6dgCOTiX"&"bdWHAACO9QsvMCn_8mm5TWXQzFwMOYbHqThCAWrAzLUTCLFWc=w1200|https://lh3.googleusercontent.com/pw/AP1GczOGrMzCO3VX-5JY_voaWemeaIk1rNsqOD3iCaf82W8ypS4eZdOhWPkQtDoC3jhHgJhXd_2n64UJvSXXttFDx9zIqkp7XTve9fdK0muB0yOpuHOO-6z1=w1200|https://lh3.googleusercontent.com/p"&"w/AP1GczOGJ4n9H0Kwu7kBXj3F20-Mzlh3Qmh1YNEMWUjEzLzZygE5n9mVFVughUEOlaiv2yTHAvvlfPN4M4bX9KQkSexvla7BazpE8uxboE-XCPiYYx9liNT4=w1200") -> https://lh3.googleusercontent.com/pw/AP1GczNg2rwgsskmo-_A3mKJ-dyYpYRdYtkQTk_wN_XnpGymgQBxUvht_vICWWXt5UdWMjuQf089l5hSPaLJw0x0PLnhTLcugkJJUgjCvm6zL-pt7Ex8VE2z=w1200|https://lh3.googleusercontent.com/pw/AP1GczOzH2Pj3Qg3vdO1_DqlyU6j1VC7Z8J4heGwAq5ohoRcXo8eCSQTguDEAL6tq9VT2Kzpdt5WTXqKiZXluRo1GCnDxhslObSfp17ab9b80MynXhPu9FGS=w1200|https://lh3.googleusercontent.com/pw/AP1GczM0reGmmBkst7N_xJ6UETL55bBv5GtzYYrqWQ8OzB48W2vwY7UQHJbSDo9K-c3NOQypz962fqvljXmChjvafe1sK8fHtIHgke5Z5dYn7kwgKe_nIhY2=w1200|https://lh3.googleusercontent.com/pw/AP1GczMq93394K4U1GY9tfsZiz01XOoVyDCQunpS2IZu1tr2M_pEZLNUJL_vcBIuRqyXwBfl7etkAv5tJOoQkngw6JjDm46dzh6kuHvvJmkQwgSdnyg2ouwD=w1200|https://lh3.googleusercontent.com/pw/AP1GczM-tCnQduwmrt9kPzVxV8UnBeNOd-XLv_4pXGe2HXihFVwZaYm0HxPXaHEmXgW885ZI7_JIDZgMbFjg6_SYBKgcSXfFKOO_gELQx_nWmlRp1Lf4nDvY=w1200|https://lh3.googleusercontent.com/pw/AP1GczPIuI7Vg7XAU6QAP_obauw49fTpvXND8CuOW9x12PYKkWd2ubiV0M0TiYJhzGn0lCt38dXziLC2f3TJoOxh-4f_oGlUKKMLI6lEd7VyQ-2Eni9we0bw=w1200|https://lh3.googleusercontent.com/pw/AP1GczOAmjmjTHnEt12WNlc0w5BT1YvvpVW4QEfmxNMR8slJN2_D529fJFlxRelfKp4F0fY1jpLx50va0x-Sr32YWizLkaHDROF2A3HtvtTPKMi5d8pG8AXA=w1200|https://lh3.googleusercontent.com/pw/AP1GczOZhd_dKfATMRSVw9mLTSf2MNcZzGkiP3gWtJoi8cWyDuZGs6GDUUA66FvmJ49DInR2DdSFfpITvR_By0w1R0ESzkfqAGPgmIy6RntcY8ZI-i0sDCMv=w1200|https://lh3.googleusercontent.com/pw/AP1GczNmlOHjHOOz_8v1eLcUkxJuAVX3iCWw__VfQE8kbzH7UVUm4KEj66cPSb3RDuwe9Xho8EVkyy51DjcZmz7AFcEBsrckJS3unQ9g1sh8Nrp1pvCoUckS=w1200|https://lh3.googleusercontent.com/pw/AP1GczO5gbayHS-EBfX0mE1adstUpQ_ZIROAG6dlPuGoafBSwzpV9L2JwyH6NjHvIivYgKvqnGpVie9b8zth_5PVzHNdtN3CcYX8XkKqCLImbplETybZGjH4=w1200|https://lh3.googleusercontent.com/pw/AP1GczNLrUp3o3JgaWjBtOWz7_eHixafJuv0xDgp5YYDl28_fil2piaUnjEbJuRMylo83PEQl4CbISGlR6liWGMlNp8oyVVm41-LABgCIAEpuqGYboqPxIOM=w1200|https://lh3.googleusercontent.com/pw/AP1GczNpemxJ7zfjZ4pgnwcfK7ZMHyiS8meImxAS_BWPLziHSKytwflVsx9RqDNmezJygSe_wdne82pLDMy_EPFKP6a_Kph9ty7WAvIGo1kFxpIY6y_XT2QY=w1200|https://lh3.googleusercontent.com/pw/AP1GczNAmJ35ntXvSBHuCyAYvc_8U7qZDxzpE4UcLlEyLdhOkm7-xo_1jTmmR6bFT595yHqtD2fvIu4X2tnaA-C9e1mEJstr4gZ485EXcRo6KsCm9yE-giiC=w1200|https://lh3.googleusercontent.com/pw/AP1GczMhco40CNWULWuDdBoNOJgoziHx0H3rmUDAx1fh0f7CjvTLCt-RiA4UFkcjvoFMDlXCZYB2UPWJ6Y93oAmEKbS0lwY4HfrfH6lb_BpbaVlcAaTRMrmy=w1200|https://lh3.googleusercontent.com/pw/AP1GczNhiDKbPW9zrX1-A2OFKsTq6NhgrPZIDC5qHcysEh90srBZ-hiaHfN2PWAEACcZvlDqXBrELC4pl_9UJ04bzcXlOqHzfLO10R1H5tu4qSfiJSlcyTU8=w1200|https://lh3.googleusercontent.com/pw/AP1GczPH1PC7MoAB9ZlO2YZ5QlrKv8GheVVa1UX_Dr8Dkb0TEczdbMA0fIImqc0TS3hloDRjJWG0mYuTKGy7-i6B2_lT6ag3-cMLc6odgFRGNamTICegg_-Y=w1200|https://lh3.googleusercontent.com/pw/AP1GczPp-h9J0CIzgLW7_6Hlao-NIwJBol5_YGJRQqbZRn3TUxgW5t-nJByW3dnaIJEyGOMOguGsTOGRzFFtk50nBUxjwx0J4ypSMJCsqwG9rNjzRXM0m2Bx=w1200|https://lh3.googleusercontent.com/pw/AP1GczMXiMMdrkJ1QmsHO_pfZxQkqMgn7KKIffOB6MhyR79KPG4hpEIj77jx3gEqs-Qpi06lCp3GXqFdzThJrSRrSZ4Flvt6YS8Tp87ClXNV0_ctym68OzzV=w1200|https://lh3.googleusercontent.com/pw/AP1GczPx1RrMeOhIr10rahDjBDrF8G5wnRmmDLSW-BqOcyVzQZZcNiVo8McZ_vE6dgCOTiXbdWHAACO9QsvMCn_8mm5TWXQzFwMOYbHqThCAWrAzLUTCLFWc=w1200|https://lh3.googleusercontent.com/pw/AP1GczOGrMzCO3VX-5JY_voaWemeaIk1rNsqOD3iCaf82W8ypS4eZdOhWPkQtDoC3jhHgJhXd_2n64UJvSXXttFDx9zIqkp7XTve9fdK0muB0yOpuHOO-6z1=w1200|https://lh3.googleusercontent.com/pw/AP1GczOGJ4n9H0Kwu7kBXj3F20-Mzlh3Qmh1YNEMWUjEzLzZygE5n9mVFVughUEOlaiv2yTHAvvlfPN4M4bX9KQkSexvla7BazpE8uxboE-XCPiYYx9liNT4=w1200
A6: =IFERROR(__xludf.DUMMYFUNCTION("""COMPUTED_VALUE"""),"2843") -> 2843 | B6: =IFERROR(__xludf.DUMMYFUNCTION("""COMPUTED_VALUE"""),"Casa en barrio Sevilla") -> Casa en barrio Sevilla | C6: =IFERROR(__xludf.DUMMYFUNCTION("""COMPUTED_VALUE"""),"Casa") -> Casa | D6: =IFERROR(__xludf.DUMMYFUNCTION("""COMPUTED_VALUE"""),"Sevilla") -> Sevilla | F6: =IFERROR(__xludf.DUMMYFUNCTION("""COMPUTED_VALUE"""),7.0E8) -> 700000000 | G6: =IFERROR(__xludf.DUMMYFUNCTION("""COMPUTED_VALUE"""),"$500'000.000 a $1.000'000.000") -> $500'000.000 a $1.000'000.000 | J6: =IFERROR(__xludf.DUMMYFUNCTION("""COMPUTED_VALUE"""),"Centro") -> Centro | K6: =IFERROR(__xludf.DUMMYFUNCTION("""COMPUTED_VALUE"""),"3") -> 3 | L6: =IFERROR(__xludf.DUMMYFUNCTION("""COMPUTED_VALUE"""),3.0) -> 3 | N6: =IFERROR(__xludf.DUMMYFUNCTION("""COMPUTED_VALUE"""),6.0) -> 6 | O6: =IFERROR(__xludf.DUMMYFUNCTION("""COMPUTED_VALUE"""),1.0) -> 1 | P6: =IFERROR(__xludf.DUMMYFUNCTION("""COMPUTED_VALUE"""),2.0) -> 2 | R6: =IFERROR(__xludf.DUMMYFUNCTION("""COMPUTED_VALUE"""),364.0) -> 364 | S6: =IFERROR(__xludf.DUMMYFUNCTION("""COMPUTED_VALUE""")," ") | T6: =IFERROR(__xludf.DUMMYFUNCTION("""COMPUTED_VALUE"""),"Neiva") -> Neiva | U6: =IFERROR(__xludf.DUMMYFUNCTION("""COMPUTED_VALUE"""),"4") -> 4 | V6: =IFERROR(__xludf.DUMMYFUNCTION("""COMPUTED_VALUE"""),"Medianera") -> Medianera | X6: =IFERROR(__xludf.DUMMYFUNCTION("""COMPUTED_VALUE"""),3.0) -> 3 | Y6: =IFERROR(__xludf.DUMMYFUNCTION("""COMPUTED_VALUE"""),"No tiene") -> No tiene | Z6: =IFERROR(__xludf.DUMMYFUNCTION("""COMPUTED_VALUE"""),"No aplica") -> No aplica | AA6: =IFERROR(__xludf.DUMMYFUNCTION("""COMPUTED_VALUE"""),"No aplica") -> No aplica | AB6: =IFERROR(__xludf.DUMMYFUNCTION("""COMPUTED_VALUE"""),"https://photos.app.goo.gl/MFdMkcBc3i82eZUV7") -> https://photos.app.goo.gl/MFdMkcBc3i82eZUV7 | AF6: =IFERROR(__xludf.DUMMYFUNCTION("""COMPUTED_VALUE"""),"integral") -> integral | AH6: =IFERROR(__xludf.DUMMYFUNCTION("""COMPUTED_VALUE"""),"Inventario") -> Inventario | AJ6: =IFERROR(__xludf.DUMMYFUNCTION("""COMPUTED_VALUE"""),"B-Inventario Sevilla") -> B-Inventario Sevilla | AL6: =IFERROR(__xludf.DUMMYFUNCTION("""COMPUTED_VALUE"""),"TIENE FOTOS") -> TIENE FOTOS | AM6: =IFERROR(__xludf.DUMMYFUNCTION("""COMPUTED_VALUE"""),3.212323681E9) -> 3212323681 | AN6: =IFERROR(__xludf.DUMMYFUNCTION("""COMPUTED_VALUE"""),3.135781638E9) -> 3135781638 | AP6: =IFERROR(__xludf.DUMMYFUNCTION("""COMPUTED_VALUE"""),"CARRERA 5 B NO. 21-31") -> CARRERA 5 B NO. 21-31 | AS6: =IFERROR(__xludf.DUMMYFUNCTION("""COMPUTED_VALUE"""),0.0) -> 0 | AT6: =IFERROR(__xludf.DUMMYFUNCTION("""COMPUTED_VALUE"""),0.0) -> 0 | AU6: =IFERROR(__xludf.DUMMYFUNCTION("""COMPUTED_VALUE"""),0.0) -> 0 | AV6: =IFERROR(__xludf.DUMMYFUNCTION("""COMPUTED_VALUE"""),0.0) -> 0 | AW6: =IFERROR(__xludf.DUMMYFUNCTION("""COMPUTED_VALUE"""),"NO") -> NO | AX6: =IFERROR(__xludf.DUMMYFUNCTION("""COMPUTED_VALUE"""),0.0) -> 0 | AY6: =IFERROR(__xludf.DUMMYFUNCTION("""COMPUTED_VALUE"""),0.0) -> 0 | AZ6: =IFERROR(__xludf.DUMMYFUNCTION("""COMPUTED_VALUE"""),0.0) -> 0 | BA6: =IFERROR(__xludf.DUMMYFUNCTION("""COMPUTED_VALUE"""),"X") -> X | BB6: =IFERROR(__xludf.DUMMYFUNCTION("""COMPUTED_VALUE"""),0.0) -> 0 | BF6: =IFERROR(__xludf.DUMMYFUNCTION("""COMPUTED_VALUE"""),"❌ Error: HTTP 404 para: https://photos.google.com/share/AF1QipPawSbNB9VDr7unrUk6mOMjTi-KhXmb-saTz_Kx8D0ns6KyZTpWeJutjM2WgS8-jQ?key=eWljS09zUVFacFoyRk1fYndRbDlPNHkyUDBWcjZB") -> ❌ Error: HTTP 404 para: https://photos.google.com/share/AF1QipPawSbNB9VDr7unrUk6mOMjTi-KhXmb-saTz_Kx8D0ns6KyZTpWeJutjM2WgS8-jQ?key=eWljS09zUVFacFoyRk1fYndRbDlPNHkyUDBWcjZB
A7: =IFERROR(__xludf.DUMMYFUNCTION("""COMPUTED_VALUE"""),"3409") -> 3409 | B7: =IFERROR(__xludf.DUMMYFUNCTION("""COMPUTED_VALUE"""),"Casa en barrio Sevilla") -> Casa en barrio Sevilla | C7: =IFERROR(__xludf.DUMMYFUNCTION("""COMPUTED_VALUE"""),"Casa") -> Casa | D7: =IFERROR(__xludf.DUMMYFUNCTION("""COMPUTED_VALUE"""),"Sevilla") -> Sevilla | F7: =IFERROR(__xludf.DUMMYFUNCTION("""COMPUTED_VALUE"""),6.5E8) -> 650000000 | G7: =IFERROR(__xludf.DUMMYFUNCTION("""COMPUTED_VALUE"""),"$500'000.000 a $1.000'000.000") -> $500'000.000 a $1.000'000.000 | J7: =IFERROR(__xludf.DUMMYFUNCTION("""COMPUTED_VALUE"""),"Centro") -> Centro | K7: =IFERROR(__xludf.DUMMYFUNCTION("""COMPUTED_VALUE"""),"3") -> 3 | L7: =IFERROR(__xludf.DUMMYFUNCTION("""COMPUTED_VALUE"""),4.0) -> 4 | N7: =IFERROR(__xludf.DUMMYFUNCTION("""COMPUTED_VALUE"""),6.0) -> 6 | O7: =IFERROR(__xludf.DUMMYFUNCTION("""COMPUTED_VALUE"""),1.0) -> 1 | P7: =IFERROR(__xludf.DUMMYFUNCTION("""COMPUTED_VALUE"""),1.0) -> 1 | Q7: =IFERROR(__xludf.DUMMYFUNCTION("""COMPUTED_VALUE"""),238.0) -> 238 | R7: =IFERROR(__xludf.DUMMYFUNCTION("""COMPUTED_VALUE"""),368.0) -> 368 | S7: =IFERROR(__xludf.DUMMYFUNCTION("""COMPUTED_VALUE""")," ") | T7: =IFERROR(__xludf.DUMMYFUNCTION("""COMPUTED_VALUE"""),"Neiva") -> Neiva | U7: =IFERROR(__xludf.DUMMYFUNCTION("""COMPUTED_VALUE"""),"4") -> 4 | V7: =IFERROR(__xludf.DUMMYFUNCTION("""COMPUTED_VALUE"""),"Medianera") -> Medianera | X7: =IFERROR(__xludf.DUMMYFUNCTION("""COMPUTED_VALUE"""),3.0) -> 3 | Y7: =IFERROR(__xludf.DUMMYFUNCTION("""COMPUTED_VALUE"""),"No tiene") -> No tiene | Z7: =IFERROR(__xludf.DUMMYFUNCTION("""COMPUTED_VALUE"""),"No aplica") -> No aplica | AA7: =IFERROR(__xludf.DUMMYFUNCTION("""COMPUTED_VALUE"""),"No aplica") -> No aplica | AB7: =IFERROR(__xludf.DUMMYFUNCTION("""COMPUTED_VALUE"""),"https://photos.app.goo.gl/GhkCaFHqVtsvqh766") -> https://photos.app.goo.gl/GhkCaFHqVtsvqh766 | AF7: =IFERROR(__xludf.DUMMYFUNCTION("""COMPUTED_VALUE"""),"integral") -> integral | AH7: =IFERROR(__xludf.DUMMYFUNCTION("""COMPUTED_VALUE"""),"Inventario") -> Inventario | AJ7: =IFERROR(__xludf.DUMMYFUNCTION("""COMPUTED_VALUE"""),"B-Inventario Sevilla") -> B-Inventario Sevilla | AL7: =IFERROR(__xludf.DUMMYFUNCTION("""COMPUTED_VALUE"""),"TIENE FOTOS") -> TIENE FOTOS | AM7: =IFERROR(__xludf.DUMMYFUNCTION("""COMPUTED_VALUE"""),3.212323681E9) -> 3212323681 | AN7: =IFERROR(__xludf.DUMMYFUNCTION("""COMPUTED_VALUE"""),3.135781638E9) -> 3135781638 | AP7: =IFERROR(__xludf.DUMMYFUNCTION("""COMPUTED_VALUE"""),"CARRERA 5 A BIS NO. 21 A - 37") -> CARRERA 5 A BIS NO. 21 A - 37 | AS7: =IFERROR(__xludf.DUMMYFUNCTION("""COMPUTED_VALUE"""),0.0) -> 0 | AT7: =IFERROR(__xludf.DUMMYFUNCTION("""COMPUTED_VALUE"""),0.0) -> 0 | AU7: =IFERROR(__xludf.DUMMYFUNCTION("""COMPUTED_VALUE"""),0.0) -> 0 | AV7: =IFERROR(__xludf.DUMMYFUNCTION("""COMPUTED_VALUE"""),0.0) -> 0 | AW7: =IFERROR(__xludf.DUMMYFUNCTION("""COMPUTED_VALUE"""),"NO") -> NO | AX7: =IFERROR(__xludf.DUMMYFUNCTION("""COMPUTED_VALUE"""),0.0) -> 0 | AY7: =IFERROR(__xludf.DUMMYFUNCTION("""COMPUTED_VALUE"""),0.0) -> 0 | AZ7: =IFERROR(__xludf.DUMMYFUNCTION("""COMPUTED_VALUE"""),0.0) -> 0 | BA7: =IFERROR(__xludf.DUMMYFUNCTION("""COMPUTED_VALUE"""),"X") -> X | BB7: =IFERROR(__xludf.DUMMYFUNCTION("""COMPUTED_VALUE"""),0.0) -> 0 | BF7: =IFERROR(__xludf.DUMMYFUNCTION("""COMPUTED_VALUE"""),"https://lh3.googleusercontent.com/pw/AP1GczMzEDjCEw8SMQVCdxTzafrdBNIcYAYbW2lGTsEvzw5_-toafpnNSrbQushkcQcLwIgar8IOscTdsT2G3wn4gVj3V8GTLBPQ1PlXhTpqdpRYFD1-pjXY=w1200|https://lh3.googleusercontent.com/pw/AP1GczOvMDh2gK0fgoRNYCz7Bk_CnmU2uzYBBXlZ9StIFtBbsaO0BG"&"Ymjqo0kHIZouk1YvOYVHXmVYkxPLwu3WyLeGK5HmrKUiSHbEoC-s1kGebqdsQh8OhL=w1200|https://lh3.googleusercontent.com/pw/AP1GczPdU1XSk6f7ykDqHVbtndsgky9cGG5k0Olqucb-rPtQloArXociKLFVi7pKPlcfUcSkmN5SlXswMp_N9ImkfUraUxYoHO-HqJkawZheeJFX8duDwk0y=w1200|https://lh3.google"&"usercontent.com/pw/AP1GczMuYW-Eh7AgDKdkzx7RjZPzCXE9Gb9f7T2DseQ5YOi3fzJHYg7j-1WoErPxyOJ-fQZfw8YHtJo97hcPUxG2tZUxztYzcnNe6tifGTWUyQWSUquntQ9R=w1200|https://lh3.googleusercontent.com/pw/AP1GczO5SJBJPD_JeQrpNmOYa4XaykqTfcBjMW8nZvBlHvh8pvbF53XZjTSTVRqUwBSfBGvR"&"4EhhazQvk20pTusv67Tquk3BpDO9oxBE8hmqDNfj4xkKBQUm=w1200|https://lh3.googleusercontent.com/pw/AP1GczP8hg9hz1B9APKZtAjwmMom0wULQkqf3pidsUnJjRDoJJ4iepq0noAhI2OlVKMIXf6FDl5Pjj6J_xYqgd6i2PwtEjw3ETAdm78xr3qMAHp8mh3kp3WF=w1200|https://lh3.googleusercontent.com/pw"&"/AP1GczO5utEMDDyXA9_nHtl9BIgVINrfmpI85i2QmqGq1M5ZGptDCTBEX9Xk6XhbtiKFTeWHuMEZXQJ3CFO05yCEG_lekv0Q9PuBtuiA8tUSQNP53vs4R0eQ=w1200|https://lh3.googleusercontent.com/pw/AP1GczMwzHNOlX067I9zX5WZPjxBcPlfjIiZSSmebd5zqCk63PVnR6KBS4aW8cwmww-L9HOAesG0VfNAXly-gSCYdL"&"4G0N0QvqLyrD6V7PMGtrjm9eD0kfr8=w1200|https://lh3.googleusercontent.com/pw/AP1GczMWa1dmVg9BSuheqnllvaPrQ31DC_JyqgAF56UTEkXdbx1TAwQDMEnHoaiFH1WOZS4fIL5VBzk1rwvCFazeWF1U5CSi_ixTNXtuMhckN9_9bnTLykP0=w1200|https://lh3.googleusercontent.com/pw/AP1GczOa5qIAgzZIC"&"au4PMGXquDYTMYlOyzmBqTashklgRDgJjaIuCsgC0Kg57TRXY5tgD6lp-9OYo536t_zPXA3FkDgVM2wDHVv7H0SJB5xS7lOBBtZ3tU4=w1200|https://lh3.googleusercontent.com/pw/AP1GczNw3xRR-zJsJb71vY9PYz2M0JgiorlRKjfo83VjeJ9nrwClg76NjiyygiPMolPGvGwl9kV1G6w4URXR-jP_1hy0ql6d93FcokO7O1o4"&"ks4_jwRFeNN4=w1200|https://lh3.googleusercontent.com/pw/AP1GczMUzKUZd2LC-ZMXNmD3wWYWVYdoIVgU7yeLjAL3sXMPUp3ADzLk-Ga75ZE_unpFIONvem7gHp2bzt-BiD4kfzciLvT45K_-OphSyI1RTSFBe972zSiz=w1200|https://lh3.googleusercontent.com/pw/AP1GczOgsYC1x150MdPbL-9NAjHI58d1g9H"&"mDg3PZd68HzcmGGQhdbeFZA6nzKmVDFaxsZ2O143fgJKjob25f47ppQbVw_En1e3dUemh-NnIBzZOdgVuP8hd=w1200|https://lh3.googleusercontent.com/pw/AP1GczPVjyO8ScIeqa4zs51VuFPPVTXxdMSvEzVwQHnsFekqLhwEP560BOV8BB2tosFeUVn42Au1ZIq1w1-U-V9VoIpwgWr93iXgSL5zFOEByhyFwWknqBDm=w1200"&"|https://lh3.googleusercontent.com/pw/AP1GczP5TH5BnAytftEvPtBVSny0kuJMuTuv-gG8_FniQyopXOmR9sONGAZMvTaW-XaK-9lFiGP4hdfyF2SBnegAxSsgtpiEzlXjYzDyDWZQnOkBPr546JAX=w1200|https://lh3.googleusercontent.com/pw/AP1GczNF3ixtO3TFG_UykEru8Azin6lXVKaoLjMV3IC5-AO3xdpFQ"&"KJPLL3f0bXL6aFQQmWF6Ug84SJo6jd33VoPVgZq1B_war_m1i6s35OG9d9V9M5DGz-I=w1200|https://lh3.googleusercontent.com/pw/AP1GczNDem5zKzf8FV-oNlmGmL6WRZXu_uM71aWlPTY8jlx3zXfqq88Z2nwip_cQW6C4QoQeeKY6kspPFDhShsyM8ZJ0bvfgX1HbPcq8zlEPeu16mbL62Nea=w1200|https://lh3.googl"&"eusercontent.com/pw/AP1GczNPr9drSiKdvzRBCbAgK2kX_lMSM30goRA1NJeDLKae8qBEa3qRkjSxT0L8pS7eQYCyM0ywa3YBy6ewcxYicYBSZasw7Zd8wR1QNflMOrH6ypmJ3rbx=w1200|https://lh3.googleusercontent.com/pw/AP1GczPnBriqpqiFY4PKfxgIL95euomZYxsr12KyFs4KU4SLfQ9yaNMwM3bzgxEnyGLnV5f"&"_A_K0BAxWywTjRsJ-KSbO3ET8tQLjxuW2f72eiw9FjpESWd75=w1200|https://lh3.googleusercontent.com/pw/AP1GczN5r6u5anUn2RRZowG-girQSEevAYQfZV4X1HoyomM3KHrRy1fCAWmxpzYZACZsWTAS78pASSw-FkYpxiCuYl2YjNlgj849jiSh367ke_7BhQKEi9d7=w1200|https://lh3.googleusercontent.com/p"&"w/AP1GczNkeDxQm7F-Zf4BEFxIdIY-I4EaxjBP7pNUBrnm28CK9feVVE_xrjlXMYqjsUjT7Sj6DB2tViOhf0FdVQxZctxjWFrjBeEng1CDk-j36YhaWB6RMOlC=w1200|https://lh3.googleusercontent.com/pw/AP1GczPcGl4xinsdQd1ITp7LdUuz-DS9UsB5o6DbYe_eQhBdMF4bI0jDlZsVPGpzFeOvtWX8AnZWS3qZCj3PBCBG9"&"QJhwE5EwFt7MlbESiTrklf3t6dRydrx=w1200|https://lh3.googleusercontent.com/pw/AP1GczNgldRkzt4InnqZxNfGJPrq--R6h932k4Z5UMQ-NY1hbuFr4TnOoqz_5Q5oET5jpqAwMWxQOsZ2Va8YJjI8W18nbzHkiPrlOqnw1ZS_LnxuyUqIA4aG=w1200|https://lh3.googleusercontent.com/pw/AP1GczNrAk7NETXn"&"-_ivwajpoRw24YJU9L49wTWm7R0junjQu1aKVQA49dB1VFTTTCTCvN-V6Ug0EySojhVUJcNMEU_nEhxEBKGuQb8OPrMPPngCj8XwZW3o=w1200|https://lh3.googleusercontent.com/pw/AP1GczO7jjNlISrYkuw59DMMg2cX9JvfcUQdOMeefQs_olQsymLKVQ3UfoNjOZxTdV5LEi3g_G4la9JHYNCnbEAMF8hF1CIxeQBjcqE-8Lg"&"_gWUGpqrqj9fx=w1200|https://lh3.googleusercontent.com/pw/AP1GczM25UNyYzCHPXnB5nv4pTPPB2EgplBKucxeV4bshcsxxb_6-4ojj-SSq7FBLKzZNgOxWSl0uF__zbrB6LYeZTa5hCh6djy694awkN6hOplewEfL6sUz=w1200|https://lh3.googleusercontent.com/pw/AP1GczO4IijvDyY7vItRArSPzXqycKENCc"&"uf3PYJfvGcoDRPW9w-al_9PzMmO7Wf91fUTqIq2-NbShnigGypOtyyZjERi_WUiTib1AOF_KNDm02k2546dA5s=w1200|https://lh3.googleusercontent.com/pw/AP1GczMhOFVEmNcis0AdyDUSQljS37trUzp_iMqQ0bH8_eOcrQmdjYWFddk6yrIC2lvzwDJq1-ARWfh3aCRJAb0S7-My_dwju8HctstMeVCvctfuy44thhXi=w120"&"0|https://lh3.googleusercontent.com/pw/AP1GczM8bNkmiT_roXSQXU7LKj82cpyILgt6ciY5hdnBIk6wGBo7j_SPBvEKZHqrNrasrQbQ8Qece458bJczWYhjCeKBvhBKvf-evGuSdpLc35Yh1Kjgr3LV=w1200|https://lh3.googleusercontent.com/pw/AP1GczPOml5G9dHoJzLlaXCbVyzQWUIZYaF9yOmasvIk3gJnTVQk"&"T2IRGuBaiB1z4u26wfekdGoWh7ugIdFtyppzH2bixr_fJTZDoP2jMSAHH1KzTD6EbXhO=w1200|https://lh3.googleusercontent.com/pw/AP1GczPW05CT4PQxt_H1XTC2MQrv6KwFMaipJI3W-5V6dHxkSDdh6C0fYDrPv2bL2u46-pyxDj7Sk7WRJGi9hae8Fm8SgWruU7WrHYDT2dlC0VGGJnASXDi6=w1200|https://lh3.goog"&"leusercontent.com/pw/AP1GczNK4sQwfeCR4JeozS3nnnPpAqWAZLwBF97fmRZJVxIJjoWK6ybJDUCqVtjtgPuJ112c5t3wmdhCtPECxF4lz0gAaevlLFAi34Z2glxq0CNeaIO8pckg=w1200") -> https://lh3.googleusercontent.com/pw/AP1GczMzEDjCEw8SMQVCdxTzafrdBNIcYAYbW2lGTsEvzw5_-toafpnNSrbQushkcQcLwIgar8IOscTdsT2G3wn4gVj3V8GTLBPQ1PlXhTpqdpRYFD1-pjXY=w1200|https://lh3.googleusercontent.com/pw/AP1GczOvMDh2gK0fgoRNYCz7Bk_CnmU2uzYBBXlZ9StIFtBbsaO0BGYmjqo0kHIZouk1YvOYVHXmVYkxPLwu3WyLeGK5HmrKUiSHbEoC-s1kGebqdsQh8OhL=w1200|https://lh3.googleusercontent.com/pw/AP1GczPdU1XSk6f7ykDqHVbtndsgky9cGG5k0Olqucb-rPtQloArXociKLFVi7pKPlcfUcSkmN5SlXswMp_N9ImkfUraUxYoHO-HqJkawZheeJFX8duDwk0y=w1200|https://lh3.googleusercontent.com/pw/AP1GczMuYW-Eh7AgDKdkzx7RjZPzCXE9Gb9f7T2DseQ5YOi3fzJHYg7j-1WoErPxyOJ-fQZfw8YHtJo97hcPUxG2tZUxztYzcnNe6tifGTWUyQWSUquntQ9R=w1200|https://lh3.googleusercontent.com/pw/AP1GczO5SJBJPD_JeQrpNmOYa4XaykqTfcBjMW8nZvBlHvh8pvbF53XZjTSTVRqUwBSfBGvR4EhhazQvk20pTusv67Tquk3BpDO9oxBE8hmqDNfj4xkKBQUm=w1200|https://lh3.googleusercontent.com/pw/AP1GczP8hg9hz1B9APKZtAjwmMom0wULQkqf3pidsUnJjRDoJJ4iepq0noAhI2OlVKMIXf6FDl5Pjj6J_xYqgd6i2PwtEjw3ETAdm78xr3qMAHp8mh3kp3WF=w1200|https://lh3.googleusercontent.com/pw/AP1GczO5utEMDDyXA9_nHtl9BIgVINrfmpI85i2QmqGq1M5ZGptDCTBEX9Xk6XhbtiKFTeWHuMEZXQJ3CFO05yCEG_lekv0Q9PuBtuiA8tUSQNP53vs4R0eQ=w1200|https://lh3.googleusercontent.com/pw/AP1GczMwzHNOlX067I9zX5WZPjxBcPlfjIiZSSmebd5zqCk63PVnR6KBS4aW8cwmww-L9HOAesG0VfNAXly-gSCYdL4G0N0QvqLyrD6V7PMGtrjm9eD0kfr8=w1200|https://lh3.googleusercontent.com/pw/AP1GczMWa1dmVg9BSuheqnllvaPrQ31DC_JyqgAF56UTEkXdbx1TAwQDMEnHoaiFH1WOZS4fIL5VBzk1rwvCFazeWF1U5CSi_ixTNXtuMhckN9_9bnTLykP0=w1200|https://lh3.googleusercontent.com/pw/AP1GczOa5qIAgzZICau4PMGXquDYTMYlOyzmBqTashklgRDgJjaIuCsgC0Kg57TRXY5tgD6lp-9OYo536t_zPXA3FkDgVM2wDHVv7H0SJB5xS7lOBBtZ3tU4=w1200|https://lh3.googleusercontent.com/pw/AP1GczNw3xRR-zJsJb71vY9PYz2M0JgiorlRKjfo83VjeJ9nrwClg76NjiyygiPMolPGvGwl9kV1G6w4URXR-jP_1hy0ql6d93FcokO7O1o4ks4_jwRFeNN4=w1200|https://lh3.googleusercontent.com/pw/AP1GczMUzKUZd2LC-ZMXNmD3wWYWVYdoIVgU7yeLjAL3sXMPUp3ADzLk-Ga75ZE_unpFIONvem7gHp2bzt-BiD4kfzciLvT45K_-OphSyI1RTSFBe972zSiz=w1200|https://lh3.googleusercontent.com/pw/AP1GczOgsYC1x150MdPbL-9NAjHI58d1g9HmDg3PZd68HzcmGGQhdbeFZA6nzKmVDFaxsZ2O143fgJKjob25f47ppQbVw_En1e3dUemh-NnIBzZOdgVuP8hd=w1200|https://lh3.googleusercontent.com/pw/AP1GczPVjyO8ScIeqa4zs51VuFPPVTXxdMSvEzVwQHnsFekqLhwEP560BOV8BB2tosFeUVn42Au1ZIq1w1-U-V9VoIpwgWr93iXgSL5zFOEByhyFwWknqBDm=w1200|https://lh3.googleusercontent.com/pw/AP1GczP5TH5BnAytftEvPtBVSny0kuJMuTuv-gG8_FniQyopXOmR9sONGAZMvTaW-XaK-9lFiGP4hdfyF2SBnegAxSsgtpiEzlXjYzDyDWZQnOkBPr546JAX=w1200|https://lh3.googleusercontent.com/pw/AP1GczNF3ixtO3TFG_UykEru8Azin6lXVKaoLjMV3IC5-AO3xdpFQKJPLL3f0bXL6aFQQmWF6Ug84SJo6jd33VoPVgZq1B_war_m1i6s35OG9d9V9M5DGz-I=w1200|https://lh3.googleusercontent.com/pw/AP1GczNDem5zKzf8FV-oNlmGmL6WRZXu_uM71aWlPTY8jlx3zXfqq88Z2nwip_cQW6C4QoQeeKY6kspPFDhShsyM8ZJ0bvfgX1HbPcq8zlEPeu16mbL62Nea=w1200|https://lh3.googleusercontent.com/pw/AP1GczNPr9drSiKdvzRBCbAgK2kX_lMSM30goRA1NJeDLKae8qBEa3qRkjSxT0L8pS7eQYCyM0ywa3YBy6ewcxYicYBSZasw7Zd8wR1QNflMOrH6ypmJ3rbx=w1200|https://lh3.googleusercontent.com/pw/AP1GczPnBriqpqiFY4PKfxgIL95euomZYxsr12KyFs4KU4SLfQ9yaNMwM3bzgxEnyGLnV5f_A_K0BAxWywTjRsJ-KSbO3ET8tQLjxuW2f72eiw9FjpESWd75=w1200|https://lh3.googleusercontent.com/pw/AP1GczN5r6u5anUn2RRZowG-girQSEevAYQfZV4X1HoyomM3KHrRy1fCAWmxpzYZACZsWTAS78pASSw-FkYpxiCuYl2YjNlgj849jiSh367ke_7BhQKEi9d7=w1200|https://lh3.googleusercontent.com/pw/AP1GczNkeDxQm7F-Zf4BEFxIdIY-I4EaxjBP7pNUBrnm28CK9feVVE_xrjlXMYqjsUjT7Sj6DB2tViOhf0FdVQxZctxjWFrjBeEng1CDk-j36YhaWB6RMOlC=w1200|https://lh3.googleusercontent.com/pw/AP1GczPcGl4xinsdQd1ITp7LdUuz-DS9UsB5o6DbYe_eQhBdMF4bI0jDlZsVPGpzFeOvtWX8AnZWS3qZCj3PBCBG9QJhwE5EwFt7MlbESiTrklf3t6dRydrx=w1200|https://lh3.googleusercontent.com/pw/AP1GczNgldRkzt4InnqZxNfGJPrq--R6h932k4Z5UMQ-NY1hbuFr4TnOoqz_5Q5oET5jpqAwMWxQOsZ2Va8YJjI8W18nbzHkiPrlOqnw1ZS_LnxuyUqIA4aG=w1200|https://lh3.googleusercontent.com/pw/AP1GczNrAk7NETXn-_ivwajpoRw24YJU9L49wTWm7R0junjQu1aKVQA49dB1VFTTTCTCvN-V6Ug0EySojhVUJcNMEU_nEhxEBKGuQb8OPrMPPngCj8XwZW3o=w1200|https://lh3.googleusercontent.com/pw/AP1GczO7jjNlISrYkuw59DMMg2cX9JvfcUQdOMeefQs_olQsymLKVQ3UfoNjOZxTdV5LEi3g_G4la9JHYNCnbEAMF8hF1CIxeQBjcqE-8Lg_gWUGpqrqj9fx=w1200|https://lh3.googleusercontent.com/pw/AP1GczM25UNyYzCHPXnB5nv4pTPPB2EgplBKucxeV4bshcsxxb_6-4ojj-SSq7FBLKzZNgOxWSl0uF__zbrB6LYeZTa5hCh6djy694awkN6hOplewEfL6sUz=w1200|https://lh3.googleusercontent.com/pw/AP1GczO4IijvDyY7vItRArSPzXqycKENCcuf3PYJfvGcoDRPW9w-al_9PzMmO7Wf91fUTqIq2-NbShnigGypOtyyZjERi_WUiTib1AOF_KNDm02k2546dA5s=w1200|https://lh3.googleusercontent.com/pw/AP1GczMhOFVEmNcis0AdyDUSQljS37trUzp_iMqQ0bH8_eOcrQmdjYWFddk6yrIC2lvzwDJq1-ARWfh3aCRJAb0S7-My_dwju8HctstMeVCvctfuy44thhXi=w1200|https://lh3.googleusercontent.com/pw/AP1GczM8bNkmiT_roXSQXU7LKj82cpyILgt6ciY5hdnBIk6wGBo7j_SPBvEKZHqrNrasrQbQ8Qece458bJczWYhjCeKBvhBKvf-evGuSdpLc35Yh1Kjgr3LV=w1200|https://lh3.googleusercontent.com/pw/AP1GczPOml5G9dHoJzLlaXCbVyzQWUIZYaF9yOmasvIk3gJnTVQkT2IRGuBaiB1z4u26wfekdGoWh7ugIdFtyppzH2bixr_fJTZDoP2jMSAHH1KzTD6EbXhO=w1200|https://lh3.googleusercontent.com/pw/AP1GczPW05CT4PQxt_H1XTC2MQrv6KwFMaipJI3W-5V6dHxkSDdh6C0fYDrPv2bL2u46-pyxDj7Sk7WRJGi9hae8Fm8SgWruU7WrHYDT2dlC0VGGJnASXDi6=w1200|https://lh3.googleusercontent.com/pw/AP1GczNK4sQwfeCR4JeozS3nnnPpAqWAZLwBF97fmRZJVxIJjoWK6ybJDUCqVtjtgPuJ112c5t3wmdhCtPECxF4lz0gAaevlLFAi34Z2glxq0CNeaIO8pckg=w1200
A8: =IFERROR(__xludf.DUMMYFUNCTION("""COMPUTED_VALUE"""),"1823") -> 1823 | B8: =IFERROR(__xludf.DUMMYFUNCTION("""COMPUTED_VALUE"""),"Casa en barrio Sevilla") -> Casa en barrio Sevilla | C8: =IFERROR(__xludf.DUMMYFUNCTION("""COMPUTED_VALUE"""),"Casa") -> Casa | D8: =IFERROR(__xludf.DUMMYFUNCTION("""COMPUTED_VALUE"""),"Sevilla") -> Sevilla | E8: =IFERROR(__xludf.DUMMYFUNCTION("""COMPUTED_VALUE""")," ") | F8: =IFERROR(__xludf.DUMMYFUNCTION("""COMPUTED_VALUE"""),4.5E8) -> 450000000 | G8: =IFERROR(__xludf.DUMMYFUNCTION("""COMPUTED_VALUE"""),"$400'000.000 a $500'000.000") -> $400'000.000 a $500'000.000 | J8: =IFERROR(__xludf.DUMMYFUNCTION("""COMPUTED_VALUE"""),"Centro") -> Centro | K8: =IFERROR(__xludf.DUMMYFUNCTION("""COMPUTED_VALUE"""),"3") -> 3 | L8: =IFERROR(__xludf.DUMMYFUNCTION("""COMPUTED_VALUE"""),4.0) -> 4 | N8: =IFERROR(__xludf.DUMMYFUNCTION("""COMPUTED_VALUE"""),4.0) -> 4 | O8: =IFERROR(__xludf.DUMMYFUNCTION("""COMPUTED_VALUE"""),3.0) -> 3 | P8: =IFERROR(__xludf.DUMMYFUNCTION("""COMPUTED_VALUE"""),2.0) -> 2 | R8: =IFERROR(__xludf.DUMMYFUNCTION("""COMPUTED_VALUE"""),225.0) -> 225 | S8: =IFERROR(__xludf.DUMMYFUNCTION("""COMPUTED_VALUE""")," ") | T8: =IFERROR(__xludf.DUMMYFUNCTION("""COMPUTED_VALUE"""),"Neiva") -> Neiva | U8: =IFERROR(__xludf.DUMMYFUNCTION("""COMPUTED_VALUE"""),"4") -> 4 | V8: =IFERROR(__xludf.DUMMYFUNCTION("""COMPUTED_VALUE"""),"Esquinera") -> Esquinera | X8: =IFERROR(__xludf.DUMMYFUNCTION("""COMPUTED_VALUE"""),4.0) -> 4 | Y8: =IFERROR(__xludf.DUMMYFUNCTION("""COMPUTED_VALUE"""),"No tiene") -> No tiene | Z8: =IFERROR(__xludf.DUMMYFUNCTION("""COMPUTED_VALUE"""),"No aplica") -> No aplica | AA8: =IFERROR(__xludf.DUMMYFUNCTION("""COMPUTED_VALUE"""),"No aplica") -> No aplica | AB8: =IFERROR(__xludf.DUMMYFUNCTION("""COMPUTED_VALUE"""),"https://photos.app.goo.gl/QreDSVBcWGaTgydG6") -> https://photos.app.goo.gl/QreDSVBcWGaTgydG6 | AF8: =IFERROR(__xludf.DUMMYFUNCTION("""COMPUTED_VALUE"""),"integral") -> integral | AH8: =IFERROR(__xludf.DUMMYFUNCTION("""COMPUTED_VALUE"""),"Inventario") -> Inventario | AJ8: =IFERROR(__xludf.DUMMYFUNCTION("""COMPUTED_VALUE"""),"B-Inventario Sevilla") -> B-Inventario Sevilla | AL8: =IFERROR(__xludf.DUMMYFUNCTION("""COMPUTED_VALUE"""),"TIENE FOTOS") -> TIENE FOTOS | AM8: =IFERROR(__xludf.DUMMYFUNCTION("""COMPUTED_VALUE"""),3.212323681E9) -> 3212323681 | AN8: =IFERROR(__xludf.DUMMYFUNCTION("""COMPUTED_VALUE"""),3.135781638E9) -> 3135781638 | AP8: =IFERROR(__xludf.DUMMYFUNCTION("""COMPUTED_VALUE"""),"CALLE 23 NO. 5-55") -> CALLE 23 NO. 5-55 | AS8: =IFERROR(__xludf.DUMMYFUNCTION("""COMPUTED_VALUE"""),0.0) -> 0 | AT8: =IFERROR(__xludf.DUMMYFUNCTION("""COMPUTED_VALUE"""),0.0) -> 0 | AU8: =IFERROR(__xludf.DUMMYFUNCTION("""COMPUTED_VALUE"""),0.0) -> 0 | AV8: =IFERROR(__xludf.DUMMYFUNCTION("""COMPUTED_VALUE"""),0.0) -> 0 | AW8: =IFERROR(__xludf.DUMMYFUNCTION("""COMPUTED_VALUE"""),"NO") -> NO | AX8: =IFERROR(__xludf.DUMMYFUNCTION("""COMPUTED_VALUE"""),0.0) -> 0 | AY8: =IFERROR(__xludf.DUMMYFUNCTION("""COMPUTED_VALUE"""),0.0) -> 0 | AZ8: =IFERROR(__xludf.DUMMYFUNCTION("""COMPUTED_VALUE"""),0.0) -> 0 | BA8: =IFERROR(__xludf.DUMMYFUNCTION("""COMPUTED_VALUE"""),"X") -> X | BB8: =IFERROR(__xludf.DUMMYFUNCTION("""COMPUTED_VALUE"""),0.0) -> 0 | BC8: =IFERROR(__xludf.DUMMYFUNCTION("""COMPUTED_VALUE"""),"26 - NINI CASTAÑO, SR. ACOSTA, 43 - SR. ACOSTA") -> 26 - NINI CASTAÑO, SR. ACOSTA, 43 - SR. ACOSTA | BF8: =IFERROR(__xludf.DUMMYFUNCTION("""COMPUTED_VALUE"""),"https://lh3.googleusercontent.com/pw/AP1GczNF5B1o7mG5pLj_U6832cyl4DHmAUiTG2qT2j9T2GNMVFmFEigioZ9tF0dK583VkMc4wJdLSJeUFiEMGbk0gZJa557VMXV6Q5szhc2sh1PJyydqWYF8=w1200|https://lh3.googleusercontent.com/pw/AP1GczP6qLTQRwIsJ-mn-9rXtcRzHIpYNVmcEmE5uToS-tSXmY7lHN"&"2LRTekqcBkS9xmdHp_YK4jlkgC-OUV2HC0CGQMO6o1OpRIeFg76JeWVdoGqznNlLrb=w1200|https://lh3.googleusercontent.com/pw/AP1GczNfDSL2jtfI9kFq9dlL7-z5jDXADOzODe4wcDfvmJ79iyG6nmzQhAwOnp98EhukHJ-WYBJw4cJj8EiC4pS5_KcbYs6HySza3GQB0Mnyse--aiZcHRN3=w1200|https://lh3.google"&"usercontent.com/pw/AP1GczOsvpwC8-agjpBQPbLQ6YmTZ_99Tn4_vMYbi1hmv2Ht97-ib6aufhQSQ1dHB3zUJfFCgIARMLHymv18gZtYVrvDuTc-TTZJj3XoeeXUdjUcjgiLXRFx=w1200|https://lh3.googleusercontent.com/pw/AP1GczPyOTBqsYtd4P300B0J6Zrf_nh-RmG2tey9-SRrcmgCnrLebf4N-NQi3c00VXJPTG-J"&"6fQ8GmTbvlolnb-U4wRyjLdfKmFr5o4ruXCGoZK3WvV1z_46=w1200|https://lh3.googleusercontent.com/pw/AP1GczNT9lQPQtNG17-aVjaMtc9sUOglgAQtPx17c_X2q9SWAyp7CUVP9e8cseEbBvokjqfGcmRLwagvUgqrqVGrpLYPHlFj319taUoom9fTI8KRNeb3GzGn=w1200|https://lh3.googleusercontent.com/pw"&"/AP1GczPAJ2rI3PYneVL5XoUyPi-jGfVVYGZNr4__ad2taJ8mU_NmiDDNlgkLzM6FjSsxyeZpkc2kCDTAam8M3FD_HVEyVT8AUBWJLQhFtr1kat_8fQVUYCpl=w1200|https://lh3.googleusercontent.com/pw/AP1GczOpZJLCkrIXYXV1eMzLRcvodRFfgYXxmhkN0dWXvla29k94fc2heSHGln65QQWhP-KMydnyBCAEMgbXy6h-WT"&"BDtNs8h-WVCcWXDiC0JU8rES5lI2Q9=w1200|https://lh3.googleusercontent.com/pw/AP1GczMlUNnSNm-0c_8IKAzOSxVUc9S3ZDYSagFJW9sBKgjvXowdMiw-sjNU44hkpUw24Tg2sN-dyHH0AT948YshrFIHjfpRqoVwDvfUbyH-0txyPwiSRyW5=w1200|https://lh3.googleusercontent.com/pw/AP1GczOp0HcmokKne"&"Zc-n9ISfYHH7qY7Ciw2kuEh6_-Y572IE4Z31ZiY6o3Duhr4G5i-o2DTx3r-2d9X5FliPftBTdS4LQQefPeyvXl_GOrztvxBvoYOxSal=w1200|https://lh3.googleusercontent.com/pw/AP1GczPivV754D--M2jTpTt58OVDGbZvjB7VsTf78WC-a9I93RbPW13jtT4ayaGqw56Y_g03Dv21g63IQC-EINvRNoHaC6U3Zq9a6oHxE_z5"&"j0KlHPcRMrPQ=w1200|https://lh3.googleusercontent.com/pw/AP1GczPtT4ikowQ7HDPsGEnl0vlF89eqTtruSoY64OYbRGac7eUj33FuSchSTRhBwD31DTP5RbStSO-Md8I-PTPGbPTQxUmTgDwx3mRAH81WMlvx_yM1iMTP=w1200|https://lh3.googleusercontent.com/pw/AP1GczNSRgdXPTYgQCVVPFO9XmPlDgrmxj9"&"hlPEdGGjJ3bhsdG-XRzREBeyf90SCddUMouYtWhY14nqz4_siWrrOEeJO3HdnzJZ2fP1TMzencL6l7hwopjSC=w1200") -> https://lh3.googleusercontent.com/pw/AP1GczNF5B1o7mG5pLj_U6832cyl4DHmAUiTG2qT2j9T2GNMVFmFEigioZ9tF0dK583VkMc4wJdLSJeUFiEMGbk0gZJa557VMXV6Q5szhc2sh1PJyydqWYF8=w1200|https://lh3.googleusercontent.com/pw/AP1GczP6qLTQRwIsJ-mn-9rXtcRzHIpYNVmcEmE5uToS-tSXmY7lHN2LRTekqcBkS9xmdHp_YK4jlkgC-OUV2HC0CGQMO6o1OpRIeFg76JeWVdoGqznNlLrb=w1200|https://lh3.googleusercontent.com/pw/AP1GczNfDSL2jtfI9kFq9dlL7-z5jDXADOzODe4wcDfvmJ79iyG6nmzQhAwOnp98EhukHJ-WYBJw4cJj8EiC4pS5_KcbYs6HySza3GQB0Mnyse--aiZcHRN3=w1200|https://lh3.googleusercontent.com/pw/AP1GczOsvpwC8-agjpBQPbLQ6YmTZ_99Tn4_vMYbi1hmv2Ht97-ib6aufhQSQ1dHB3zUJfFCgIARMLHymv18gZtYVrvDuTc-TTZJj3XoeeXUdjUcjgiLXRFx=w1200|https://lh3.googleusercontent.com/pw/AP1GczPyOTBqsYtd4P300B0J6Zrf_nh-RmG2tey9-SRrcmgCnrLebf4N-NQi3c00VXJPTG-J6fQ8GmTbvlolnb-U4wRyjLdfKmFr5o4ruXCGoZK3WvV1z_46=w1200|https://lh3.googleusercontent.com/pw/AP1GczNT9lQPQtNG17-aVjaMtc9sUOglgAQtPx17c_X2q9SWAyp7CUVP9e8cseEbBvokjqfGcmRLwagvUgqrqVGrpLYPHlFj319taUoom9fTI8KRNeb3GzGn=w1200|https://lh3.googleusercontent.com/pw/AP1GczPAJ2rI3PYneVL5XoUyPi-jGfVVYGZNr4__ad2taJ8mU_NmiDDNlgkLzM6FjSsxyeZpkc2kCDTAam8M3FD_HVEyVT8AUBWJLQhFtr1kat_8fQVUYCpl=w1200|https://lh3.googleusercontent.com/pw/AP1GczOpZJLCkrIXYXV1eMzLRcvodRFfgYXxmhkN0dWXvla29k94fc2heSHGln65QQWhP-KMydnyBCAEMgbXy6h-WTBDtNs8h-WVCcWXDiC0JU8rES5lI2Q9=w1200|https://lh3.googleusercontent.com/pw/AP1GczMlUNnSNm-0c_8IKAzOSxVUc9S3ZDYSagFJW9sBKgjvXowdMiw-sjNU44hkpUw24Tg2sN-dyHH0AT948YshrFIHjfpRqoVwDvfUbyH-0txyPwiSRyW5=w1200|https://lh3.googleusercontent.com/pw/AP1GczOp0HcmokKneZc-n9ISfYHH7qY7Ciw2kuEh6_-Y572IE4Z31ZiY6o3Duhr4G5i-o2DTx3r-2d9X5FliPftBTdS4LQQefPeyvXl_GOrztvxBvoYOxSal=w1200|https://lh3.googleusercontent.com/pw/AP1GczPivV754D--M2jTpTt58OVDGbZvjB7VsTf78WC-a9I93RbPW13jtT4ayaGqw56Y_g03Dv21g63IQC-EINvRNoHaC6U3Zq9a6oHxE_z5j0KlHPcRMrPQ=w1200|https://lh3.googleusercontent.com/pw/AP1GczPtT4ikowQ7HDPsGEnl0vlF89eqTtruSoY64OYbRGac7eUj33FuSchSTRhBwD31DTP5RbStSO-Md8I-PTPGbPTQxUmTgDwx3mRAH81WMlvx_yM1iMTP=w1200|https://lh3.googleusercontent.com/pw/AP1GczNSRgdXPTYgQCVVPFO9XmPlDgrmxj9hlPEdGGjJ3bhsdG-XRzREBeyf90SCddUMouYtWhY14nqz4_siWrrOEeJO3HdnzJZ2fP1TMzencL6l7hwopjSC=w1200
A9: =IFERROR(__xludf.DUMMYFUNCTION("""COMPUTED_VALUE"""),"3708") -> 3708 | B9: =IFERROR(__xludf.DUMMYFUNCTION("""COMPUTED_VALUE"""),"Casa en barrio Sevilla") -> Casa en barrio Sevilla | C9: =IFERROR(__xludf.DUMMYFUNCTION("""COMPUTED_VALUE"""),"Casa") -> Casa | D9: =IFERROR(__xludf.DUMMYFUNCTION("""COMPUTED_VALUE"""),"Sevilla") -> Sevilla | F9: =IFERROR(__xludf.DUMMYFUNCTION("""COMPUTED_VALUE"""),3.1E8) -> 310000000 | G9: =IFERROR(__xludf.DUMMYFUNCTION("""COMPUTED_VALUE"""),"$300'000.000 a $400'000.000") -> $300'000.000 a $400'000.000 | J9: =IFERROR(__xludf.DUMMYFUNCTION("""COMPUTED_VALUE"""),"Centro") -> Centro | K9: =IFERROR(__xludf.DUMMYFUNCTION("""COMPUTED_VALUE"""),"3") -> 3 | L9: =IFERROR(__xludf.DUMMYFUNCTION("""COMPUTED_VALUE"""),4.0) -> 4 | N9: =IFERROR(__xludf.DUMMYFUNCTION("""COMPUTED_VALUE"""),3.0) -> 3 | O9: =IFERROR(__xludf.DUMMYFUNCTION("""COMPUTED_VALUE"""),1.0) -> 1 | P9: =IFERROR(__xludf.DUMMYFUNCTION("""COMPUTED_VALUE"""),2.0) -> 2 | R9: =IFERROR(__xludf.DUMMYFUNCTION("""COMPUTED_VALUE"""),113.0) -> 113 | S9: =IFERROR(__xludf.DUMMYFUNCTION("""COMPUTED_VALUE""")," ") | T9: =IFERROR(__xludf.DUMMYFUNCTION("""COMPUTED_VALUE"""),"Neiva") -> Neiva | U9: =IFERROR(__xludf.DUMMYFUNCTION("""COMPUTED_VALUE"""),"3") -> 3 | V9: =IFERROR(__xludf.DUMMYFUNCTION("""COMPUTED_VALUE"""),"Medianera") -> Medianera | X9: =IFERROR(__xludf.DUMMYFUNCTION("""COMPUTED_VALUE"""),4.0) -> 4 | Y9: =IFERROR(__xludf.DUMMYFUNCTION("""COMPUTED_VALUE"""),"No tiene") -> No tiene | Z9: =IFERROR(__xludf.DUMMYFUNCTION("""COMPUTED_VALUE"""),"No aplica") -> No aplica | AA9: =IFERROR(__xludf.DUMMYFUNCTION("""COMPUTED_VALUE"""),"No aplica") -> No aplica | AB9: =IFERROR(__xludf.DUMMYFUNCTION("""COMPUTED_VALUE"""),"https://photos.app.goo.gl/J7BteKbURmw1SYqA6") -> https://photos.app.goo.gl/J7BteKbURmw1SYqA6 | AF9: =IFERROR(__xludf.DUMMYFUNCTION("""COMPUTED_VALUE"""),"integral") -> integral | AH9: =IFERROR(__xludf.DUMMYFUNCTION("""COMPUTED_VALUE"""),"Inventario") -> Inventario | AJ9: =IFERROR(__xludf.DUMMYFUNCTION("""COMPUTED_VALUE"""),"B-Inventario Sevilla") -> B-Inventario Sevilla | AL9: =IFERROR(__xludf.DUMMYFUNCTION("""COMPUTED_VALUE"""),"TIENE FOTOS") -> TIENE FOTOS | AM9: =IFERROR(__xludf.DUMMYFUNCTION("""COMPUTED_VALUE"""),3.212323681E9) -> 3212323681 | AN9: =IFERROR(__xludf.DUMMYFUNCTION("""COMPUTED_VALUE"""),"prop. 3153119443-3158910074") -> prop. 3153119443-3158910074 | AP9: =IFERROR(__xludf.DUMMYFUNCTION("""COMPUTED_VALUE"""),"CARRERA 5 B No. 24 - 15") -> CARRERA 5 B No. 24 - 15 | AS9: =IFERROR(__xludf.DUMMYFUNCTION("""COMPUTED_VALUE"""),0.0) -> 0 | AT9: =IFERROR(__xludf.DUMMYFUNCTION("""COMPUTED_VALUE"""),0.0) -> 0 | AU9: =IFERROR(__xludf.DUMMYFUNCTION("""COMPUTED_VALUE"""),0.0) -> 0 | AV9: =IFERROR(__xludf.DUMMYFUNCTION("""COMPUTED_VALUE"""),0.0) -> 0 | AW9: =IFERROR(__xludf.DUMMYFUNCTION("""COMPUTED_VALUE"""),"NO") -> NO | AX9: =IFERROR(__xludf.DUMMYFUNCTION("""COMPUTED_VALUE"""),0.0) -> 0 | AY9: =IFERROR(__xludf.DUMMYFUNCTION("""COMPUTED_VALUE"""),"P") -> P | AZ9: =IFERROR(__xludf.DUMMYFUNCTION("""COMPUTED_VALUE"""),0.0) -> 0 | BA9: =IFERROR(__xludf.DUMMYFUNCTION("""COMPUTED_VALUE"""),"X") -> X | BB9: =IFERROR(__xludf.DUMMYFUNCTION("""COMPUTED_VALUE"""),0.0) -> 0 | BF9: =IFERROR(__xludf.DUMMYFUNCTION("""COMPUTED_VALUE"""),"https://lh3.googleusercontent.com/pw/AP1GczNKgOnMUoohoLWqxYQEsazpwvXJw_p2vuCJXuLSzwDrxEE18isZPNhQaVnW-13K57TtZjd3bpaNj9YZQR0guySVtoITTFZ9RMvepXItAqYPSqpL-GSN=w1200|https://lh3.googleusercontent.com/pw/AP1GczMOyeG8ioop6PcwBxnG40frrn5uyaASpV4BVmHPld7s1gxNyK"&"ei0bEcDxBGoycEvfaaPOkOHpLQrJw9MaYlxWPHxIe7Fk4Id_gNAmZr0js3M4Jk6UID=w1200|https://lh3.googleusercontent.com/pw/AP1GczNwz912P1QA-9JHBAzUuzxvnvBolj1XLx1-l7wmtHSWgHx0JwhfUlv1WAwwgHcjztVhO0Gz2m-xBcpQ28jITcIq3NmuKT3YF4BviB38pAM3Ux3VX6Jg=w1200|https://lh3.google"&"usercontent.com/pw/AP1GczOr_8PReQYN21gnB4fCqmD3fAgHKXF9hfiZvwsI_WUDZ9R5VzK_6mRY6aaPUeQ7gqgqm2sVEOo6pXdd6m1KtSZGtL5M10wHhl8pAUFz2vkXBD7XvQGj=w1200|https://lh3.googleusercontent.com/pw/AP1GczOO3ilV55qIFXfYuc9dHJkitsPij488jVv72kVsd5BXH_WXwfJbO9ymjZ2NkK_BhXj9"&"rQKmdX0rJwg6EVU8PIC3Y9iWV0lFFel3qBQWf62sukiAuRlv=w1200|https://lh3.googleusercontent.com/pw/AP1GczOYE5YBWG-k7Emd4XbtQXUPJ3zkNyco2JNUwPpfYz38xe0JNcur5Jryyw93buQp37qdCbGW_vgcO_4yvr3CG8GWCSGeJ-QD2JtTt86X55Dq0pW5w9am=w1200|https://lh3.googleusercontent.com/pw"&"/AP1GczPw6PBE1Hdd3-5pYs83PhjedJiKlsRS-RjSrMu-GDW5AwK5wsc0THu-lA4tp7RT-QzozOwsNk-u18bBKDfdR5h5ISPbefpYsbd8UrWOBcRFndralFIf=w1200|https://lh3.googleusercontent.com/pw/AP1GczPl22eUZq6-Y4G0sK8tXZfxcyCwwoSmZCisQrD_r8h2CV95lCFZfAd-5RZTg8VcwXVTfqD9grRf7VdhRWUOli"&"7wvDg-N3cvQwCMc6dDVY0Xy3_r9cJL=w1200|https://lh3.googleusercontent.com/pw/AP1GczNkgZGr-fYrvx41UYOKo-gQO-O3xK1qaJBMU_dDqvD00AA2WbEhoVjmsd1plc5pLG6kcSSxI1iQ10NUxBaqYs6PPhlyQWoaBVJpCFiLIOukx1CQF2N2=w1200|https://lh3.googleusercontent.com/pw/AP1GczNVhRYKQOIlb"&"WYwWqb8xwjBiEEDQfp6iBWPMdFBdyY4BpMnb9sj6LiS9PmokDjFYHy8uIFV2ja3ndvza_vrFGglOQsx-bTsw3dFS31VA8WXcvGSK5ws=w1200") -> https://lh3.googleusercontent.com/pw/AP1GczNKgOnMUoohoLWqxYQEsazpwvXJw_p2vuCJXuLSzwDrxEE18isZPNhQaVnW-13K57TtZjd3bpaNj9YZQR0guySVtoITTFZ9RMvepXItAqYPSqpL-GSN=w1200|https://lh3.googleusercontent.com/pw/AP1GczMOyeG8ioop6PcwBxnG40frrn5uyaASpV4BVmHPld7s1gxNyKei0bEcDxBGoycEvfaaPOkOHpLQrJw9MaYlxWPHxIe7Fk4Id_gNAmZr0js3M4Jk6UID=w1200|https://lh3.googleusercontent.com/pw/AP1GczNwz912P1QA-9JHBAzUuzxvnvBolj1XLx1-l7wmtHSWgHx0JwhfUlv1WAwwgHcjztVhO0Gz2m-xBcpQ28jITcIq3NmuKT3YF4BviB38pAM3Ux3VX6Jg=w1200|https://lh3.googleusercontent.com/pw/AP1GczOr_8PReQYN21gnB4fCqmD3fAgHKXF9hfiZvwsI_WUDZ9R5VzK_6mRY6aaPUeQ7gqgqm2sVEOo6pXdd6m1KtSZGtL5M10wHhl8pAUFz2vkXBD7XvQGj=w1200|https://lh3.googleusercontent.com/pw/AP1GczOO3ilV55qIFXfYuc9dHJkitsPij488jVv72kVsd5BXH_WXwfJbO9ymjZ2NkK_BhXj9rQKmdX0rJwg6EVU8PIC3Y9iWV0lFFel3qBQWf62sukiAuRlv=w1200|https://lh3.googleusercontent.com/pw/AP1GczOYE5YBWG-k7Emd4XbtQXUPJ3zkNyco2JNUwPpfYz38xe0JNcur5Jryyw93buQp37qdCbGW_vgcO_4yvr3CG8GWCSGeJ-QD2JtTt86X55Dq0pW5w9am=w1200|https://lh3.googleusercontent.com/pw/AP1GczPw6PBE1Hdd3-5pYs83PhjedJiKlsRS-RjSrMu-GDW5AwK5wsc0THu-lA4tp7RT-QzozOwsNk-u18bBKDfdR5h5ISPbefpYsbd8UrWOBcRFndralFIf=w1200|https://lh3.googleusercontent.com/pw/AP1GczPl22eUZq6-Y4G0sK8tXZfxcyCwwoSmZCisQrD_r8h2CV95lCFZfAd-5RZTg8VcwXVTfqD9grRf7VdhRWUOli7wvDg-N3cvQwCMc6dDVY0Xy3_r9cJL=w1200|https://lh3.googleusercontent.com/pw/AP1GczNkgZGr-fYrvx41UYOKo-gQO-O3xK1qaJBMU_dDqvD00AA2WbEhoVjmsd1plc5pLG6kcSSxI1iQ10NUxBaqYs6PPhlyQWoaBVJpCFiLIOukx1CQF2N2=w1200|https://lh3.googleusercontent.com/pw/AP1GczNVhRYKQOIlbWYwWqb8xwjBiEEDQfp6iBWPMdFBdyY4BpMnb9sj6LiS9PmokDjFYHy8uIFV2ja3ndvza_vrFGglOQsx-bTsw3dFS31VA8WXcvGSK5ws=w1200
A10: =IFERROR(__xludf.DUMMYFUNCTION("""COMPUTED_VALUE"""),"3781") -> 3781 | B10: =IFERROR(__xludf.DUMMYFUNCTION("""COMPUTED_VALUE"""),"Casa en barrio Villa Carolina") -> Casa en barrio Villa Carolina | C10: =IFERROR(__xludf.DUMMYFUNCTION("""COMPUTED_VALUE"""),"Casa") -> Casa | D10: =IFERROR(__xludf.DUMMYFUNCTION("""COMPUTED_VALUE"""),"Villa Carolina") -> Villa Carolina | F10: =IFERROR(__xludf.DUMMYFUNCTION("""COMPUTED_VALUE"""),3.4E8) -> 340000000 | G10: =IFERROR(__xludf.DUMMYFUNCTION("""COMPUTED_VALUE"""),"$300'000.000 a $400'000.000") -> $300'000.000 a $400'000.000 | J10: =IFERROR(__xludf.DUMMYFUNCTION("""COMPUTED_VALUE"""),"Norte") -> Norte | K10: =IFERROR(__xludf.DUMMYFUNCTION("""COMPUTED_VALUE"""),"2") -> 2 | L10: =IFERROR(__xludf.DUMMYFUNCTION("""COMPUTED_VALUE"""),4.0) -> 4 | N10: =IFERROR(__xludf.DUMMYFUNCTION("""COMPUTED_VALUE"""),3.0) -> 3 | O10: =IFERROR(__xludf.DUMMYFUNCTION("""COMPUTED_VALUE"""),1.0) -> 1 | P10: =IFERROR(__xludf.DUMMYFUNCTION("""COMPUTED_VALUE"""),2.0) -> 2 | Q10: =IFERROR(__xludf.DUMMYFUNCTION("""COMPUTED_VALUE"""),150.0) -> 150 | R10: =IFERROR(__xludf.DUMMYFUNCTION("""COMPUTED_VALUE"""),84.0) -> 84 | S10: =IFERROR(__xludf.DUMMYFUNCTION("""COMPUTED_VALUE""")," ") | T10: =IFERROR(__xludf.DUMMYFUNCTION("""COMPUTED_VALUE"""),"Neiva") -> Neiva | U10: =IFERROR(__xludf.DUMMYFUNCTION("""COMPUTED_VALUE"""),"3") -> 3 | V10: =IFERROR(__xludf.DUMMYFUNCTION("""COMPUTED_VALUE"""),"Esquinera") -> Esquinera | X10: =IFERROR(__xludf.DUMMYFUNCTION("""COMPUTED_VALUE"""),4.0) -> 4 | Y10: =IFERROR(__xludf.DUMMYFUNCTION("""COMPUTED_VALUE"""),"No tiene") -> No tiene | Z10: =IFERROR(__xludf.DUMMYFUNCTION("""COMPUTED_VALUE"""),"No aplica") -> No aplica | AA10: =IFERROR(__xludf.DUMMYFUNCTION("""COMPUTED_VALUE"""),"No aplica") -> No aplica | AB10: =IFERROR(__xludf.DUMMYFUNCTION("""COMPUTED_VALUE"""),"https://photos.app.goo.gl/BeHTDzEhVihhPL939") -> https://photos.app.goo.gl/BeHTDzEhVihhPL939 | AF10: =IFERROR(__xludf.DUMMYFUNCTION("""COMPUTED_VALUE"""),"integral") -> integral | AH10: =IFERROR(__xludf.DUMMYFUNCTION("""COMPUTED_VALUE"""),"Inventario") -> Inventario | AJ10: =IFERROR(__xludf.DUMMYFUNCTION("""COMPUTED_VALUE"""),"B-Inventario Villa Carolina") -> B-Inventario Villa Carolina | AL10: =IFERROR(__xludf.DUMMYFUNCTION("""COMPUTED_VALUE"""),"TIENE FOTOS") -> TIENE FOTOS | AM10: =IFERROR(__xludf.DUMMYFUNCTION("""COMPUTED_VALUE"""),3.212323681E9) -> 3212323681 | AN10: =IFERROR(__xludf.DUMMYFUNCTION("""COMPUTED_VALUE"""),3.135781638E9) -> 3135781638 | AP10: =IFERROR(__xludf.DUMMYFUNCTION("""COMPUTED_VALUE"""),"CALLE 57 A No. 19 - 58") -> CALLE 57 A No. 19 - 58 | AS10: =IFERROR(__xludf.DUMMYFUNCTION("""COMPUTED_VALUE"""),0.0) -> 0 | AT10: =IFERROR(__xludf.DUMMYFUNCTION("""COMPUTED_VALUE"""),0.0) -> 0 | AU10: =IFERROR(__xludf.DUMMYFUNCTION("""COMPUTED_VALUE"""),0.0) -> 0 | AV10: =IFERROR(__xludf.DUMMYFUNCTION("""COMPUTED_VALUE"""),0.0) -> 0 | AW10: =IFERROR(__xludf.DUMMYFUNCTION("""COMPUTED_VALUE"""),"NO") -> NO | AX10: =IFERROR(__xludf.DUMMYFUNCTION("""COMPUTED_VALUE"""),0.0) -> 0 | AY10: =IFERROR(__xludf.DUMMYFUNCTION("""COMPUTED_VALUE"""),0.0) -> 0 | AZ10: =IFERROR(__xludf.DUMMYFUNCTION("""COMPUTED_VALUE"""),0.0) -> 0 | BA10: =IFERROR(__xludf.DUMMYFUNCTION("""COMPUTED_VALUE"""),"X") -> X | BB10: =IFERROR(__xludf.DUMMYFUNCTION("""COMPUTED_VALUE"""),0.0) -> 0 | BF10: =IFERROR(__xludf.DUMMYFUNCTION("""COMPUTED_VALUE"""),"https://lh3.googleusercontent.com/pw/AP1GczNbZI_lSYLTL-CrUJ9U8PEl4ZvAcSMW3aoRrlKpsMsftPe390opxMC_L9jdX4v8092eMISww4KJQTW-4AKIzP7uw2UmQMbTOlqJhR4GMeh2GemZbN7m=w1200|https://lh3.googleusercontent.com/pw/AP1GczNLsRhuKz24_WrvJ08qr4rP93ZxHEO-iYPsY7lJsK8sEG4qZe"&"4Vb4t1LjyOJBDxzEE6Qf6QJCddhfg7idaWQtIfq9pxUBne4rTIfTgTELSv3BDo2Mew=w1200|https://lh3.googleusercontent.com/pw/AP1GczP_lRJ645jxrxRav7ulLog4JHKQs1eWkczZSPN6E-VZT8fRO83kVf1dju6LHU0_3HB2eUkKtTNTmcnVi5NMtEQmf2gxs3v64gj1idn1PlkoKxOT0wgi=w1200|https://lh3.google"&"usercontent.com/pw/AP1GczMucjKnk2USZ0kXDpOgCs6iH2pbu0QTlMPDy2npE1ap5JWDw9t3CGyaiSxk-JgYAtyv9VOWazSSO2hkn980vXuJ-THCfWQ1PFV6bZ5wH5HqolCkjHPa=w1200|https://lh3.googleusercontent.com/pw/AP1GczN0_amNhR8E9CUV_HT0URsqrYsRJsrNgeZIaAAB_-HoNnJI8h7-7yqd_R5RBisQniyk"&"PTJwwtQJgWpUUwrIIAvozqTuSB98xb70tUOOvdAXWpkhLu6x=w1200|https://lh3.googleusercontent.com/pw/AP1GczMyEg02Eh2U-DlRcCQ83a5eF4FHuaSa5iUEQbGiG4ajp8ytuDQ5X9s8FpiGhJySjg_1g097ME5XMITFvJrZhlxW40hJedY2hMmceah7AgszVnCNI1Js=w1200|https://lh3.googleusercontent.com/pw"&"/AP1GczMCzAKGdZWGOVK_uwEVnbyhWvt0Obu-ErBVmSwsi_bt1-gyX18GSFIMjN9Qz4FHIJQ3ztKcCO5vfHC8tt2s9d5Lq8IweFqerkkfD7dz-D4jUpFfwdy_=w1200|https://lh3.googleusercontent.com/pw/AP1GczP3Hw1OmvKOmus55fkpD6dQEORerMPhawjKqz-9g9sQWj3oD9HdbMsU8dcjmuND65qh1syo04BagQrd8Jqbro"&"xr5ifmdgc0h-MASt9nG9LVlVwrRNrW=w1200|https://lh3.googleusercontent.com/pw/AP1GczPlszP9FYaEcQFAzCUFJ5AuTz_ncpzmqWXOAgl3JKqF3TWkb6MnbBe_ogXI-d_QwUXAKLfg1FO3yr4vLvtvYrVqplq29NQmpdlvx71SpaBK2ujoDQ-W=w1200|https://lh3.googleusercontent.com/pw/AP1GczPpzdwX9-0OO"&"Hg6R4g771924PdGEfS8gNDM5mLKhzHS8AzM5lgz_fEkg6HQUmoNMXeUMDq35QY9ZObclPbYplAxpbUZ86frDG38fulGaS2xXNOd_sEf=w1200|https://lh3.googleusercontent.com/pw/AP1GczNn27UY_7yLkj5PkDTuTf1Le3wWD6guFF1b13MBfVKLTvoiRiH9fYsdzLb9hwsjgO9jgBCs6PBIF6lN89N517PZIoQWBpuYu2XXZWoX"&"MsmZKz6hU8dW=w1200|https://lh3.googleusercontent.com/pw/AP1GczMFT0E1G9qJITpQyWoIir2Vr12j8qqgPDSW5-suOr49NMa9CxI05mII8WBmKHCAYz8xNFvYqV4zUHDxtidtrKCry_bALVX9zg1yAVzGi_aA1Iood_MM=w1200|https://lh3.googleusercontent.com/pw/AP1GczNWtu_vBMfy5G-yncRKwF2DFzxY0z2"&"Cp_3a0aY6vlGU0BWBlOrlnMoo5MRx2XIu3XwnB9UdtEeaKWZaiYFK32Wv04Z-f0ufZm5kTrebHeewyAnuypYe=w1200|https://lh3.googleusercontent.com/pw/AP1GczN7bsYcnsC3xEXQl7Sh2zjiROOJ25RYDocmKmW1t3bOeFy4wDVPdtF6ULSBrQFDbxKw70XknCDm3w6IkdSeUDj4OaeZ_hDLbOrWOTYxqyG-mxJ4cDvo=w1200"&"|https://lh3.googleusercontent.com/pw/AP1GczOySQgh-0DuDeYRh93vzQzIJUH_8uz62tqJsNcjqnTAT9vmfs3t93tFs_Nyq7Xl1u2KfBVi16o3pXG3nmPjGy8CsJFq2sv7KKUvCK1SvzvOQ9hbilMV=w1200|https://lh3.googleusercontent.com/pw/AP1GczMR4cm9rOHzKKtMKz6KRu-x7GMthWFi2JNb_TzfTeRNEEebR"&"1iqDwhO1hF-LFqIHOTOpGIFwG2Th9vuMzu0Z6e0htYZjSGfcOfavYInxqpyCXIY_7BR=w1200|https://lh3.googleusercontent.com/pw/AP1GczOs2lwPpJ1CrBPjigAdhi-lHfmDtU3Smh3FlA2HotQRcIqtxopMqGByZVS6F2HyiFeM0jvagGy6Ja3g_cbTYier2rKvKOGfkWT8mfLttH4zapJ4fG1x=w1200|https://lh3.googl"&"eusercontent.com/pw/AP1GczMy2QYjL2G_BoWM0IxjFGSCZ_JcXT7IV7LD1c2UKMk-W90VkqYgGGNCS5ycKaeXq1QOjjG0cXvSfsd5B9hbLGu_M6h9roTAX3-tTuZ-yFA1WYrWX2sd=w1200|https://lh3.googleusercontent.com/pw/AP1GczOJwvm-GGhWENxgFqXjNOZ2AU5cXwuBWLfSaZsR9suHFRc3B7JwUzp0zGdcFw8RAfj"&"85ZQxP_M0V2582CQrMivNt871Y8TpSaLRTChy6dmTTQ6kCvWC=w1200") -> https://lh3.googleusercontent.com/pw/AP1GczNbZI_lSYLTL-CrUJ9U8PEl4ZvAcSMW3aoRrlKpsMsftPe390opxMC_L9jdX4v8092eMISww4KJQTW-4AKIzP7uw2UmQMbTOlqJhR4GMeh2GemZbN7m=w1200|https://lh3.googleusercontent.com/pw/AP1GczNLsRhuKz24_WrvJ08qr4rP93ZxHEO-iYPsY7lJsK8sEG4qZe4Vb4t1LjyOJBDxzEE6Qf6QJCddhfg7idaWQtIfq9pxUBne4rTIfTgTELSv3BDo2Mew=w1200|https://lh3.googleusercontent.com/pw/AP1GczP_lRJ645jxrxRav7ulLog4JHKQs1eWkczZSPN6E-VZT8fRO83kVf1dju6LHU0_3HB2eUkKtTNTmcnVi5NMtEQmf2gxs3v64gj1idn1PlkoKxOT0wgi=w1200|https://lh3.googleusercontent.com/pw/AP1GczMucjKnk2USZ0kXDpOgCs6iH2pbu0QTlMPDy2npE1ap5JWDw9t3CGyaiSxk-JgYAtyv9VOWazSSO2hkn980vXuJ-THCfWQ1PFV6bZ5wH5HqolCkjHPa=w1200|https://lh3.googleusercontent.com/pw/AP1GczN0_amNhR8E9CUV_HT0URsqrYsRJsrNgeZIaAAB_-HoNnJI8h7-7yqd_R5RBisQniykPTJwwtQJgWpUUwrIIAvozqTuSB98xb70tUOOvdAXWpkhLu6x=w1200|https://lh3.googleusercontent.com/pw/AP1GczMyEg02Eh2U-DlRcCQ83a5eF4FHuaSa5iUEQbGiG4ajp8ytuDQ5X9s8FpiGhJySjg_1g097ME5XMITFvJrZhlxW40hJedY2hMmceah7AgszVnCNI1Js=w1200|https://lh3.googleusercontent.com/pw/AP1GczMCzAKGdZWGOVK_uwEVnbyhWvt0Obu-ErBVmSwsi_bt1-gyX18GSFIMjN9Qz4FHIJQ3ztKcCO5vfHC8tt2s9d5Lq8IweFqerkkfD7dz-D4jUpFfwdy_=w1200|https://lh3.googleusercontent.com/pw/AP1GczP3Hw1OmvKOmus55fkpD6dQEORerMPhawjKqz-9g9sQWj3oD9HdbMsU8dcjmuND65qh1syo04BagQrd8Jqbroxr5ifmdgc0h-MASt9nG9LVlVwrRNrW=w1200|https://lh3.googleusercontent.com/pw/AP1GczPlszP9FYaEcQFAzCUFJ5AuTz_ncpzmqWXOAgl3JKqF3TWkb6MnbBe_ogXI-d_QwUXAKLfg1FO3yr4vLvtvYrVqplq29NQmpdlvx71SpaBK2ujoDQ-W=w1200|https://lh3.googleusercontent.com/pw/AP1GczPpzdwX9-0OOHg6R4g771924PdGEfS8gNDM5mLKhzHS8AzM5lgz_fEkg6HQUmoNMXeUMDq35QY9ZObclPbYplAxpbUZ86frDG38fulGaS2xXNOd_sEf=w1200|https://lh3.googleusercontent.com/pw/AP1GczNn27UY_7yLkj5PkDTuTf1Le3wWD6guFF1b13MBfVKLTvoiRiH9fYsdzLb9hwsjgO9jgBCs6PBIF6lN89N517PZIoQWBpuYu2XXZWoXMsmZKz6hU8dW=w1200|https://lh3.googleusercontent.com/pw/AP1GczMFT0E1G9qJITpQyWoIir2Vr12j8qqgPDSW5-suOr49NMa9CxI05mII8WBmKHCAYz8xNFvYqV4zUHDxtidtrKCry_bALVX9zg1yAVzGi_aA1Iood_MM=w1200|https://lh3.googleusercontent.com/pw/AP1GczNWtu_vBMfy5G-yncRKwF2DFzxY0z2Cp_3a0aY6vlGU0BWBlOrlnMoo5MRx2XIu3XwnB9UdtEeaKWZaiYFK32Wv04Z-f0ufZm5kTrebHeewyAnuypYe=w1200|https://lh3.googleusercontent.com/pw/AP1GczN7bsYcnsC3xEXQl7Sh2zjiROOJ25RYDocmKmW1t3bOeFy4wDVPdtF6ULSBrQFDbxKw70XknCDm3w6IkdSeUDj4OaeZ_hDLbOrWOTYxqyG-mxJ4cDvo=w1200|https://lh3.googleusercontent.com/pw/AP1GczOySQgh-0DuDeYRh93vzQzIJUH_8uz62tqJsNcjqnTAT9vmfs3t93tFs_Nyq7Xl1u2KfBVi16o3pXG3nmPjGy8CsJFq2sv7KKUvCK1SvzvOQ9hbilMV=w1200|https://lh3.googleusercontent.com/pw/AP1GczMR4cm9rOHzKKtMKz6KRu-x7GMthWFi2JNb_TzfTeRNEEebR1iqDwhO1hF-LFqIHOTOpGIFwG2Th9vuMzu0Z6e0htYZjSGfcOfavYInxqpyCXIY_7BR=w1200|https://lh3.googleusercontent.com/pw/AP1GczOs2lwPpJ1CrBPjigAdhi-lHfmDtU3Smh3FlA2HotQRcIqtxopMqGByZVS6F2HyiFeM0jvagGy6Ja3g_cbTYier2rKvKOGfkWT8mfLttH4zapJ4fG1x=w1200|https://lh3.googleusercontent.com/pw/AP1GczMy2QYjL2G_BoWM0IxjFGSCZ_JcXT7IV7LD1c2UKMk-W90VkqYgGGNCS5ycKaeXq1QOjjG0cXvSfsd5B9hbLGu_M6h9roTAX3-tTuZ-yFA1WYrWX2sd=w1200|https://lh3.googleusercontent.com/pw/AP1GczOJwvm-GGhWENxgFqXjNOZ2AU5cXwuBWLfSaZsR9suHFRc3B7JwUzp0zGdcFw8RAfj85ZQxP_M0V2582CQrMivNt871Y8TpSaLRTChy6dmTTQ6kCvWC=w1200
A11: =IFERROR(__xludf.DUMMYFUNCTION("""COMPUTED_VALUE"""),"4094") -> 4094 | B11: =IFERROR(__xludf.DUMMYFUNCTION("""COMPUTED_VALUE"""),"Casa en barrio Las Granjas") -> Casa en barrio Las Granjas | C11: =IFERROR(__xludf.DUMMYFUNCTION("""COMPUTED_VALUE"""),"Casa") -> Casa | D11: =IFERROR(__xludf.DUMMYFUNCTION("""COMPUTED_VALUE"""),"Las Granjas") -> Las Granjas | F11: =IFERROR(__xludf.DUMMYFUNCTION("""COMPUTED_VALUE"""),3.5E8) -> 350000000 | G11: =IFERROR(__xludf.DUMMYFUNCTION("""COMPUTED_VALUE"""),"$300'000.000 a $400'000.000") -> $300'000.000 a $400'000.000 | J11: =IFERROR(__xludf.DUMMYFUNCTION("""COMPUTED_VALUE"""),"Norte") -> Norte | K11: =IFERROR(__xludf.DUMMYFUNCTION("""COMPUTED_VALUE"""),"2") -> 2 | L11: =IFERROR(__xludf.DUMMYFUNCTION("""COMPUTED_VALUE"""),6.0) -> 6 | N11: =IFERROR(__xludf.DUMMYFUNCTION("""COMPUTED_VALUE"""),2.0) -> 2 | O11: =IFERROR(__xludf.DUMMYFUNCTION("""COMPUTED_VALUE"""),1.0) -> 1 | P11: =IFERROR(__xludf.DUMMYFUNCTION("""COMPUTED_VALUE"""),1.0) -> 1 | R11: =IFERROR(__xludf.DUMMYFUNCTION("""COMPUTED_VALUE"""),202.24) -> 202.24 | S11: =IFERROR(__xludf.DUMMYFUNCTION("""COMPUTED_VALUE""")," ") | T11: =IFERROR(__xludf.DUMMYFUNCTION("""COMPUTED_VALUE"""),"Neiva") -> Neiva | U11: =IFERROR(__xludf.DUMMYFUNCTION("""COMPUTED_VALUE"""),"2") -> 2 | V11: =IFERROR(__xludf.DUMMYFUNCTION("""COMPUTED_VALUE"""),"Esquinera") -> Esquinera | X11: =IFERROR(__xludf.DUMMYFUNCTION("""COMPUTED_VALUE"""),0.0) -> 0 | Y11: =IFERROR(__xludf.DUMMYFUNCTION("""COMPUTED_VALUE"""),"No tiene") -> No tiene | Z11: =IFERROR(__xludf.DUMMYFUNCTION("""COMPUTED_VALUE"""),"No aplica") -> No aplica | AA11: =IFERROR(__xludf.DUMMYFUNCTION("""COMPUTED_VALUE"""),"No aplica") -> No aplica | AF11: =IFERROR(__xludf.DUMMYFUNCTION("""COMPUTED_VALUE"""),"semi-integral") -> semi-integral | AH11: =IFERROR(__xludf.DUMMYFUNCTION("""COMPUTED_VALUE"""),"Inventario") -> Inventario | AJ11: =IFERROR(__xludf.DUMMYFUNCTION("""COMPUTED_VALUE"""),"Buriticá") -> Buriticá | AK11: =IFERROR(__xludf.DUMMYFUNCTION("""COMPUTED_VALUE"""),"No aplica") -> No aplica | AM11: =IFERROR(__xludf.DUMMYFUNCTION("""COMPUTED_VALUE"""),3.204643026E9) -> 3204643026 | AN11: =IFERROR(__xludf.DUMMYFUNCTION("""COMPUTED_VALUE"""),3.165286933E9) -> 3165286933 | AP11: =IFERROR(__xludf.DUMMYFUNCTION("""COMPUTED_VALUE"""),"Calle 38 # 8-04") -> Calle 38 # 8-04 | AS11: =IFERROR(__xludf.DUMMYFUNCTION("""COMPUTED_VALUE"""),0.0) -> 0 | AT11: =IFERROR(__xludf.DUMMYFUNCTION("""COMPUTED_VALUE"""),0.0) -> 0 | AU11: =IFERROR(__xludf.DUMMYFUNCTION("""COMPUTED_VALUE"""),0.0) -> 0 | AV11: =IFERROR(__xludf.DUMMYFUNCTION("""COMPUTED_VALUE"""),0.0) -> 0 | AW11: =IFERROR(__xludf.DUMMYFUNCTION("""COMPUTED_VALUE"""),"NO") -> NO | AX11: =IFERROR(__xludf.DUMMYFUNCTION("""COMPUTED_VALUE"""),0.0) -> 0 | AY11: =IFERROR(__xludf.DUMMYFUNCTION("""COMPUTED_VALUE"""),"P") -> P | BA11: =IFERROR(__xludf.DUMMYFUNCTION("""COMPUTED_VALUE"""),"X") -> X | BC11: =IFERROR(__xludf.DUMMYFUNCTION("""COMPUTED_VALUE"""),"12 - LEIDY YULIETH") -> 12 - LEIDY YULIETH
A12: =IFERROR(__xludf.DUMMYFUNCTION("""COMPUTED_VALUE"""),"3997") -> 3997 | B12: =IFERROR(__xludf.DUMMYFUNCTION("""COMPUTED_VALUE"""),"Casa en barrio Los Cámbulos II") -> Casa en barrio Los Cámbulos II | C12: =IFERROR(__xludf.DUMMYFUNCTION("""COMPUTED_VALUE"""),"Casa") -> Casa | D12: =IFERROR(__xludf.DUMMYFUNCTION("""COMPUTED_VALUE"""),"Los Cámbulos II") -> Los Cámbulos II | F12: =IFERROR(__xludf.DUMMYFUNCTION("""COMPUTED_VALUE"""),3.2E8) -> 320000000 | G12: =IFERROR(__xludf.DUMMYFUNCTION("""COMPUTED_VALUE"""),"$300'000.000 a $400'000.000") -> $300'000.000 a $400'000.000 | J12: =IFERROR(__xludf.DUMMYFUNCTION("""COMPUTED_VALUE"""),"Norte") -> Norte | K12: =IFERROR(__xludf.DUMMYFUNCTION("""COMPUTED_VALUE"""),"2") -> 2 | L12: =IFERROR(__xludf.DUMMYFUNCTION("""COMPUTED_VALUE"""),4.0) -> 4 | N12: =IFERROR(__xludf.DUMMYFUNCTION("""COMPUTED_VALUE"""),2.0) -> 2 | O12: =IFERROR(__xludf.DUMMYFUNCTION("""COMPUTED_VALUE"""),1.0) -> 1 | P12: =IFERROR(__xludf.DUMMYFUNCTION("""COMPUTED_VALUE"""),2.0) -> 2 | R12: =IFERROR(__xludf.DUMMYFUNCTION("""COMPUTED_VALUE"""),84.0) -> 84 | S12: =IFERROR(__xludf.DUMMYFUNCTION("""COMPUTED_VALUE""")," ") | T12: =IFERROR(__xludf.DUMMYFUNCTION("""COMPUTED_VALUE"""),"Neiva") -> Neiva | U12: =IFERROR(__xludf.DUMMYFUNCTION("""COMPUTED_VALUE"""),"3") -> 3 | V12: =IFERROR(__xludf.DUMMYFUNCTION("""COMPUTED_VALUE"""),"Medianera") -> Medianera | X12: =IFERROR(__xludf.DUMMYFUNCTION("""COMPUTED_VALUE"""),3.0) -> 3 | Y12: =IFERROR(__xludf.DUMMYFUNCTION("""COMPUTED_VALUE"""),"No tiene") -> No tiene | Z12: =IFERROR(__xludf.DUMMYFUNCTION("""COMPUTED_VALUE"""),"No aplica") -> No aplica | AA12: =IFERROR(__xludf.DUMMYFUNCTION("""COMPUTED_VALUE"""),"No aplica") -> No aplica | AF12: =IFERROR(__xludf.DUMMYFUNCTION("""COMPUTED_VALUE"""),"integral") -> integral | AH12: =IFERROR(__xludf.DUMMYFUNCTION("""COMPUTED_VALUE"""),"Inventario") -> Inventario | AJ12: =IFERROR(__xludf.DUMMYFUNCTION("""COMPUTED_VALUE"""),"Buriticá") -> Buriticá | AK12: =IFERROR(__xludf.DUMMYFUNCTION("""COMPUTED_VALUE"""),"No aplica") -> No aplica | AM12: =IFERROR(__xludf.DUMMYFUNCTION("""COMPUTED_VALUE"""),3.204643026E9) -> 3204643026 | AN12: =IFERROR(__xludf.DUMMYFUNCTION("""COMPUTED_VALUE"""),3.165286933E9) -> 3165286933 | AP12: =IFERROR(__xludf.DUMMYFUNCTION("""COMPUTED_VALUE"""),"Carrera 12 # 27-38") -> Carrera 12 # 27-38 | AT12: =IFERROR(__xludf.DUMMYFUNCTION("""COMPUTED_VALUE"""),0.0) -> 0 | AU12: =IFERROR(__xludf.DUMMYFUNCTION("""COMPUTED_VALUE"""),0.0) -> 0 | AV12: =IFERROR(__xludf.DUMMYFUNCTION("""COMPUTED_VALUE"""),0.0) -> 0 | AW12: =IFERROR(__xludf.DUMMYFUNCTION("""COMPUTED_VALUE"""),"SI") -> SI | AX12: =IFERROR(__xludf.DUMMYFUNCTION("""COMPUTED_VALUE"""),0.0) -> 0 | AY12: =IFERROR(__xludf.DUMMYFUNCTION("""COMPUTED_VALUE"""),"P") -> P | BA12: =IFERROR(__xludf.DUMMYFUNCTION("""COMPUTED_VALUE"""),"X") -> X
A13: =IFERROR(__xludf.DUMMYFUNCTION("""COMPUTED_VALUE"""),"3384") -> 3384 | B13: =IFERROR(__xludf.DUMMYFUNCTION("""COMPUTED_VALUE"""),"Casa en barrio Los Molinos") -> Casa en barrio Los Molinos | C13: =IFERROR(__xludf.DUMMYFUNCTION("""COMPUTED_VALUE"""),"Casa") -> Casa | D13: =IFERROR(__xludf.DUMMYFUNCTION("""COMPUTED_VALUE"""),"Los Molinos") -> Los Molinos | F13: =IFERROR(__xludf.DUMMYFUNCTION("""COMPUTED_VALUE"""),2.6E8) -> 260000000 | G13: =IFERROR(__xludf.DUMMYFUNCTION("""COMPUTED_VALUE"""),"$200'000.000 a $300'000.000") -> $200'000.000 a $300'000.000 | J13: =IFERROR(__xludf.DUMMYFUNCTION("""COMPUTED_VALUE"""),"Norte") -> Norte | K13: =IFERROR(__xludf.DUMMYFUNCTION("""COMPUTED_VALUE"""),"2") -> 2 | L13: =IFERROR(__xludf.DUMMYFUNCTION("""COMPUTED_VALUE"""),3.0) -> 3 | N13: =IFERROR(__xludf.DUMMYFUNCTION("""COMPUTED_VALUE"""),3.0) -> 3 | O13: =IFERROR(__xludf.DUMMYFUNCTION("""COMPUTED_VALUE"""),1.0) -> 1 | P13: =IFERROR(__xludf.DUMMYFUNCTION("""COMPUTED_VALUE"""),2.0) -> 2 | Q13: =IFERROR(__xludf.DUMMYFUNCTION("""COMPUTED_VALUE"""),155.0) -> 155 | R13: =IFERROR(__xludf.DUMMYFUNCTION("""COMPUTED_VALUE"""),90.0) -> 90 | S13: =IFERROR(__xludf.DUMMYFUNCTION("""COMPUTED_VALUE""")," ") | T13: =IFERROR(__xludf.DUMMYFUNCTION("""COMPUTED_VALUE"""),"Neiva") -> Neiva | U13: =IFERROR(__xludf.DUMMYFUNCTION("""COMPUTED_VALUE"""),"4") -> 4 | V13: =IFERROR(__xludf.DUMMYFUNCTION("""COMPUTED_VALUE"""),"Medianera") -> Medianera | X13: =IFERROR(__xludf.DUMMYFUNCTION("""COMPUTED_VALUE"""),3.0) -> 3 | Y13: =IFERROR(__xludf.DUMMYFUNCTION("""COMPUTED_VALUE"""),"No tiene") -> No tiene | Z13: =IFERROR(__xludf.DUMMYFUNCTION("""COMPUTED_VALUE"""),"No aplica") -> No aplica | AA13: =IFERROR(__xludf.DUMMYFUNCTION("""COMPUTED_VALUE"""),"No aplica") -> No aplica | AF13: =IFERROR(__xludf.DUMMYFUNCTION("""COMPUTED_VALUE"""),"integral") -> integral | AH13: =IFERROR(__xludf.DUMMYFUNCTION("""COMPUTED_VALUE"""),"Inventario") -> Inventario | AJ13: =IFERROR(__xludf.DUMMYFUNCTION("""COMPUTED_VALUE"""),"Buriticá") -> Buriticá | AL13: =IFERROR(__xludf.DUMMYFUNCTION("""COMPUTED_VALUE"""),"TIENE FOTOS") -> TIENE FOTOS | AM13: =IFERROR(__xludf.DUMMYFUNCTION("""COMPUTED_VALUE"""),3.212323681E9) -> 3212323681 | AN13: =IFERROR(__xludf.DUMMYFUNCTION("""COMPUTED_VALUE"""),3.135781638E9) -> 3135781638 | AP13: =IFERROR(__xludf.DUMMYFUNCTION("""COMPUTED_VALUE"""),"CALLE 36 No. 8F - 90") -> CALLE 36 No. 8F - 90 | AS13: =IFERROR(__xludf.DUMMYFUNCTION("""COMPUTED_VALUE"""),0.0) -> 0 | AT13: =IFERROR(__xludf.DUMMYFUNCTION("""COMPUTED_VALUE"""),0.0) -> 0 | AU13: =IFERROR(__xludf.DUMMYFUNCTION("""COMPUTED_VALUE"""),0.0) -> 0 | AV13: =IFERROR(__xludf.DUMMYFUNCTION("""COMPUTED_VALUE"""),0.0) -> 0 | AW13: =IFERROR(__xludf.DUMMYFUNCTION("""COMPUTED_VALUE"""),"NO") -> NO | AX13: =IFERROR(__xludf.DUMMYFUNCTION("""COMPUTED_VALUE"""),0.0) -> 0 | AY13: =IFERROR(__xludf.DUMMYFUNCTION("""COMPUTED_VALUE"""),0.0) -> 0 | AZ13: =IFERROR(__xludf.DUMMYFUNCTION("""COMPUTED_VALUE"""),0.0) -> 0 | BA13: =IFERROR(__xludf.DUMMYFUNCTION("""COMPUTED_VALUE"""),"X") -> X | BB13: =IFERROR(__xludf.DUMMYFUNCTION("""COMPUTED_VALUE"""),0.0) -> 0 | BC13: =IFERROR(__xludf.DUMMYFUNCTION("""COMPUTED_VALUE"""),"35 - LUIS ANGEL VARGAS") -> 35 - LUIS ANGEL VARGAS
A14: =IFERROR(__xludf.DUMMYFUNCTION("""COMPUTED_VALUE"""),"1246") -> 1246 | B14: =IFERROR(__xludf.DUMMYFUNCTION("""COMPUTED_VALUE"""),"Casa con dos apartamentos y tres oficinas en barrio La Toma") -> Casa con dos apartamentos y tres oficinas en barrio La Toma | C14: =IFERROR(__xludf.DUMMYFUNCTION("""COMPUTED_VALUE"""),"Casa rentable") -> Casa rentable | D14: =IFERROR(__xludf.DUMMYFUNCTION("""COMPUTED_VALUE"""),"La Toma") -> La Toma | E14: =IFERROR(__xludf.DUMMYFUNCTION("""COMPUTED_VALUE""")," ") | F14: =IFERROR(__xludf.DUMMYFUNCTION("""COMPUTED_VALUE"""),8.0E8) -> 800000000 | G14: =IFERROR(__xludf.DUMMYFUNCTION("""COMPUTED_VALUE"""),"$500'000.000 a $1.000'000.000") -> $500'000.000 a $1.000'000.000 | J14: =IFERROR(__xludf.DUMMYFUNCTION("""COMPUTED_VALUE"""),"Centro") -> Centro | K14: =IFERROR(__xludf.DUMMYFUNCTION("""COMPUTED_VALUE"""),"3") -> 3 | L14: =IFERROR(__xludf.DUMMYFUNCTION("""COMPUTED_VALUE"""),9.0) -> 9 | N14: =IFERROR(__xludf.DUMMYFUNCTION("""COMPUTED_VALUE"""),5.0) -> 5 | O14: =IFERROR(__xludf.DUMMYFUNCTION("""COMPUTED_VALUE"""),3.0) -> 3 | P14: =IFERROR(__xludf.DUMMYFUNCTION("""COMPUTED_VALUE"""),3.0) -> 3 | R14: =IFERROR(__xludf.DUMMYFUNCTION("""COMPUTED_VALUE"""),121.0) -> 121 | S14: =IFERROR(__xludf.DUMMYFUNCTION("""COMPUTED_VALUE"""),"Rentabilidad $2,300,000") -> Rentabilidad $2,300,000 | T14: =IFERROR(__xludf.DUMMYFUNCTION("""COMPUTED_VALUE"""),"Neiva") -> Neiva | U14: =IFERROR(__xludf.DUMMYFUNCTION("""COMPUTED_VALUE"""),"3") -> 3 | V14: =IFERROR(__xludf.DUMMYFUNCTION("""COMPUTED_VALUE"""),"Medianera") -> Medianera | X14: =IFERROR(__xludf.DUMMYFUNCTION("""COMPUTED_VALUE"""),6.0) -> 6 | Y14: =IFERROR(__xludf.DUMMYFUNCTION("""COMPUTED_VALUE"""),"No tiene") -> No tiene | Z14: =IFERROR(__xludf.DUMMYFUNCTION("""COMPUTED_VALUE"""),"No aplica") -> No aplica | AA14: =IFERROR(__xludf.DUMMYFUNCTION("""COMPUTED_VALUE"""),"29 años") -> 29 años | AB14: =IFERROR(__xludf.DUMMYFUNCTION("""COMPUTED_VALUE"""),"https://photos.app.goo.gl/ifKcNM57JsW8PTto8") -> https://photos.app.goo.gl/ifKcNM57JsW8PTto8 | AC14: =IFERROR(__xludf.DUMMYFUNCTION("""COMPUTED_VALUE"""),"Se Vende casa de 3 pisos con un área de 121 m2 consta: Primer piso: 3 oficinas, baño privado, baño auxiliar, 3 parqueaderos. Segundo piso: 3 habitaciones, baño privado, baño auxiliar, 3 closets de madera, 2 A.A, cocina integral,"&" la divisiones de los baños son en vidrios, sala comedor, patio de ropas, zona de lavandería. Tercer piso: 3 habitaciones, sala comedor, baño privado, baño auxiliar, 3 closets de madera, 1 A.A, cocina semiintegral, el baño auxiliar tiene divisiones "&"en vidrio,patio de ropas, zona de lavandería, garaje.") -> Se Vende casa de 3 pisos con un área de 121 m2 consta: Primer piso: 3 oficinas, baño privado, baño auxiliar, 3 parqueaderos. Segundo piso: 3 habitaciones, baño privado, baño auxiliar, 3 closets de madera, 2 A.A, cocina integral, la divisiones de los baños son en vidrios, sala comedor, patio de ropas, zona de lavandería. Tercer piso: 3 habitaciones, sala comedor, baño privado, baño auxiliar, 3 closets de madera, 1 A.A, cocina semiintegral, el baño auxiliar tiene divisiones en vidrio,patio de ropas, zona de lavandería, garaje. | AF14: =IFERROR(__xludf.DUMMYFUNCTION("""COMPUTED_VALUE"""),"semi-integral") -> semi-integral | AG14: =IFERROR(__xludf.DUMMYFUNCTION("""COMPUTED_VALUE"""),"SI") -> SI | AH14: =IFERROR(__xludf.DUMMYFUNCTION("""COMPUTED_VALUE"""),"Inventario") -> Inventario | AI14: =IFERROR(__xludf.DUMMYFUNCTION("""COMPUTED_VALUE"""),"Aliado") -> Aliado | AJ14: =IFERROR(__xludf.DUMMYFUNCTION("""COMPUTED_VALUE"""),"C&C") -> C&C | AK14: =IFERROR(__xludf.DUMMYFUNCTION("""COMPUTED_VALUE"""),"No aplica") -> No aplica | AL14: =IFERROR(__xludf.DUMMYFUNCTION("""COMPUTED_VALUE"""),"TIENE FOTOS") -> TIENE FOTOS | AM14: =IFERROR(__xludf.DUMMYFUNCTION("""COMPUTED_VALUE"""),3.13351965E9) -> 3133519650 | AN14: =IFERROR(__xludf.DUMMYFUNCTION("""COMPUTED_VALUE"""),0.0) -> 0 | AP14: =IFERROR(__xludf.DUMMYFUNCTION("""COMPUTED_VALUE"""),"CARRERA 7A No. 13-27") -> CARRERA 7A No. 13-27 | AQ14: =IFERROR(__xludf.DUMMYFUNCTION("""COMPUTED_VALUE"""),2.9323784) -> 2.9323784 | AR14: =IFERROR(__xludf.DUMMYFUNCTION("""COMPUTED_VALUE"""),-75.2875936) -> -75.287594 | AS14: =IFERROR(__xludf.DUMMYFUNCTION("""COMPUTED_VALUE"""),2300000.0) -> 2300000 | AT14: =IFERROR(__xludf.DUMMYFUNCTION("""COMPUTED_VALUE"""),0.0) -> 0 | AU14: =IFERROR(__xludf.DUMMYFUNCTION("""COMPUTED_VALUE"""),"NO") -> NO | AV14: =IFERROR(__xludf.DUMMYFUNCTION("""COMPUTED_VALUE"""),0.0) -> 0 | AW14: =IFERROR(__xludf.DUMMYFUNCTION("""COMPUTED_VALUE"""),"SI") -> SI | AX14: =IFERROR(__xludf.DUMMYFUNCTION("""COMPUTED_VALUE"""),0.0) -> 0 | AY14: =IFERROR(__xludf.DUMMYFUNCTION("""COMPUTED_VALUE"""),"P") -> P | AZ14: =IFERROR(__xludf.DUMMYFUNCTION("""COMPUTED_VALUE"""),0.0) -> 0 | BA14: =IFERROR(__xludf.DUMMYFUNCTION("""COMPUTED_VALUE"""),"X") -> X | BB14: =IFERROR(__xludf.DUMMYFUNCTION("""COMPUTED_VALUE"""),0.0) -> 0 | BC14: =IFERROR(__xludf.DUMMYFUNCTION("""COMPUTED_VALUE"""),"2 - JAIRO DIAZ, 7 - ROCIO YAGUARA VELA, NUBIA DIAZ, 22 - JOSE LUIS OYOLA, 12 - LEIDY YULIETH") -> 2 - JAIRO DIAZ, 7 - ROCIO YAGUARA VELA, NUBIA DIAZ, 22 - JOSE LUIS OYOLA, 12 - LEIDY YULIETH | BF14: =IFERROR(__xludf.DUMMYFUNCTION("""COMPUTED_VALUE"""),"https://lh3.googleusercontent.com/pw/AP1GczNc9V_zOX1I5Vo0-TJMJZPQnsUyo5dHvS45ar1gHQNmgLOlf9BhkBu3Jsu1u0vgPqSthU61tk05uH31jOQmKRu-yj2IzIxmSTPYkfV90qard0F76CqE=w1200|https://lh3.googleusercontent.com/pw/AP1GczM_vrVuds_4Xn5s3EpZn8nTSbiMN_4xRJoHK6syWY70YPjIjw"&"lpvpTe76VHFeK0qETMjXytkFdvwfR05rsjCN96-ML0zUXec5iJzPtBv6C23oncxzvU=w1200|https://lh3.googleusercontent.com/pw/AP1GczMUzsCUU7xlyTPUE1LU0gpMjepnJnAbDPPhbHkA09QQqrJrwXb3RiOdCOmHd6cZuClMtt8NC5Gqtio_-sB5BMXuDm7ivwoaYs1wQPHNz_bam4bReEJA=w1200|https://lh3.google"&"usercontent.com/pw/AP1GczMG_jbiCM-pEj1_r1dED_h5qgbv-L88KdTckPSZxGLqYErGnkZNwhorjnVtGUHOdLfePzuLWDFNtWVqByTngNfhCrWsmK3NSLqZ_BUwZiGfEKZfLAWX=w1200|https://lh3.googleusercontent.com/pw/AP1GczNQ_--b9jbZcGUMSMwpunX1kMZiVWTFCpjQNf2nrlrN4NQkJaxLGvGMwU0GC1P1bQpC"&"m0bxaEy4ep9cV2ulkPuHRNn_efD4oUA430rKsvJIrgLSDfUh=w1200|https://lh3.googleusercontent.com/pw/AP1GczMplg7WAe0RcdAP1bRlXkUQCqtSXhNjGxitCWZa9C6h0ZzyawNPVWbPuE_1hdGQisevnhGFL415SKQaepPlxNqHZBOdzFi8PFeORk0__fvKWLyVYAJ7=w1200|https://lh3.googleusercontent.com/pw"&"/AP1GczP0E9UY-jzh_i78FjIkoRZBR867FOFLPVuhcuT4ZFQqTk4WEYlQ5vFO6GuZWCkkCfW8B9TFQA64urTDyp34TC8k5S-20OweQl831p6ZODOnfaukyKXX=w1200|https://lh3.googleusercontent.com/pw/AP1GczMFbDWi4BgICAdAA0d0FHvli9abwy7ywGe4DyS1XD5vosYRLynBVN9gszL43_qoZMJCSRlzu4yrrzyCJmtxb9"&"NF575p8TGgH7o9VhXbnHpG4E0b6I3D=w1200|https://lh3.googleusercontent.com/pw/AP1GczMwa7vZzb-Mxdgu6HoBFK4ygSbpV6Y_ayUqLtl8p_7B17YIQNy9zNRQTBAvR4JQN3_SCDuafRgRx7pFLmE5V2sDHGSUnC4LVrAZ2zi3raCUkZH29n7J=w1200|https://lh3.googleusercontent.com/pw/AP1GczMflwtWuopM4"&"VI_5Y4XJIJd9ujybfsQ62s1yGWETEqHw6YtPqRglcdUEc8hF9znUFzbp6mWKRfyu5D4uynB_XzR27k9Wd4krAJJQKvPFJGKSN87pI9N=w1200|https://lh3.googleusercontent.com/pw/AP1GczN6f3RS_tBt_Kf__y8_w76R_ftRx_CwDxIh8eGaHg_NjxQ1SIdDS3jhBRcQ9bsWxG1IGbkz1WRzF3HxpBrWTRNfVouwpse4OE7-HiwQ"&"ozHlF4Var59h=w1200|https://lh3.googleusercontent.com/pw/AP1GczOuouHUYqJwV0L9gxYqtpcrkF1JduK2jLDwbtk0YU7Fqc4evxhyIqTnqte60OaPGYOSC32EmiCbuLmwB4FBLHIbTajCQFEliTzQosltAJWFpurOnITX=w1200|https://lh3.googleusercontent.com/pw/AP1GczPem6fsrEpGb_X-JjtyEQcO6GPnDNp"&"COy5jGkk4ci25kpe9dkN4sDfcDopOznjC9k9SokVvTpbjs1iytJuXqSYO8HFtUi3YWF2BMgR0UwwqMNSidzrS=w1200|https://lh3.googleusercontent.com/pw/AP1GczOF6MAvHp0jVYty0uT3aJNB0l9XY9ViwzL0qOC__EvWo1RSLf8OIameA1ANqvybKLJX_5heRrJwwA3-MpXs8zvj-vQK5rtOx7KU0RN1_pea_uZjkq0G=w1200"&"|https://lh3.googleusercontent.com/pw/AP1GczNp7EiaFXurdX_5uAH2lfQ02jNx8dnoyZbDjaBpircYno1zwUWquYElLpV1qm93KclVLIyUCqHom5hOoKG-GwCzuH1Ln8TjsuEzdNhJ6IWydxlQxNQo=w1200|https://lh3.googleusercontent.com/pw/AP1GczPovAuwPGGGIzZKBthzoSEzjILGa0MGcjZ1GUkY3hauqngeT"&"bCl9PUae5LCRGUzLQmIj0rGSu_dAhz9EFdoRHfwFJUZTe-sTt6ZrJOdZRtMZ4xhDyXW=w1200|https://lh3.googleusercontent.com/pw/AP1GczOL-Ie6Xbiz10NvOowR1bmi5z_CUHoyqlRLTpdcFNvIAoz8x0YRsway8K9IdILkn3UMLWhn-Hub2FZeDhhcnhGZ_Xx6QUrjA8IsaT-nC546gejDUsdg=w1200|https://lh3.googl"&"eusercontent.com/pw/AP1GczNcc-36TgCoeHjDnsGuXqetTZrAV6tpF2jCcPdPqPPKmT5gliiQ6JwTmKTDV7JyihQL--F_FGtW1iTi6SnI9D9ZGr2j82DIiW-d_IS5-PaXhgx_NOhz=w1200|https://lh3.googleusercontent.com/pw/AP1GczPWxRZ-b5U9MZ8x4eyJ2PQy_jDQWFZ86n_DeP_CRtOu-CvGewMSP5Ka2tGT192_A2r"&"_sO9cdcOgdGaNUGoxH9-_nDxFEo7_a0u-QhPa2l558IOUsHri=w1200") -> https://lh3.googleusercontent.com/pw/AP1GczNc9V_zOX1I5Vo0-TJMJZPQnsUyo5dHvS45ar1gHQNmgLOlf9BhkBu3Jsu1u0vgPqSthU61tk05uH31jOQmKRu-yj2IzIxmSTPYkfV90qard0F76CqE=w1200|https://lh3.googleusercontent.com/pw/AP1GczM_vrVuds_4Xn5s3EpZn8nTSbiMN_4xRJoHK6syWY70YPjIjwlpvpTe76VHFeK0qETMjXytkFdvwfR05rsjCN96-ML0zUXec5iJzPtBv6C23oncxzvU=w1200|https://lh3.googleusercontent.com/pw/AP1GczMUzsCUU7xlyTPUE1LU0gpMjepnJnAbDPPhbHkA09QQqrJrwXb3RiOdCOmHd6cZuClMtt8NC5Gqtio_-sB5BMXuDm7ivwoaYs1wQPHNz_bam4bReEJA=w1200|https://lh3.googleusercontent.com/pw/AP1GczMG_jbiCM-pEj1_r1dED_h5qgbv-L88KdTckPSZxGLqYErGnkZNwhorjnVtGUHOdLfePzuLWDFNtWVqByTngNfhCrWsmK3NSLqZ_BUwZiGfEKZfLAWX=w1200|https://lh3.googleusercontent.com/pw/AP1GczNQ_--b9jbZcGUMSMwpunX1kMZiVWTFCpjQNf2nrlrN4NQkJaxLGvGMwU0GC1P1bQpCm0bxaEy4ep9cV2ulkPuHRNn_efD4oUA430rKsvJIrgLSDfUh=w1200|https://lh3.googleusercontent.com/pw/AP1GczMplg7WAe0RcdAP1bRlXkUQCqtSXhNjGxitCWZa9C6h0ZzyawNPVWbPuE_1hdGQisevnhGFL415SKQaepPlxNqHZBOdzFi8PFeORk0__fvKWLyVYAJ7=w1200|https://lh3.googleusercontent.com/pw/AP1GczP0E9UY-jzh_i78FjIkoRZBR867FOFLPVuhcuT4ZFQqTk4WEYlQ5vFO6GuZWCkkCfW8B9TFQA64urTDyp34TC8k5S-20OweQl831p6ZODOnfaukyKXX=w1200|https://lh3.googleusercontent.com/pw/AP1GczMFbDWi4BgICAdAA0d0FHvli9abwy7ywGe4DyS1XD5vosYRLynBVN9gszL43_qoZMJCSRlzu4yrrzyCJmtxb9NF575p8TGgH7o9VhXbnHpG4E0b6I3D=w1200|https://lh3.googleusercontent.com/pw/AP1GczMwa7vZzb-Mxdgu6HoBFK4ygSbpV6Y_ayUqLtl8p_7B17YIQNy9zNRQTBAvR4JQN3_SCDuafRgRx7pFLmE5V2sDHGSUnC4LVrAZ2zi3raCUkZH29n7J=w1200|https://lh3.googleusercontent.com/pw/AP1GczMflwtWuopM4VI_5Y4XJIJd9ujybfsQ62s1yGWETEqHw6YtPqRglcdUEc8hF9znUFzbp6mWKRfyu5D4uynB_XzR27k9Wd4krAJJQKvPFJGKSN87pI9N=w1200|https://lh3.googleusercontent.com/pw/AP1GczN6f3RS_tBt_Kf__y8_w76R_ftRx_CwDxIh8eGaHg_NjxQ1SIdDS3jhBRcQ9bsWxG1IGbkz1WRzF3HxpBrWTRNfVouwpse4OE7-HiwQozHlF4Var59h=w1200|https://lh3.googleusercontent.com/pw/AP1GczOuouHUYqJwV0L9gxYqtpcrkF1JduK2jLDwbtk0YU7Fqc4evxhyIqTnqte60OaPGYOSC32EmiCbuLmwB4FBLHIbTajCQFEliTzQosltAJWFpurOnITX=w1200|https://lh3.googleusercontent.com/pw/AP1GczPem6fsrEpGb_X-JjtyEQcO6GPnDNpCOy5jGkk4ci25kpe9dkN4sDfcDopOznjC9k9SokVvTpbjs1iytJuXqSYO8HFtUi3YWF2BMgR0UwwqMNSidzrS=w1200|https://lh3.googleusercontent.com/pw/AP1GczOF6MAvHp0jVYty0uT3aJNB0l9XY9ViwzL0qOC__EvWo1RSLf8OIameA1ANqvybKLJX_5heRrJwwA3-MpXs8zvj-vQK5rtOx7KU0RN1_pea_uZjkq0G=w1200|https://lh3.googleusercontent.com/pw/AP1GczNp7EiaFXurdX_5uAH2lfQ02jNx8dnoyZbDjaBpircYno1zwUWquYElLpV1qm93KclVLIyUCqHom5hOoKG-GwCzuH1Ln8TjsuEzdNhJ6IWydxlQxNQo=w1200|https://lh3.googleusercontent.com/pw/AP1GczPovAuwPGGGIzZKBthzoSEzjILGa0MGcjZ1GUkY3hauqngeTbCl9PUae5LCRGUzLQmIj0rGSu_dAhz9EFdoRHfwFJUZTe-sTt6ZrJOdZRtMZ4xhDyXW=w1200|https://lh3.googleusercontent.com/pw/AP1GczOL-Ie6Xbiz10NvOowR1bmi5z_CUHoyqlRLTpdcFNvIAoz8x0YRsway8K9IdILkn3UMLWhn-Hub2FZeDhhcnhGZ_Xx6QUrjA8IsaT-nC546gejDUsdg=w1200|https://lh3.googleusercontent.com/pw/AP1GczNcc-36TgCoeHjDnsGuXqetTZrAV6tpF2jCcPdPqPPKmT5gliiQ6JwTmKTDV7JyihQL--F_FGtW1iTi6SnI9D9ZGr2j82DIiW-d_IS5-PaXhgx_NOhz=w1200|https://lh3.googleusercontent.com/pw/AP1GczPWxRZ-b5U9MZ8x4eyJ2PQy_jDQWFZ86n_DeP_CRtOu-CvGewMSP5Ka2tGT192_A2r_sO9cdcOgdGaNUGoxH9-_nDxFEo7_a0u-QhPa2l558IOUsHri=w1200
A15: =IFERROR(__xludf.DUMMYFUNCTION("""COMPUTED_VALUE"""),"912") -> 912 | B15: =IFERROR(__xludf.DUMMYFUNCTION("""COMPUTED_VALUE"""),"Casa con un apartaestudio y dos locales en barrio Sevilla") -> Casa con un apartaestudio y dos locales en barrio Sevilla | C15: =IFERROR(__xludf.DUMMYFUNCTION("""COMPUTED_VALUE"""),"Casa rentable") -> Casa rentable | D15: =IFERROR(__xludf.DUMMYFUNCTION("""COMPUTED_VALUE"""),"Sevilla") -> Sevilla | F15: =IFERROR(__xludf.DUMMYFUNCTION("""COMPUTED_VALUE"""),6.3E8) -> 630000000 | G15: =IFERROR(__xludf.DUMMYFUNCTION("""COMPUTED_VALUE"""),"$500'000.000 a $1.000'000.000") -> $500'000.000 a $1.000'000.000 | J15: =IFERROR(__xludf.DUMMYFUNCTION("""COMPUTED_VALUE"""),"Centro") -> Centro | K15: =IFERROR(__xludf.DUMMYFUNCTION("""COMPUTED_VALUE"""),"3") -> 3 | L15: =IFERROR(__xludf.DUMMYFUNCTION("""COMPUTED_VALUE"""),6.0) -> 6 | N15: =IFERROR(__xludf.DUMMYFUNCTION("""COMPUTED_VALUE"""),4.0) -> 4 | O15: =IFERROR(__xludf.DUMMYFUNCTION("""COMPUTED_VALUE"""),1.0) -> 1 | P15: =IFERROR(__xludf.DUMMYFUNCTION("""COMPUTED_VALUE"""),1.0) -> 1 | Q15: =IFERROR(__xludf.DUMMYFUNCTION("""COMPUTED_VALUE"""),171.0) -> 171 | R15: =IFERROR(__xludf.DUMMYFUNCTION("""COMPUTED_VALUE"""),171.0) -> 171 | S15: =IFERROR(__xludf.DUMMYFUNCTION("""COMPUTED_VALUE"""),"Rentabilidad $1,500,000") -> Rentabilidad $1,500,000 | T15: =IFERROR(__xludf.DUMMYFUNCTION("""COMPUTED_VALUE"""),"Neiva") -> Neiva | U15: =IFERROR(__xludf.DUMMYFUNCTION("""COMPUTED_VALUE"""),"4") -> 4 | V15: =IFERROR(__xludf.DUMMYFUNCTION("""COMPUTED_VALUE"""),"Esquinera") -> Esquinera | X15: =IFERROR(__xludf.DUMMYFUNCTION("""COMPUTED_VALUE"""),4.0) -> 4 | Y15: =IFERROR(__xludf.DUMMYFUNCTION("""COMPUTED_VALUE"""),"No tiene") -> No tiene | Z15: =IFERROR(__xludf.DUMMYFUNCTION("""COMPUTED_VALUE"""),"No aplica") -> No aplica | AA15: =IFERROR(__xludf.DUMMYFUNCTION("""COMPUTED_VALUE"""),"35 años") -> 35 años | AB15: =IFERROR(__xludf.DUMMYFUNCTION("""COMPUTED_VALUE"""),"https://photos.app.goo.gl/xZQqFfPcjaiK5Ky9A") -> https://photos.app.goo.gl/xZQqFfPcjaiK5Ky9A | AC15: =IFERROR(__xludf.DUMMYFUNCTION("""COMPUTED_VALUE"""),"Casa esquinera con 171 mts2 estrato 2 consta de: 3 habitaciones 2 con baño, sala comedor, cocina semi-integral, zona de lavandería, patio, baño social, garaje, cuenta con 2 locales, 1 Aparta estudio con entrada independiente, pisos en cerámica, techo en M"&"achimbre tipo español.") -> Casa esquinera con 171 mts2 estrato 2 consta de: 3 habitaciones 2 con baño, sala comedor, cocina semi-integral, zona de lavandería, patio, baño social, garaje, cuenta con 2 locales, 1 Aparta estudio con entrada independiente, pisos en cerámica, techo en Machimbre tipo español. | AD15: =IFERROR(__xludf.DUMMYFUNCTION("""COMPUTED_VALUE"""),"Esquinera") -> Esquinera | AF15: =IFERROR(__xludf.DUMMYFUNCTION("""COMPUTED_VALUE"""),"semi-integral") -> semi-integral | AG15: =IFERROR(__xludf.DUMMYFUNCTION("""COMPUTED_VALUE"""),"SI") -> SI | AH15: =IFERROR(__xludf.DUMMYFUNCTION("""COMPUTED_VALUE"""),"Inventario") -> Inventario | AI15: =IFERROR(__xludf.DUMMYFUNCTION("""COMPUTED_VALUE"""),"Aliado") -> Aliado | AJ15: =IFERROR(__xludf.DUMMYFUNCTION("""COMPUTED_VALUE"""),"C&C") -> C&C | AK15: =IFERROR(__xludf.DUMMYFUNCTION("""COMPUTED_VALUE"""),"No aplica") -> No aplica | AL15: =IFERROR(__xludf.DUMMYFUNCTION("""COMPUTED_VALUE"""),"TIENE FOTOS") -> TIENE FOTOS | AM15: =IFERROR(__xludf.DUMMYFUNCTION("""COMPUTED_VALUE"""),3.13351965E9) -> 3133519650 | AN15: =IFERROR(__xludf.DUMMYFUNCTION("""COMPUTED_VALUE"""),"3012305496-3172307994 PROPIETARIO") -> 3012305496-3172307994 PROPIETARIO | AO15: =IFERROR(__xludf.DUMMYFUNCTION("""COMPUTED_VALUE"""),"PROPIETARIO IRMA - BRANT MILLER- INMOBILIARIA CASA & CASA") -> PROPIETARIO IRMA - BRANT MILLER- INMOBILIARIA CASA & CASA | AP15: =IFERROR(__xludf.DUMMYFUNCTION("""COMPUTED_VALUE"""),"CARRERA 6 NO.XXX-22") -> CARRERA 6 NO.XXX-22 | AQ15: =IFERROR(__xludf.DUMMYFUNCTION("""COMPUTED_VALUE"""),2.9386909) -> 2.9386909 | AR15: =IFERROR(__xludf.DUMMYFUNCTION("""COMPUTED_VALUE"""),-75.2902595) -> -75.29026 | AS15: =IFERROR(__xludf.DUMMYFUNCTION("""COMPUTED_VALUE"""),1500000.0) -> 1500000 | AT15: =IFERROR(__xludf.DUMMYFUNCTION("""COMPUTED_VALUE"""),0.0) -> 0 | AU15: =IFERROR(__xludf.DUMMYFUNCTION("""COMPUTED_VALUE"""),0.0) -> 0 | AV15: =IFERROR(__xludf.DUMMYFUNCTION("""COMPUTED_VALUE"""),0.0) -> 0 | AW15: =IFERROR(__xludf.DUMMYFUNCTION("""COMPUTED_VALUE"""),"NO") -> NO | AX15: =IFERROR(__xludf.DUMMYFUNCTION("""COMPUTED_VALUE"""),0.0) -> 0 | AY15: =IFERROR(__xludf.DUMMYFUNCTION("""COMPUTED_VALUE"""),"P") -> P | AZ15: =IFERROR(__xludf.DUMMYFUNCTION("""COMPUTED_VALUE"""),0.0) -> 0 | BA15: =IFERROR(__xludf.DUMMYFUNCTION("""COMPUTED_VALUE"""),"X") -> X | BB15: =IFERROR(__xludf.DUMMYFUNCTION("""COMPUTED_VALUE"""),0.0) -> 0 | BF15: =IFERROR(__xludf.DUMMYFUNCTION("""COMPUTED_VALUE"""),"https://lh3.googleusercontent.com/pw/AP1GczPLo5Q331sbe9YG4Mi9fH1FRORONzn-SYT9WOZuzs8S_AnhXRZAnas2vvJ2-Cx-cJqXSip1IyVUFFYXZi3r8TYeT4PgJNuSMmGFwnJGcXzTjN85o7Ll=w1200|https://lh3.googleusercontent.com/pw/AP1GczP7RUimfVxtA8SwNEEyyiAOEZMOgc-P9GWfe7EPd6Rer-kIg5"&"Et8H3dgSAmh1aCc21NjD9t9QWkW-1FiYgLEe4roKnr1lx5eCEl_zfNAaDnFQGYJ-MT=w1200|https://lh3.googleusercontent.com/pw/AP1GczPAWVx-YXXte2ohAua27OF9xoNwuYtvsBh5e7dE13ZOUeDjASRIoMMpgw91afZNOHjdfgWxofu1Plq4OrwhP4618hrQE_ICi3vohT7ftFWavClT1dPV=w1200|https://lh3.google"&"usercontent.com/pw/AP1GczOvplp8R-dFJezR_PQtWm9wvej6FKIpzN87K7G6w6brXY9vh4J8qb6K4guoItjiMgh9fFEJA_dr98LlU_mCneE7QXhv39whocvE1P19wJuin82EufRX=w1200|https://lh3.googleusercontent.com/pw/AP1GczMZEZtkDpokxw_lkKWcpXkF2-fE-7RI1ndpiLL0-RYbIyp4_foURK_3qFlp6212tuv4"&"VyX9LWXYYI1pihV4z1yN98vAe6QARQ6AyeSu0A2YM9oIBV7K=w1200|https://lh3.googleusercontent.com/pw/AP1GczMAM1xM-bigovV0DlpXOzN-CouhQ79PEeXUfG8lvJgdOXBvdvZzEpcUEfG5bMPVrHwzKqXlF3Wz-KRbwIitrD7AT2dLfhNSPNAM9ALyXEJe1S59hC3a=w1200|https://lh3.googleusercontent.com/pw"&"/AP1GczMor3UuszLYfqiNjv_APOI3sRvVO_LslUxZSLCfRv7z7aVfuHghdqQPLVEPQUqlA8Ww7MCQZn6LJX6slLUE1dpiNNsWCIkdF6KhRvDpvVTHW1ZBOCTq=w1200|https://lh3.googleusercontent.com/pw/AP1GczPG4-s_mtE200Yz8sZ77rKG7b91UISwlgRfimhRWis3OQSezQbqaYPh9UTTu7EdhS9Lk826wWwO7bX576LECh"&"p7ReoObfjam0OiAejHl59Je49C4hi9=w1200|https://lh3.googleusercontent.com/pw/AP1GczM99CMa7dz5ftA62NOypiZPcPHzqUphhqxQG4k57tmwrROhK7zhVkaq6WaHyrrBwg6JDwPYe1yLCFafJa_WFykfLVMUvwIY_GWxP8t39tXUhKfAda4u=w1200|https://lh3.googleusercontent.com/pw/AP1GczOWCJ5EiqHWn"&"Cy_dIdH8uEvJHIzpYZFAYa3oNHBjzVgjD6vD7n28ZKx3hGGrzzt-11wxfGl_pcIkEJpNr2PUl_T7cvNuWwQOLkOcw321nx18hOfs1m0=w1200|https://lh3.googleusercontent.com/pw/AP1GczMOYHgbVKyq5RG8FE_aIKqSjYHOVNRjVaGi-67dCqv6_UPvH7blVrb9IdnxR4a3MZJRFO6ofwGYxemS6cdG39xNwW_XkOZb7QvdFdft"&"jkPjx_mnIA5U=w1200|https://lh3.googleusercontent.com/pw/AP1GczPiyJsd-COrwrZqBML6LWopMzpMntBfcTNSNEqY0zT-RnhvzMALpTf3wWpyLmt1R3qbZPAJd7YsKju05j5RgWdHWa-C4Rs9ZgHrNdozdnkWNSvHpbh9=w1200|https://lh3.googleusercontent.com/pw/AP1GczM0Ol29TITRNr5VKEcln0GYxFSzXm5"&"HJlcsLaij0fZaK3eSUEXuIx6onFR0gktiVsrUmZX5iYrw-3z121_PvDVOGx9qbM5kQHvGVkFVugA0WsI647Gz=w1200|https://lh3.googleusercontent.com/pw/AP1GczOaypFfuKRnXcwGkJHp-wSPS5hDbAitmei5SDoivWUZPwFaYiUWc0LQONOjs-vnKBqzqqLyes2WqRzhLv_Rg5iygpYI4Y2he5t014h6xjJOMPpqVMaO=w1200"&"|https://lh3.googleusercontent.com/pw/AP1GczPh9kCZTs0ETIivaf9A9j9R6ULr4GN7sBuIXgYAKAAg7yGv130hTnlhUaTr1ZWu7dkx_PR-xN26kNMBjB4Kmb5KWk43GjDqezhoz2-49uln-VJkYpQK=w1200|https://lh3.googleusercontent.com/pw/AP1GczMFuqWI85fNTkt_Du0pqUs2JNjiIS_yT_NEC8FtXi2FdqkSy"&"gbkE8l7vI3tec2II2Beg9ouXr4V6UWO8ctOCjabpbAlK-QbVKrJ05itLF5fEGOl_wxh=w1200|https://lh3.googleusercontent.com/pw/AP1GczOXNdihgP9MKOPhFtIyMWYoBe8XfyVMvgEGcxsP8WHHZ3Ab8eowAWc0B746pLmv0K2VTe_gtFcFjoCey1PkxejFEjT-pJMAPV8cbKcKxWxVyfkeb92G=w1200|https://lh3.googl"&"eusercontent.com/pw/AP1GczOYpFGbR14CZgHmzP06j8ej12S2XXwahgwyRmPT474vV08ERgUuPyShfeblYiIYPSeISBqDXdRNvE-0TfffC8uYJfIgzeHw3jsLpNZuinwukDMZKKDa=w1200|https://lh3.googleusercontent.com/pw/AP1GczPeN9rAVe2LV8rvEYXS7Zq9MNslS61ehRlal-R0i6bp1G6pl4Ch6Eup4MK-bT7eCqS"&"vlk9fOucRHUW6UV8xN6pDLqNGtwcOfBAherC6m3LVJ9BkAXyL=w1200|https://lh3.googleusercontent.com/pw/AP1GczP1C8nX63LKbiysSCIKT-FnhOlvzlsNxORwvGHYQaKVNLOu3g4AhTUOxeTrEkUQdt6mSgRjNvv3bIi9C8C7Puh3fbJWTLfQevsDx2YTR4g-YmbXoZWd=w1200|https://lh3.googleusercontent.com/p"&"w/AP1GczNK7a_A771EH67_Vpq3Slp1NSzStYCR_QmSPCAKMIeG534LL0djnI-QwSmymTqMwfePk8YtBpumh0fElA6gZ-UC5242PtnTYmhfONNTe9Br94liEkia=w1200|https://lh3.googleusercontent.com/pw/AP1GczOtzu6qHKbOJxGGg5THp8KtEjtuBDT-xgVb9kem0Ym7MWi-m4bm2vIySPtcXDGARLm0XdMDqiTzH4aT5Nzii"&"qMLV4Vh6q78ptNMUiq7uvurvvjp0B_b=w1200|https://lh3.googleusercontent.com/pw/AP1GczOm5GJNFmsbeCHTZi2XL-uE6354gpyyQyrcvsaceollez0U_5_HrXdDa1-oHwjqDj_ZHsosqqZtmfXZHwexZ2-Z4yOOj2uPGQJFrcDEUE4sTKVGYop8=w1200|https://lh3.googleusercontent.com/pw/AP1GczO6siIkWK6u"&"sxCTXyihif5jsqJRlhw8VasJvP8PiO21rShiG6pFH-KFGPNg8m3ruskFWHJNLL45JkSEwwVfydhPes3qOmiuI4talxzy07aCQToVZKhZ=w1200|https://lh3.googleusercontent.com/pw/AP1GczOhSbRP1QzrrLq-uuTD99ZoKxlWXPKIZ4WskWhFFuicctbdvFwoL91JDfF5ppaQSb9p-BnTRHLh0rDvkJOwxTURV5H43WT1UcAQX5e"&"0ovSVIjgR1M5P=w1200|https://lh3.googleusercontent.com/pw/AP1GczN63pws2TgN-g9KUuc0T8sX-nz-_kaWnOUH30TvN6ueZBtRnxvmMUSPSbH2fAVIrafXsmlQ2xYxwx-w7i9dsUUWsvKw7UtUkUN3SBdPI_rFMyh9S3Rr=w1200|https://lh3.googleusercontent.com/pw/AP1GczPr6x1xGJJXf3_HllcuVuEcuzkLCw"&"UO4EiYHq5oR0i8H6INp6T1YYutbl42GrGanFQk-Iiyx6M4BBT6eAthfMYwXyVbgIzbYzUhjZe3XSjLwvIG15iZ=w1200") -> https://lh3.googleusercontent.com/pw/AP1GczPLo5Q331sbe9YG4Mi9fH1FRORONzn-SYT9WOZuzs8S_AnhXRZAnas2vvJ2-Cx-cJqXSip1IyVUFFYXZi3r8TYeT4PgJNuSMmGFwnJGcXzTjN85o7Ll=w1200|https://lh3.googleusercontent.com/pw/AP1GczP7RUimfVxtA8SwNEEyyiAOEZMOgc-P9GWfe7EPd6Rer-kIg5Et8H3dgSAmh1aCc21NjD9t9QWkW-1FiYgLEe4roKnr1lx5eCEl_zfNAaDnFQGYJ-MT=w1200|https://lh3.googleusercontent.com/pw/AP1GczPAWVx-YXXte2ohAua27OF9xoNwuYtvsBh5e7dE13ZOUeDjASRIoMMpgw91afZNOHjdfgWxofu1Plq4OrwhP4618hrQE_ICi3vohT7ftFWavClT1dPV=w1200|https://lh3.googleusercontent.com/pw/AP1GczOvplp8R-dFJezR_PQtWm9wvej6FKIpzN87K7G6w6brXY9vh4J8qb6K4guoItjiMgh9fFEJA_dr98LlU_mCneE7QXhv39whocvE1P19wJuin82EufRX=w1200|https://lh3.googleusercontent.com/pw/AP1GczMZEZtkDpokxw_lkKWcpXkF2-fE-7RI1ndpiLL0-RYbIyp4_foURK_3qFlp6212tuv4VyX9LWXYYI1pihV4z1yN98vAe6QARQ6AyeSu0A2YM9oIBV7K=w1200|https://lh3.googleusercontent.com/pw/AP1GczMAM1xM-bigovV0DlpXOzN-CouhQ79PEeXUfG8lvJgdOXBvdvZzEpcUEfG5bMPVrHwzKqXlF3Wz-KRbwIitrD7AT2dLfhNSPNAM9ALyXEJe1S59hC3a=w1200|https://lh3.googleusercontent.com/pw/AP1GczMor3UuszLYfqiNjv_APOI3sRvVO_LslUxZSLCfRv7z7aVfuHghdqQPLVEPQUqlA8Ww7MCQZn6LJX6slLUE1dpiNNsWCIkdF6KhRvDpvVTHW1ZBOCTq=w1200|https://lh3.googleusercontent.com/pw/AP1GczPG4-s_mtE200Yz8sZ77rKG7b91UISwlgRfimhRWis3OQSezQbqaYPh9UTTu7EdhS9Lk826wWwO7bX576LEChp7ReoObfjam0OiAejHl59Je49C4hi9=w1200|https://lh3.googleusercontent.com/pw/AP1GczM99CMa7dz5ftA62NOypiZPcPHzqUphhqxQG4k57tmwrROhK7zhVkaq6WaHyrrBwg6JDwPYe1yLCFafJa_WFykfLVMUvwIY_GWxP8t39tXUhKfAda4u=w1200|https://lh3.googleusercontent.com/pw/AP1GczOWCJ5EiqHWnCy_dIdH8uEvJHIzpYZFAYa3oNHBjzVgjD6vD7n28ZKx3hGGrzzt-11wxfGl_pcIkEJpNr2PUl_T7cvNuWwQOLkOcw321nx18hOfs1m0=w1200|https://lh3.googleusercontent.com/pw/AP1GczMOYHgbVKyq5RG8FE_aIKqSjYHOVNRjVaGi-67dCqv6_UPvH7blVrb9IdnxR4a3MZJRFO6ofwGYxemS6cdG39xNwW_XkOZb7QvdFdftjkPjx_mnIA5U=w1200|https://lh3.googleusercontent.com/pw/AP1GczPiyJsd-COrwrZqBML6LWopMzpMntBfcTNSNEqY0zT-RnhvzMALpTf3wWpyLmt1R3qbZPAJd7YsKju05j5RgWdHWa-C4Rs9ZgHrNdozdnkWNSvHpbh9=w1200|https://lh3.googleusercontent.com/pw/AP1GczM0Ol29TITRNr5VKEcln0GYxFSzXm5HJlcsLaij0fZaK3eSUEXuIx6onFR0gktiVsrUmZX5iYrw-3z121_PvDVOGx9qbM5kQHvGVkFVugA0WsI647Gz=w1200|https://lh3.googleusercontent.com/pw/AP1GczOaypFfuKRnXcwGkJHp-wSPS5hDbAitmei5SDoivWUZPwFaYiUWc0LQONOjs-vnKBqzqqLyes2WqRzhLv_Rg5iygpYI4Y2he5t014h6xjJOMPpqVMaO=w1200|https://lh3.googleusercontent.com/pw/AP1GczPh9kCZTs0ETIivaf9A9j9R6ULr4GN7sBuIXgYAKAAg7yGv130hTnlhUaTr1ZWu7dkx_PR-xN26kNMBjB4Kmb5KWk43GjDqezhoz2-49uln-VJkYpQK=w1200|https://lh3.googleusercontent.com/pw/AP1GczMFuqWI85fNTkt_Du0pqUs2JNjiIS_yT_NEC8FtXi2FdqkSygbkE8l7vI3tec2II2Beg9ouXr4V6UWO8ctOCjabpbAlK-QbVKrJ05itLF5fEGOl_wxh=w1200|https://lh3.googleusercontent.com/pw/AP1GczOXNdihgP9MKOPhFtIyMWYoBe8XfyVMvgEGcxsP8WHHZ3Ab8eowAWc0B746pLmv0K2VTe_gtFcFjoCey1PkxejFEjT-pJMAPV8cbKcKxWxVyfkeb92G=w1200|https://lh3.googleusercontent.com/pw/AP1GczOYpFGbR14CZgHmzP06j8ej12S2XXwahgwyRmPT474vV08ERgUuPyShfeblYiIYPSeISBqDXdRNvE-0TfffC8uYJfIgzeHw3jsLpNZuinwukDMZKKDa=w1200|https://lh3.googleusercontent.com/pw/AP1GczPeN9rAVe2LV8rvEYXS7Zq9MNslS61ehRlal-R0i6bp1G6pl4Ch6Eup4MK-bT7eCqSvlk9fOucRHUW6UV8xN6pDLqNGtwcOfBAherC6m3LVJ9BkAXyL=w1200|https://lh3.googleusercontent.com/pw/AP1GczP1C8nX63LKbiysSCIKT-FnhOlvzlsNxORwvGHYQaKVNLOu3g4AhTUOxeTrEkUQdt6mSgRjNvv3bIi9C8C7Puh3fbJWTLfQevsDx2YTR4g-YmbXoZWd=w1200|https://lh3.googleusercontent.com/pw/AP1GczNK7a_A771EH67_Vpq3Slp1NSzStYCR_QmSPCAKMIeG534LL0djnI-QwSmymTqMwfePk8YtBpumh0fElA6gZ-UC5242PtnTYmhfONNTe9Br94liEkia=w1200|https://lh3.googleusercontent.com/pw/AP1GczOtzu6qHKbOJxGGg5THp8KtEjtuBDT-xgVb9kem0Ym7MWi-m4bm2vIySPtcXDGARLm0XdMDqiTzH4aT5NziiqMLV4Vh6q78ptNMUiq7uvurvvjp0B_b=w1200|https://lh3.googleusercontent.com/pw/AP1GczOm5GJNFmsbeCHTZi2XL-uE6354gpyyQyrcvsaceollez0U_5_HrXdDa1-oHwjqDj_ZHsosqqZtmfXZHwexZ2-Z4yOOj2uPGQJFrcDEUE4sTKVGYop8=w1200|https://lh3.googleusercontent.com/pw/AP1GczO6siIkWK6usxCTXyihif5jsqJRlhw8VasJvP8PiO21rShiG6pFH-KFGPNg8m3ruskFWHJNLL45JkSEwwVfydhPes3qOmiuI4talxzy07aCQToVZKhZ=w1200|https://lh3.googleusercontent.com/pw/AP1GczOhSbRP1QzrrLq-uuTD99ZoKxlWXPKIZ4WskWhFFuicctbdvFwoL91JDfF5ppaQSb9p-BnTRHLh0rDvkJOwxTURV5H43WT1UcAQX5e0ovSVIjgR1M5P=w1200|https://lh3.googleusercontent.com/pw/AP1GczN63pws2TgN-g9KUuc0T8sX-nz-_kaWnOUH30TvN6ueZBtRnxvmMUSPSbH2fAVIrafXsmlQ2xYxwx-w7i9dsUUWsvKw7UtUkUN3SBdPI_rFMyh9S3Rr=w1200|https://lh3.googleusercontent.com/pw/AP1GczPr6x1xGJJXf3_HllcuVuEcuzkLCwUO4EiYHq5oR0i8H6INp6T1YYutbl42GrGanFQk-Iiyx6M4BBT6eAthfMYwXyVbgIzbYzUhjZe3XSjLwvIG15iZ=w1200
A16: =IFERROR(__xludf.DUMMYFUNCTION("""COMPUTED_VALUE"""),"1648") -> 1648 | B16: =IFERROR(__xludf.DUMMYFUNCTION("""COMPUTED_VALUE"""),"Casa con local en barrio Santa Clara - Cámbulos II") -> Casa con local en barrio Santa Clara - Cámbulos II | C16: =IFERROR(__xludf.DUMMYFUNCTION("""COMPUTED_VALUE"""),"Casa rentable") -> Casa rentable | D16: =IFERROR(__xludf.DUMMYFUNCTION("""COMPUTED_VALUE"""),"Santa Clara") -> Santa Clara | F16: =IFERROR(__xludf.DUMMYFUNCTION("""COMPUTED_VALUE"""),3.8E8) -> 380000000 | G16: =IFERROR(__xludf.DUMMYFUNCTION("""COMPUTED_VALUE"""),"$300'000.000 a $400'000.000") -> $300'000.000 a $400'000.000 | J16: =IFERROR(__xludf.DUMMYFUNCTION("""COMPUTED_VALUE"""),"Norte") -> Norte | K16: =IFERROR(__xludf.DUMMYFUNCTION("""COMPUTED_VALUE"""),"2") -> 2 | L16: =IFERROR(__xludf.DUMMYFUNCTION("""COMPUTED_VALUE"""),3.0) -> 3 | N16: =IFERROR(__xludf.DUMMYFUNCTION("""COMPUTED_VALUE"""),3.0) -> 3 | O16: =IFERROR(__xludf.DUMMYFUNCTION("""COMPUTED_VALUE"""),1.0) -> 1 | P16: =IFERROR(__xludf.DUMMYFUNCTION("""COMPUTED_VALUE"""),2.0) -> 2 | Q16: =IFERROR(__xludf.DUMMYFUNCTION("""COMPUTED_VALUE"""),0.0) -> 0 | R16: =IFERROR(__xludf.DUMMYFUNCTION("""COMPUTED_VALUE"""),97.0) -> 97 | S16: =IFERROR(__xludf.DUMMYFUNCTION("""COMPUTED_VALUE""")," ") | T16: =IFERROR(__xludf.DUMMYFUNCTION("""COMPUTED_VALUE"""),"Neiva") -> Neiva | U16: =IFERROR(__xludf.DUMMYFUNCTION("""COMPUTED_VALUE"""),"3") -> 3 | V16: =IFERROR(__xludf.DUMMYFUNCTION("""COMPUTED_VALUE"""),"Medianera") -> Medianera | X16: =IFERROR(__xludf.DUMMYFUNCTION("""COMPUTED_VALUE"""),3.0) -> 3 | Y16: =IFERROR(__xludf.DUMMYFUNCTION("""COMPUTED_VALUE"""),"No tiene") -> No tiene | Z16: =IFERROR(__xludf.DUMMYFUNCTION("""COMPUTED_VALUE"""),"No aplica") -> No aplica | AA16: =IFERROR(__xludf.DUMMYFUNCTION("""COMPUTED_VALUE"""),"No aplica") -> No aplica | AB16: =IFERROR(__xludf.DUMMYFUNCTION("""COMPUTED_VALUE"""),"https://photos.app.goo.gl/fSaSXTFLumJN5a7h9") -> https://photos.app.goo.gl/fSaSXTFLumJN5a7h9 | AC16: =IFERROR(__xludf.DUMMYFUNCTION("""COMPUTED_VALUE"""),"Casa de 2 pisos por toda la Avenida 26, para uso comercial o de vivienda. B/ Santa Clara, con un área de 97 mts 2, estrato 3 consta de: Primer Piso: Sala amplia, comedor, cocina integral, garaje interno, patio de ropas, baño auxiliar, pisos en baldosa, y "&"techo en PVC, paredes decorativas. Segundo Piso: 3 habitaciones, la principal con Amplio baño con tina, closets en madera y baño auxiliar.") -> Casa de 2 pisos por toda la Avenida 26, para uso comercial o de vivienda. B/ Santa Clara, con un área de 97 mts 2, estrato 3 consta de: Primer Piso: Sala amplia, comedor, cocina integral, garaje interno, patio de ropas, baño auxiliar, pisos en baldosa, y techo en PVC, paredes decorativas. Segundo Piso: 3 habitaciones, la principal con Amplio baño con tina, closets en madera y baño auxiliar. | AF16: =IFERROR(__xludf.DUMMYFUNCTION("""COMPUTED_VALUE"""),"integral") -> integral | AG16: =IFERROR(__xludf.DUMMYFUNCTION("""COMPUTED_VALUE"""),"SI") -> SI | AH16: =IFERROR(__xludf.DUMMYFUNCTION("""COMPUTED_VALUE"""),"Inventario") -> Inventario | AI16: =IFERROR(__xludf.DUMMYFUNCTION("""COMPUTED_VALUE"""),"Aliado") -> Aliado | AJ16: =IFERROR(__xludf.DUMMYFUNCTION("""COMPUTED_VALUE"""),"C&C") -> C&C | AK16: =IFERROR(__xludf.DUMMYFUNCTION("""COMPUTED_VALUE"""),"No aplica") -> No aplica | AL16: =IFERROR(__xludf.DUMMYFUNCTION("""COMPUTED_VALUE"""),"TIENE FOTOS") -> TIENE FOTOS | AM16: =IFERROR(__xludf.DUMMYFUNCTION("""COMPUTED_VALUE"""),3.13351965E9) -> 3133519650 | AP16: =IFERROR(__xludf.DUMMYFUNCTION("""COMPUTED_VALUE"""),"AV. 26 # 33-38 B7") -> AV. 26 # 33-38 B7 | AQ16: =IFERROR(__xludf.DUMMYFUNCTION("""COMPUTED_VALUE"""),2.9464325) -> 2.9464325 | AR16: =IFERROR(__xludf.DUMMYFUNCTION("""COMPUTED_VALUE"""),-75.2882221) -> -75.288222 | AT16: =IFERROR(__xludf.DUMMYFUNCTION("""COMPUTED_VALUE"""),0.0) -> 0 | AU16: =IFERROR(__xludf.DUMMYFUNCTION("""COMPUTED_VALUE"""),0.0) -> 0 | AV16: =IFERROR(__xludf.DUMMYFUNCTION("""COMPUTED_VALUE"""),0.0) -> 0 | AW16: =IFERROR(__xludf.DUMMYFUNCTION("""COMPUTED_VALUE"""),"SI") -> SI | AY16: =IFERROR(__xludf.DUMMYFUNCTION("""COMPUTED_VALUE"""),"P") -> P | BA16: =IFERROR(__xludf.DUMMYFUNCTION("""COMPUTED_VALUE"""),"X") -> X | BF16: =IFERROR(__xludf.DUMMYFUNCTION("""COMPUTED_VALUE"""),"https://lh3.googleusercontent.com/pw/AP1GczPi4K_xNvS8GWiFu_kSPaJ4uusK1Q00n13ZP4BsfOTeGeQgjJVDdLegQBRUYBTLT3nlHNXH80rzOePhtJDLnTSapxfU94JNTshhl1vAgnm4GATAfXHq=w1200|https://lh3.googleusercontent.com/pw/AP1GczNKwHJ3NxA0XB1NcB9V1OSgc7lgaKZerxpKf_czyEoTc4qAtT"&"LXDkW88GM3q-Lb2wLcpJ8K_e59q2Tfx9EpBQ8ANdSJQ2vJCbX5Pm2HOjYxp22mPB9X=w1200|https://lh3.googleusercontent.com/pw/AP1GczP6pbccvz7xrQrLQFFmnAJSNIebMNR7ssrdB8FEioB1HqvWHKBAMdgCz-gxjvtKtV7PXiV8sPhc1APElF1RId92WGjwLDFeppXje7eFlY4_kP3h6a76=w1200|https://lh3.google"&"usercontent.com/pw/AP1GczNZrFKe3QROQlxsPKYgFkhCs0YuVdMADTH2eHtgIc_kwnNW5n8lT7QvghnAEQSi2tKtYYhx04atglUF7C4ROznN5bfNG2_wpHwsJ6tNMcSIJ5yqnb9T=w1200|https://lh3.googleusercontent.com/pw/AP1GczNxvONgYW_XGpnzwZcYnTCj5cqCziri_XsgtAjhOVXEVVRwU2ymq6Nn2-fPrZ0YLacm"&"c-2bY8CX8j9-LYs1iUZEArtlHpzDda5u6Hge4WoJAa6XbBCB=w1200|https://lh3.googleusercontent.com/pw/AP1GczPtlwqN6-1u5eWyQihKnFEf23fe81dvqeJ-ST_rTENddWTQ1dBpry8qOQz9JNDil9lTLIbpc8twVJnBmXL_MCOFj7R46A89Xv6rl22WJJqSvTmo0XeF=w1200|https://lh3.googleusercontent.com/pw"&"/AP1GczPQCoNnAL0aDTvfAmyRYbq2FLkK0fbMHexl4yuj2LZjc8HOJpqKE-qumRQlVV0n-G0LRYP24pNlek2cSuzSBylqI6H2siUIbscBqmBrrYwpokPRBst3=w1200|https://lh3.googleusercontent.com/pw/AP1GczOp-h0e6boiu6ufq7r27Rf89lv_QWKET7duqZWkVHNchD3OZY62hGCDkfIBkxB-3dTgMU-7p0QFUNuj9ubE55"&"6QSPnbWtCyem6D5ry-WMzmOpiQlWOs=w1200|https://lh3.googleusercontent.com/pw/AP1GczPJKOXx-z9Lncw-Tx0nKeL0GpYk0aJF2AZqqeA_I3CS69anqH2dWD4W5qYoQuED3mStl3EGxTS0qnJnNHca2Dp6k0p6UgOjwqS88Asb9DzY4O7X7Z7f=w1200|https://lh3.googleusercontent.com/pw/AP1GczPc8mmtgLq2o"&"XYKnbdCuHlQMHHblvHeAhNfFlPQuQ-ewcxR9eXzDXhIKsIU9FC3Lib2Gd1ABp1Ch4PrHdUZoaap8-iLtrhrV1dQf6bMZAq_XYyDiWOI=w1200|https://lh3.googleusercontent.com/pw/AP1GczOjHifDb_xrUs9Vl7HBMk_ilfuI4d7IKQaT2QmXfTg2MrS5KXLSQX8_ZpSMCsY4xg8IHEQvCeYLxSFavtRqOzERd6eCKaQeGZiqgQRC"&"XRxd2lKOVFT3=w1200|https://lh3.googleusercontent.com/pw/AP1GczP2qeNunU-A6rw8EH_YNjn_E6itU1_drnZefEsbfstltzOlTx0E_AzNUH4Qi31jFYa2K4pYyYwRi2Vav1Qn-DUXUYlOP5C2NLfr_i9Sj3h7ZdN1XO7k=w1200|https://lh3.googleusercontent.com/pw/AP1GczMQ2-ZOS4BzHOtOzyy-hYwKgEOJ0ae"&"Vr_PqFV0kWevqi9nkDTs6lzbo2cp6BGmg9-MLBOcnA55JSrqbnKKIeomUVIxM7tqfADIOW8zbdJ6gZxAhXfsF=w1200|https://lh3.googleusercontent.com/pw/AP1GczMMUMvEGWhdxD5gZlx52JjJF3MmVrP_xpmJ3Gm95rmZ60cZKdLgWSaluePKeY1TI1qzFpzGF5t3gZj-1tJQ_aTH8ucpjxw3iH87BgpILbBZLY_02z5F=w1200"&"|https://lh3.googleusercontent.com/pw/AP1GczP0vKvyTlxkt6PjgbcpbYvSZD60XuLfGQgRgai9Q4Fv72L7m1xWkIiaATTHmWuhH7MT7dXzIBS7aYPIv7z1koI3jAfWIBtxFTYRIHYvNxopWjryg5Ly=w1200|https://lh3.googleusercontent.com/pw/AP1GczOm3tO6sFBZP7Mzm7pcnorpLtYZYEalT5Uowr1cy7--bogu3"&"OdtfuO_rOmQxkqocsPA7UQ2pp8JyNn2seJTtXClAAESip6Sjwlld-v1syDHLyx_8auy=w1200|https://lh3.googleusercontent.com/pw/AP1GczPBLhVqZQH4an7SCigjBmioQGN2IljzChPa4fZQnDoXa-r2i5OP1YNJ8VANCD8byVB9iNYbOmtcxxtBcQvf3QCTnt7R4BwTQkxDNQh2RGVSYUEQ3jQA=w1200|https://lh3.googl"&"eusercontent.com/pw/AP1GczOqAvHUtmoVc5_X_WbVT2ETCeSIDMrd-I9zIYY7oWNqFLz8gOY8-M4auHw9ytoh0MjQGRMDgeRe2Q-o52WZ76KEyIHJvQaoUwyLQpcEwga8D6ji6y72=w1200|https://lh3.googleusercontent.com/pw/AP1GczNc-pBFpuIygrNGzKojepQVZv7lEyHa5miQGCIqsySJ8yDeYqPixGX-ms2VwUPIbjz"&"M8BZy0bVG60uhMY0D2hY0VKcmHBnbCTRCs9VoMTHOoYaojYat=w1200") -> https://lh3.googleusercontent.com/pw/AP1GczPi4K_xNvS8GWiFu_kSPaJ4uusK1Q00n13ZP4BsfOTeGeQgjJVDdLegQBRUYBTLT3nlHNXH80rzOePhtJDLnTSapxfU94JNTshhl1vAgnm4GATAfXHq=w1200|https://lh3.googleusercontent.com/pw/AP1GczNKwHJ3NxA0XB1NcB9V1OSgc7lgaKZerxpKf_czyEoTc4qAtTLXDkW88GM3q-Lb2wLcpJ8K_e59q2Tfx9EpBQ8ANdSJQ2vJCbX5Pm2HOjYxp22mPB9X=w1200|https://lh3.googleusercontent.com/pw/AP1GczP6pbccvz7xrQrLQFFmnAJSNIebMNR7ssrdB8FEioB1HqvWHKBAMdgCz-gxjvtKtV7PXiV8sPhc1APElF1RId92WGjwLDFeppXje7eFlY4_kP3h6a76=w1200|https://lh3.googleusercontent.com/pw/AP1GczNZrFKe3QROQlxsPKYgFkhCs0YuVdMADTH2eHtgIc_kwnNW5n8lT7QvghnAEQSi2tKtYYhx04atglUF7C4ROznN5bfNG2_wpHwsJ6tNMcSIJ5yqnb9T=w1200|https://lh3.googleusercontent.com/pw/AP1GczNxvONgYW_XGpnzwZcYnTCj5cqCziri_XsgtAjhOVXEVVRwU2ymq6Nn2-fPrZ0YLacmc-2bY8CX8j9-LYs1iUZEArtlHpzDda5u6Hge4WoJAa6XbBCB=w1200|https://lh3.googleusercontent.com/pw/AP1GczPtlwqN6-1u5eWyQihKnFEf23fe81dvqeJ-ST_rTENddWTQ1dBpry8qOQz9JNDil9lTLIbpc8twVJnBmXL_MCOFj7R46A89Xv6rl22WJJqSvTmo0XeF=w1200|https://lh3.googleusercontent.com/pw/AP1GczPQCoNnAL0aDTvfAmyRYbq2FLkK0fbMHexl4yuj2LZjc8HOJpqKE-qumRQlVV0n-G0LRYP24pNlek2cSuzSBylqI6H2siUIbscBqmBrrYwpokPRBst3=w1200|https://lh3.googleusercontent.com/pw/AP1GczOp-h0e6boiu6ufq7r27Rf89lv_QWKET7duqZWkVHNchD3OZY62hGCDkfIBkxB-3dTgMU-7p0QFUNuj9ubE556QSPnbWtCyem6D5ry-WMzmOpiQlWOs=w1200|https://lh3.googleusercontent.com/pw/AP1GczPJKOXx-z9Lncw-Tx0nKeL0GpYk0aJF2AZqqeA_I3CS69anqH2dWD4W5qYoQuED3mStl3EGxTS0qnJnNHca2Dp6k0p6UgOjwqS88Asb9DzY4O7X7Z7f=w1200|https://lh3.googleusercontent.com/pw/AP1GczPc8mmtgLq2oXYKnbdCuHlQMHHblvHeAhNfFlPQuQ-ewcxR9eXzDXhIKsIU9FC3Lib2Gd1ABp1Ch4PrHdUZoaap8-iLtrhrV1dQf6bMZAq_XYyDiWOI=w1200|https://lh3.googleusercontent.com/pw/AP1GczOjHifDb_xrUs9Vl7HBMk_ilfuI4d7IKQaT2QmXfTg2MrS5KXLSQX8_ZpSMCsY4xg8IHEQvCeYLxSFavtRqOzERd6eCKaQeGZiqgQRCXRxd2lKOVFT3=w1200|https://lh3.googleusercontent.com/pw/AP1GczP2qeNunU-A6rw8EH_YNjn_E6itU1_drnZefEsbfstltzOlTx0E_AzNUH4Qi31jFYa2K4pYyYwRi2Vav1Qn-DUXUYlOP5C2NLfr_i9Sj3h7ZdN1XO7k=w1200|https://lh3.googleusercontent.com/pw/AP1GczMQ2-ZOS4BzHOtOzyy-hYwKgEOJ0aeVr_PqFV0kWevqi9nkDTs6lzbo2cp6BGmg9-MLBOcnA55JSrqbnKKIeomUVIxM7tqfADIOW8zbdJ6gZxAhXfsF=w1200|https://lh3.googleusercontent.com/pw/AP1GczMMUMvEGWhdxD5gZlx52JjJF3MmVrP_xpmJ3Gm95rmZ60cZKdLgWSaluePKeY1TI1qzFpzGF5t3gZj-1tJQ_aTH8ucpjxw3iH87BgpILbBZLY_02z5F=w1200|https://lh3.googleusercontent.com/pw/AP1GczP0vKvyTlxkt6PjgbcpbYvSZD60XuLfGQgRgai9Q4Fv72L7m1xWkIiaATTHmWuhH7MT7dXzIBS7aYPIv7z1koI3jAfWIBtxFTYRIHYvNxopWjryg5Ly=w1200|https://lh3.googleusercontent.com/pw/AP1GczOm3tO6sFBZP7Mzm7pcnorpLtYZYEalT5Uowr1cy7--bogu3OdtfuO_rOmQxkqocsPA7UQ2pp8JyNn2seJTtXClAAESip6Sjwlld-v1syDHLyx_8auy=w1200|https://lh3.googleusercontent.com/pw/AP1GczPBLhVqZQH4an7SCigjBmioQGN2IljzChPa4fZQnDoXa-r2i5OP1YNJ8VANCD8byVB9iNYbOmtcxxtBcQvf3QCTnt7R4BwTQkxDNQh2RGVSYUEQ3jQA=w1200|https://lh3.googleusercontent.com/pw/AP1GczOqAvHUtmoVc5_X_WbVT2ETCeSIDMrd-I9zIYY7oWNqFLz8gOY8-M4auHw9ytoh0MjQGRMDgeRe2Q-o52WZ76KEyIHJvQaoUwyLQpcEwga8D6ji6y72=w1200|https://lh3.googleusercontent.com/pw/AP1GczNc-pBFpuIygrNGzKojepQVZv7lEyHa5miQGCIqsySJ8yDeYqPixGX-ms2VwUPIbjzM8BZy0bVG60uhMY0D2hY0VKcmHBnbCTRCs9VoMTHOoYaojYat=w1200
A17: =IFERROR(__xludf.DUMMYFUNCTION("""COMPUTED_VALUE"""),"179") -> 179 | B17: =IFERROR(__xludf.DUMMYFUNCTION("""COMPUTED_VALUE"""),"Casa con local y dos apartamentos en barrio Las Granjas") -> Casa con local y dos apartamentos en barrio Las Granjas | C17: =IFERROR(__xludf.DUMMYFUNCTION("""COMPUTED_VALUE"""),"Casa rentable") -> Casa rentable | D17: =IFERROR(__xludf.DUMMYFUNCTION("""COMPUTED_VALUE"""),"Las Granjas") -> Las Granjas | E17: =IFERROR(__xludf.DUMMYFUNCTION("""COMPUTED_VALUE""")," ") | F17: =IFERROR(__xludf.DUMMYFUNCTION("""COMPUTED_VALUE"""),3.2E8) -> 320000000 | G17: =IFERROR(__xludf.DUMMYFUNCTION("""COMPUTED_VALUE"""),"$300'000.000 a $400'000.000") -> $300'000.000 a $400'000.000 | J17: =IFERROR(__xludf.DUMMYFUNCTION("""COMPUTED_VALUE"""),"Norte") -> Norte | K17: =IFERROR(__xludf.DUMMYFUNCTION("""COMPUTED_VALUE"""),"2") -> 2 | L17: =IFERROR(__xludf.DUMMYFUNCTION("""COMPUTED_VALUE"""),5.0) -> 5 | N17: =IFERROR(__xludf.DUMMYFUNCTION("""COMPUTED_VALUE"""),3.0) -> 3 | O17: =IFERROR(__xludf.DUMMYFUNCTION("""COMPUTED_VALUE"""),0.0) -> 0 | P17: =IFERROR(__xludf.DUMMYFUNCTION("""COMPUTED_VALUE"""),1.0) -> 1 | Q17: =IFERROR(__xludf.DUMMYFUNCTION("""COMPUTED_VALUE"""),180.0) -> 180 | R17: =IFERROR(__xludf.DUMMYFUNCTION("""COMPUTED_VALUE"""),180.0) -> 180 | S17: =IFERROR(__xludf.DUMMYFUNCTION("""COMPUTED_VALUE"""),"Rentabilidad $1,500,000") -> Rentabilidad $1,500,000 | T17: =IFERROR(__xludf.DUMMYFUNCTION("""COMPUTED_VALUE"""),"Neiva") -> Neiva | U17: =IFERROR(__xludf.DUMMYFUNCTION("""COMPUTED_VALUE"""),"2") -> 2 | V17: =IFERROR(__xludf.DUMMYFUNCTION("""COMPUTED_VALUE"""),"Medianera") -> Medianera | X17: =IFERROR(__xludf.DUMMYFUNCTION("""COMPUTED_VALUE"""),0.0) -> 0 | Y17: =IFERROR(__xludf.DUMMYFUNCTION("""COMPUTED_VALUE"""),"No tiene") -> No tiene | Z17: =IFERROR(__xludf.DUMMYFUNCTION("""COMPUTED_VALUE"""),"No aplica") -> No aplica | AA17: =IFERROR(__xludf.DUMMYFUNCTION("""COMPUTED_VALUE"""),"18 años") -> 18 años | AB17: =IFERROR(__xludf.DUMMYFUNCTION("""COMPUTED_VALUE"""),"https://photos.app.goo.gl/cuREDmpg6MZf8hSS9") -> https://photos.app.goo.gl/cuREDmpg6MZf8hSS9 | AF17: =IFERROR(__xludf.DUMMYFUNCTION("""COMPUTED_VALUE"""),"básica") -> básica | AG17: =IFERROR(__xludf.DUMMYFUNCTION("""COMPUTED_VALUE"""),"SI") -> SI | AH17: =IFERROR(__xludf.DUMMYFUNCTION("""COMPUTED_VALUE"""),"Inventario") -> Inventario | AI17: =IFERROR(__xludf.DUMMYFUNCTION("""COMPUTED_VALUE"""),"Aliado") -> Aliado | AJ17: =IFERROR(__xludf.DUMMYFUNCTION("""COMPUTED_VALUE"""),"C&C") -> C&C | AK17: =IFERROR(__xludf.DUMMYFUNCTION("""COMPUTED_VALUE"""),"No aplica") -> No aplica | AL17: =IFERROR(__xludf.DUMMYFUNCTION("""COMPUTED_VALUE"""),"TIENE FOTOS") -> TIENE FOTOS | AM17: =IFERROR(__xludf.DUMMYFUNCTION("""COMPUTED_VALUE"""),3.13351965E9) -> 3133519650 | AN17: =IFERROR(__xludf.DUMMYFUNCTION("""COMPUTED_VALUE"""),0.0) -> 0 | AP17: =IFERROR(__xludf.DUMMYFUNCTION("""COMPUTED_VALUE"""),"Carrera 7 No. 45- 27") -> Carrera 7 No. 45- 27 | AQ17: =IFERROR(__xludf.DUMMYFUNCTION("""COMPUTED_VALUE"""),2.952564) -> 2.952564 | AR17: =IFERROR(__xludf.DUMMYFUNCTION("""COMPUTED_VALUE"""),-75.2908635) -> -75.290864 | AS17: =IFERROR(__xludf.DUMMYFUNCTION("""COMPUTED_VALUE"""),1500000.0) -> 1500000 | AT17: =IFERROR(__xludf.DUMMYFUNCTION("""COMPUTED_VALUE"""),0.0) -> 0 | AU17: =IFERROR(__xludf.DUMMYFUNCTION("""COMPUTED_VALUE"""),0.0) -> 0 | AV17: =IFERROR(__xludf.DUMMYFUNCTION("""COMPUTED_VALUE"""),0.0) -> 0 | AW17: =IFERROR(__xludf.DUMMYFUNCTION("""COMPUTED_VALUE"""),"NO") -> NO | AX17: =IFERROR(__xludf.DUMMYFUNCTION("""COMPUTED_VALUE"""),0.0) -> 0 | AY17: =IFERROR(__xludf.DUMMYFUNCTION("""COMPUTED_VALUE"""),0.0) -> 0 | AZ17: =IFERROR(__xludf.DUMMYFUNCTION("""COMPUTED_VALUE"""),0.0) -> 0 | BA17: =IFERROR(__xludf.DUMMYFUNCTION("""COMPUTED_VALUE"""),"X") -> X | BB17: =IFERROR(__xludf.DUMMYFUNCTION("""COMPUTED_VALUE"""),0.0) -> 0 | BC17: =IFERROR(__xludf.DUMMYFUNCTION("""COMPUTED_VALUE"""),"41 - NORMA MEDINA") -> 41 - NORMA MEDINA | BF17: =IFERROR(__xludf.DUMMYFUNCTION("""COMPUTED_VALUE"""),"https://lh3.googleusercontent.com/pw/AP1GczNYfpCn1VcCWoDriiCb6r5dRQvs5kLb4EMmNQWkJpuP29eFHcTUTvsY_hl0V3ILCvh8OkXJtburnDeO-9ta-9jyakurlkSrkMnFkSkIRGOw37WXUHm8=w1200|https://lh3.googleusercontent.com/pw/AP1GczNPZOL_1pzM8MKfVALYdJ4-bWGrCrSPTUzdbpeC5IsGDlZwB5"&"dj_8NcMzFZEhXQHnQk1IJ2tI2-s5QgSESciMDWpG05vxX28lx5-aSR-9zcwyS7Uw4D=w1200|https://lh3.googleusercontent.com/pw/AP1GczMQVVNABH3mjuUN0HgyTVxHCYdlryszoEdYL9-gqbKY-u8oiye_slvT206pwts2BXSsQfkpdn72K4Q6zs1xOABKZVMvptxJkU2KaqAoYMxa_M9thza3=w1200|https://lh3.google"&"usercontent.com/pw/AP1GczMXI0fMUyQpcTenMmTbsk8ZP_j70CW_-F4C6OpaIdHFKWGWrZKvUc-tsSm98SxqBnlUJ9cQoycvNsbG9dZFWD0BfkHtU54p0kIDIrIOSrdkKum6Tfft=w1200|https://lh3.googleusercontent.com/pw/AP1GczMZShn4JWpMN1_bxukU44S77sx9T3fweAk3Y3jfPjZqSr4vvAKluXfEEclgfyeXesZz"&"agBFytpvOCCBptu-45LTwIz852Qz0gRsC1naEJ4ygvmKRrCx=w1200|https://lh3.googleusercontent.com/pw/AP1GczNAmGz1idZSwpFcAbWQNcKyCQycb1SvxRn3FwXStvNE0oUQvne38eiz_UWCJN32hCqABd1uAmzwa1E3RSO0GZsa_2jNqQQFaI7qd0iwmiUqFKuYsmwv=w1200") -> https://lh3.googleusercontent.com/pw/AP1GczNYfpCn1VcCWoDriiCb6r5dRQvs5kLb4EMmNQWkJpuP29eFHcTUTvsY_hl0V3ILCvh8OkXJtburnDeO-9ta-9jyakurlkSrkMnFkSkIRGOw37WXUHm8=w1200|https://lh3.googleusercontent.com/pw/AP1GczNPZOL_1pzM8MKfVALYdJ4-bWGrCrSPTUzdbpeC5IsGDlZwB5dj_8NcMzFZEhXQHnQk1IJ2tI2-s5QgSESciMDWpG05vxX28lx5-aSR-9zcwyS7Uw4D=w1200|https://lh3.googleusercontent.com/pw/AP1GczMQVVNABH3mjuUN0HgyTVxHCYdlryszoEdYL9-gqbKY-u8oiye_slvT206pwts2BXSsQfkpdn72K4Q6zs1xOABKZVMvptxJkU2KaqAoYMxa_M9thza3=w1200|https://lh3.googleusercontent.com/pw/AP1GczMXI0fMUyQpcTenMmTbsk8ZP_j70CW_-F4C6OpaIdHFKWGWrZKvUc-tsSm98SxqBnlUJ9cQoycvNsbG9dZFWD0BfkHtU54p0kIDIrIOSrdkKum6Tfft=w1200|https://lh3.googleusercontent.com/pw/AP1GczMZShn4JWpMN1_bxukU44S77sx9T3fweAk3Y3jfPjZqSr4vvAKluXfEEclgfyeXesZzagBFytpvOCCBptu-45LTwIz852Qz0gRsC1naEJ4ygvmKRrCx=w1200|https://lh3.googleusercontent.com/pw/AP1GczNAmGz1idZSwpFcAbWQNcKyCQycb1SvxRn3FwXStvNE0oUQvne38eiz_UWCJN32hCqABd1uAmzwa1E3RSO0GZsa_2jNqQQFaI7qd0iwmiUqFKuYsmwv=w1200
A18: =IFERROR(__xludf.DUMMYFUNCTION("""COMPUTED_VALUE"""),"998") -> 998 | B18: =IFERROR(__xludf.DUMMYFUNCTION("""COMPUTED_VALUE"""),"Casa en barrio Villa Carolina") -> Casa en barrio Villa Carolina | C18: =IFERROR(__xludf.DUMMYFUNCTION("""COMPUTED_VALUE"""),"Casa") -> Casa | D18: =IFERROR(__xludf.DUMMYFUNCTION("""COMPUTED_VALUE"""),"Villa Carolina") -> Villa Carolina | F18: =IFERROR(__xludf.DUMMYFUNCTION("""COMPUTED_VALUE"""),2.9E8) -> 290000000 | G18: =IFERROR(__xludf.DUMMYFUNCTION("""COMPUTED_VALUE"""),"$200'000.000 a $300'000.000") -> $200'000.000 a $300'000.000 | J18: =IFERROR(__xludf.DUMMYFUNCTION("""COMPUTED_VALUE"""),"Norte") -> Norte | K18: =IFERROR(__xludf.DUMMYFUNCTION("""COMPUTED_VALUE"""),"2") -> 2 | L18: =IFERROR(__xludf.DUMMYFUNCTION("""COMPUTED_VALUE"""),4.0) -> 4 | N18: =IFERROR(__xludf.DUMMYFUNCTION("""COMPUTED_VALUE"""),3.0) -> 3 | O18: =IFERROR(__xludf.DUMMYFUNCTION("""COMPUTED_VALUE"""),1.0) -> 1 | P18: =IFERROR(__xludf.DUMMYFUNCTION("""COMPUTED_VALUE"""),2.0) -> 2 | R18: =IFERROR(__xludf.DUMMYFUNCTION("""COMPUTED_VALUE"""),120.0) -> 120 | S18: =IFERROR(__xludf.DUMMYFUNCTION("""COMPUTED_VALUE""")," ") | T18: =IFERROR(__xludf.DUMMYFUNCTION("""COMPUTED_VALUE"""),"Neiva") -> Neiva | U18: =IFERROR(__xludf.DUMMYFUNCTION("""COMPUTED_VALUE"""),"3") -> 3 | V18: =IFERROR(__xludf.DUMMYFUNCTION("""COMPUTED_VALUE"""),"Medianera") -> Medianera | X18: =IFERROR(__xludf.DUMMYFUNCTION("""COMPUTED_VALUE"""),3.0) -> 3 | Y18: =IFERROR(__xludf.DUMMYFUNCTION("""COMPUTED_VALUE"""),"No tiene") -> No tiene | Z18: =IFERROR(__xludf.DUMMYFUNCTION("""COMPUTED_VALUE"""),"No aplica") -> No aplica | AA18: =IFERROR(__xludf.DUMMYFUNCTION("""COMPUTED_VALUE"""),"No aplica") -> No aplica | AF18: =IFERROR(__xludf.DUMMYFUNCTION("""COMPUTED_VALUE"""),"integral") -> integral | AH18: =IFERROR(__xludf.DUMMYFUNCTION("""COMPUTED_VALUE"""),"Inventario") -> Inventario | AI18: =IFERROR(__xludf.DUMMYFUNCTION("""COMPUTED_VALUE"""),"Aliado") -> Aliado | AJ18: =IFERROR(__xludf.DUMMYFUNCTION("""COMPUTED_VALUE"""),"C&C") -> C&C | AK18: =IFERROR(__xludf.DUMMYFUNCTION("""COMPUTED_VALUE"""),"No aplica") -> No aplica | AL18: =IFERROR(__xludf.DUMMYFUNCTION("""COMPUTED_VALUE"""),"TIENE FOTOS") -> TIENE FOTOS | AM18: =IFERROR(__xludf.DUMMYFUNCTION("""COMPUTED_VALUE"""),3.13351965E9) -> 3133519650 | AP18: =IFERROR(__xludf.DUMMYFUNCTION("""COMPUTED_VALUE"""),"CALLE 56 NO. 17C-12") -> CALLE 56 NO. 17C-12 | AS18: =IFERROR(__xludf.DUMMYFUNCTION("""COMPUTED_VALUE"""),0.0) -> 0 | AT18: =IFERROR(__xludf.DUMMYFUNCTION("""COMPUTED_VALUE"""),0.0) -> 0 | AU18: =IFERROR(__xludf.DUMMYFUNCTION("""COMPUTED_VALUE"""),0.0) -> 0 | AV18: =IFERROR(__xludf.DUMMYFUNCTION("""COMPUTED_VALUE"""),0.0) -> 0 | AW18: =IFERROR(__xludf.DUMMYFUNCTION("""COMPUTED_VALUE"""),"NO") -> NO | AX18: =IFERROR(__xludf.DUMMYFUNCTION("""COMPUTED_VALUE"""),0.0) -> 0 | AY18: =IFERROR(__xludf.DUMMYFUNCTION("""COMPUTED_VALUE"""),0.0) -> 0 | AZ18: =IFERROR(__xludf.DUMMYFUNCTION("""COMPUTED_VALUE"""),0.0) -> 0 | BA18: =IFERROR(__xludf.DUMMYFUNCTION("""COMPUTED_VALUE"""),"X") -> X | BB18: =IFERROR(__xludf.DUMMYFUNCTION("""COMPUTED_VALUE"""),0.0) -> 0
A19: =IFERROR(__xludf.DUMMYFUNCTION("""COMPUTED_VALUE"""),"768") -> 768 | B19: =IFERROR(__xludf.DUMMYFUNCTION("""COMPUTED_VALUE"""),"Casa con dos apartamentos en barrio Santa Librada") -> Casa con dos apartamentos en barrio Santa Librada | C19: =IFERROR(__xludf.DUMMYFUNCTION("""COMPUTED_VALUE"""),"Casa rentable") -> Casa rentable | D19: =IFERROR(__xludf.DUMMYFUNCTION("""COMPUTED_VALUE"""),"Santa Librada") -> Santa Librada | F19: =IFERROR(__xludf.DUMMYFUNCTION("""COMPUTED_VALUE"""),5.0E8) -> 500000000 | G19: =IFERROR(__xludf.DUMMYFUNCTION("""COMPUTED_VALUE"""),"$500'000.000 a $1.000'000.000") -> $500'000.000 a $1.000'000.000 | J19: =IFERROR(__xludf.DUMMYFUNCTION("""COMPUTED_VALUE"""),"Centro") -> Centro | K19: =IFERROR(__xludf.DUMMYFUNCTION("""COMPUTED_VALUE"""),"3") -> 3 | L19: =IFERROR(__xludf.DUMMYFUNCTION("""COMPUTED_VALUE"""),7.0) -> 7 | N19: =IFERROR(__xludf.DUMMYFUNCTION("""COMPUTED_VALUE"""),5.0) -> 5 | O19: =IFERROR(__xludf.DUMMYFUNCTION("""COMPUTED_VALUE"""),1.0) -> 1 | P19: =IFERROR(__xludf.DUMMYFUNCTION("""COMPUTED_VALUE"""),2.0) -> 2 | R19: =IFERROR(__xludf.DUMMYFUNCTION("""COMPUTED_VALUE"""),250.0) -> 250 | S19: =IFERROR(__xludf.DUMMYFUNCTION("""COMPUTED_VALUE"""),"Rentabilidad $1,500,000") -> Rentabilidad $1,500,000 | T19: =IFERROR(__xludf.DUMMYFUNCTION("""COMPUTED_VALUE"""),"Neiva") -> Neiva | U19: =IFERROR(__xludf.DUMMYFUNCTION("""COMPUTED_VALUE"""),"2") -> 2 | V19: =IFERROR(__xludf.DUMMYFUNCTION("""COMPUTED_VALUE"""),"Medianera") -> Medianera | X19: =IFERROR(__xludf.DUMMYFUNCTION("""COMPUTED_VALUE"""),2.0) -> 2 | Y19: =IFERROR(__xludf.DUMMYFUNCTION("""COMPUTED_VALUE"""),"No tiene") -> No tiene | Z19: =IFERROR(__xludf.DUMMYFUNCTION("""COMPUTED_VALUE"""),"No aplica") -> No aplica | AA19: =IFERROR(__xludf.DUMMYFUNCTION("""COMPUTED_VALUE"""),"28 años") -> 28 años | AB19: =IFERROR(__xludf.DUMMYFUNCTION("""COMPUTED_VALUE"""),"https://photos.app.goo.gl/Vreh7uUdMUXAhqUG6") -> https://photos.app.goo.gl/Vreh7uUdMUXAhqUG6 | AF19: =IFERROR(__xludf.DUMMYFUNCTION("""COMPUTED_VALUE"""),"básica") -> básica | AH19: =IFERROR(__xludf.DUMMYFUNCTION("""COMPUTED_VALUE"""),"Inventario") -> Inventario | AJ19: =IFERROR(__xludf.DUMMYFUNCTION("""COMPUTED_VALUE"""),"C&C") -> C&C | AK19: =IFERROR(__xludf.DUMMYFUNCTION("""COMPUTED_VALUE"""),"No aplica") -> No aplica | AL19: =IFERROR(__xludf.DUMMYFUNCTION("""COMPUTED_VALUE"""),"TIENE FOTOS") -> TIENE FOTOS | AM19: =IFERROR(__xludf.DUMMYFUNCTION("""COMPUTED_VALUE"""),3.13351965E9) -> 3133519650 | AN19: =IFERROR(__xludf.DUMMYFUNCTION("""COMPUTED_VALUE"""),0.0) -> 0 | AP19: =IFERROR(__xludf.DUMMYFUNCTION("""COMPUTED_VALUE"""),"CARRERA 16 NO. 16 - 113") -> CARRERA 16 NO. 16 - 113 | AS19: =IFERROR(__xludf.DUMMYFUNCTION("""COMPUTED_VALUE"""),1500000.0) -> 1500000 | AT19: =IFERROR(__xludf.DUMMYFUNCTION("""COMPUTED_VALUE"""),0.0) -> 0 | AU19: =IFERROR(__xludf.DUMMYFUNCTION("""COMPUTED_VALUE"""),0.0) -> 0 | AV19: =IFERROR(__xludf.DUMMYFUNCTION("""COMPUTED_VALUE"""),0.0) -> 0 | AW19: =IFERROR(__xludf.DUMMYFUNCTION("""COMPUTED_VALUE"""),"NO") -> NO | AX19: =IFERROR(__xludf.DUMMYFUNCTION("""COMPUTED_VALUE"""),0.0) -> 0 | AY19: =IFERROR(__xludf.DUMMYFUNCTION("""COMPUTED_VALUE"""),0.0) -> 0 | AZ19: =IFERROR(__xludf.DUMMYFUNCTION("""COMPUTED_VALUE"""),10.0) -> 10 | BA19: =IFERROR(__xludf.DUMMYFUNCTION("""COMPUTED_VALUE"""),"X") -> X | BB19: =IFERROR(__xludf.DUMMYFUNCTION("""COMPUTED_VALUE"""),25.0) -> 25 | BF19: =IFERROR(__xludf.DUMMYFUNCTION("""COMPUTED_VALUE"""),"https://lh3.googleusercontent.com/pw/AP1GczPlKurr9Lpt5kb2OilFzw_2P8VcV2UUDUzNMM7A6w9v10hh9d7b4UIyMk3GFilXzJkOgg5WTtq8-XUVx70IqHaUkSDQIjIhx6GvNW7UGPrcvtt8pAmy=w1200|https://lh3.googleusercontent.com/pw/AP1GczN8aCfzmr739AAXSkSJoAX7dGBa-jbKJLUtSoUwDJivJ301cN"&"_Qp3OPHovKC0NS3xLd5JXAzVTK3TGZwwhZWXYHaBrX3TSwH_QwVXhWtqjPwI47FGyi=w1200|https://lh3.googleusercontent.com/pw/AP1GczNttCNWpyuWU6n66uQgzocQcSMHAj_YkfVL-lqZcZ9ibi-3vGlzZFGPOUWHBBQlLg5urp0GqdGPP149WgtT6g5CDZ7OxqC_cdpOQk-z2rsC_TYkLEQ1=w1200|https://lh3.google"&"usercontent.com/pw/AP1GczOhZo1NwxYm4nY4SgoP0q8-Iz38sEhBjRNtmLDxrCI_qdH3KNTXvmbTaNrAHjMI4cU6bhnb4Qhi9VsMD6m3Eg8GOBqrkXzVnbcnh2C8qKPbD1x64OvH=w1200|https://lh3.googleusercontent.com/pw/AP1GczNSqHVUXLdoRggxQ0O9RJqkhU-5viczJr300UiVAE5jAU8cAqYSCyStMqfodomIF1Kl"&"cRg8Jsy9rvOOKWQ9KtEeVifSLQtNgbK9obVFaM4HlDhb6Z-x=w1200|https://lh3.googleusercontent.com/pw/AP1GczPKPwApzx2budgvWUIHQGU-Op1ATBYPKn1i3fsYXvb3-d-m4yPZCYjp-sWbwCD5q_kxW8VZAm04oCHFV5KRHtvKCI0DKVGZK8SkPFCXfSv2Weib7awp=w1200|https://lh3.googleusercontent.com/pw"&"/AP1GczNfu-fovI41Me97OoeIuhfHv5WB2kjY5AvIsO_0SB5gqJHj2zRXcV0pSoWgYTCpNWPlmG0l46IuPHsJ-M9p-oEJumMKf5z5hdr3CQuWYE844IZPTiUH=w1200|https://lh3.googleusercontent.com/pw/AP1GczNBp_bd6rfWUzFVeMcQLy-97ljbr-inhAZpR1Nqgh2Iis-8-jt9NF1Y4zevgamFXadJ50bcZEBc-XVUMVP8nD"&"tkWgFveOLg-YUcLZ6ZWIUFIF6QCYhu=w1200|https://lh3.googleusercontent.com/pw/AP1GczO8FJu4KM529tzAmWQ8q_bn5mCRzmY-FhRVAhFzf_aZVE8OVSjwXei4fXakWtHg0pRpsYfIB-hgCTDxCNKhc_j6ypZfTL1NsbudawVNTY5GRPdZmbSV=w1200|https://lh3.googleusercontent.com/pw/AP1GczNyDvVmbndJr"&"m8ppIMPl2SWJu4st4gRdlqTqCuPKuah8CMmUoFZhhYdyQq4GAhmjH-yrzmLAsj1CiC2yfhTO4f4zY5VnYnplMNonQvehxBcY5EVxAfg=w1200|https://lh3.googleusercontent.com/pw/AP1GczP0XG6Tnn75_YCu8HgpVi0twRWzWsww9kFAoK4Q_mde98VMnQrUEKX86_8_KG6Oe48jBUvERZw6qvgtMzVSDCKU3-FwmPn_1A-J7AKK"&"hcFULZEIctJO=w1200|https://lh3.googleusercontent.com/pw/AP1GczPOD2BjEmUccDHcQpYJrNhoWqrL3aU9Y59uqnZTUbdQBD6i199DdZtz47W3qeetF4aPB9IOnfw6LxSKvvx35wruuYRAKyxw8VguV3rQIgjpfOG5pOV1=w1200|https://lh3.googleusercontent.com/pw/AP1GczNSh2VWMLaKJYmUIulevTJL54Cb8su"&"Q4Q9Pg20Ab1-iOlJm3hqY4m-IOwCyCkBB8XUHh5_QaGOOHiSmwyoF3qKpkNh53jTGcRuRXM1FUrn3LIiNk-3d=w1200|https://lh3.googleusercontent.com/pw/AP1GczM554VOX0OvaMC6w_YJXglVdJRfATneaECyCt5QVClSkGnUkzMj1Pd6E0voI5CZ5PXA3Kugk_zd2vrO9yOMapqXlxGBXoWs7P0C2WQrOMWH6lgbTheD=w1200") -> https://lh3.googleusercontent.com/pw/AP1GczPlKurr9Lpt5kb2OilFzw_2P8VcV2UUDUzNMM7A6w9v10hh9d7b4UIyMk3GFilXzJkOgg5WTtq8-XUVx70IqHaUkSDQIjIhx6GvNW7UGPrcvtt8pAmy=w1200|https://lh3.googleusercontent.com/pw/AP1GczN8aCfzmr739AAXSkSJoAX7dGBa-jbKJLUtSoUwDJivJ301cN_Qp3OPHovKC0NS3xLd5JXAzVTK3TGZwwhZWXYHaBrX3TSwH_QwVXhWtqjPwI47FGyi=w1200|https://lh3.googleusercontent.com/pw/AP1GczNttCNWpyuWU6n66uQgzocQcSMHAj_YkfVL-lqZcZ9ibi-3vGlzZFGPOUWHBBQlLg5urp0GqdGPP149WgtT6g5CDZ7OxqC_cdpOQk-z2rsC_TYkLEQ1=w1200|https://lh3.googleusercontent.com/pw/AP1GczOhZo1NwxYm4nY4SgoP0q8-Iz38sEhBjRNtmLDxrCI_qdH3KNTXvmbTaNrAHjMI4cU6bhnb4Qhi9VsMD6m3Eg8GOBqrkXzVnbcnh2C8qKPbD1x64OvH=w1200|https://lh3.googleusercontent.com/pw/AP1GczNSqHVUXLdoRggxQ0O9RJqkhU-5viczJr300UiVAE5jAU8cAqYSCyStMqfodomIF1KlcRg8Jsy9rvOOKWQ9KtEeVifSLQtNgbK9obVFaM4HlDhb6Z-x=w1200|https://lh3.googleusercontent.com/pw/AP1GczPKPwApzx2budgvWUIHQGU-Op1ATBYPKn1i3fsYXvb3-d-m4yPZCYjp-sWbwCD5q_kxW8VZAm04oCHFV5KRHtvKCI0DKVGZK8SkPFCXfSv2Weib7awp=w1200|https://lh3.googleusercontent.com/pw/AP1GczNfu-fovI41Me97OoeIuhfHv5WB2kjY5AvIsO_0SB5gqJHj2zRXcV0pSoWgYTCpNWPlmG0l46IuPHsJ-M9p-oEJumMKf5z5hdr3CQuWYE844IZPTiUH=w1200|https://lh3.googleusercontent.com/pw/AP1GczNBp_bd6rfWUzFVeMcQLy-97ljbr-inhAZpR1Nqgh2Iis-8-jt9NF1Y4zevgamFXadJ50bcZEBc-XVUMVP8nDtkWgFveOLg-YUcLZ6ZWIUFIF6QCYhu=w1200|https://lh3.googleusercontent.com/pw/AP1GczO8FJu4KM529tzAmWQ8q_bn5mCRzmY-FhRVAhFzf_aZVE8OVSjwXei4fXakWtHg0pRpsYfIB-hgCTDxCNKhc_j6ypZfTL1NsbudawVNTY5GRPdZmbSV=w1200|https://lh3.googleusercontent.com/pw/AP1GczNyDvVmbndJrm8ppIMPl2SWJu4st4gRdlqTqCuPKuah8CMmUoFZhhYdyQq4GAhmjH-yrzmLAsj1CiC2yfhTO4f4zY5VnYnplMNonQvehxBcY5EVxAfg=w1200|https://lh3.googleusercontent.com/pw/AP1GczP0XG6Tnn75_YCu8HgpVi0twRWzWsww9kFAoK4Q_mde98VMnQrUEKX86_8_KG6Oe48jBUvERZw6qvgtMzVSDCKU3-FwmPn_1A-J7AKKhcFULZEIctJO=w1200|https://lh3.googleusercontent.com/pw/AP1GczPOD2BjEmUccDHcQpYJrNhoWqrL3aU9Y59uqnZTUbdQBD6i199DdZtz47W3qeetF4aPB9IOnfw6LxSKvvx35wruuYRAKyxw8VguV3rQIgjpfOG5pOV1=w1200|https://lh3.googleusercontent.com/pw/AP1GczNSh2VWMLaKJYmUIulevTJL54Cb8suQ4Q9Pg20Ab1-iOlJm3hqY4m-IOwCyCkBB8XUHh5_QaGOOHiSmwyoF3qKpkNh53jTGcRuRXM1FUrn3LIiNk-3d=w1200|https://lh3.googleusercontent.com/pw/AP1GczM554VOX0OvaMC6w_YJXglVdJRfATneaECyCt5QVClSkGnUkzMj1Pd6E0voI5CZ5PXA3Kugk_zd2vrO9yOMapqXlxGBXoWs7P0C2WQrOMWH6lgbTheD=w1200
A20: =IFERROR(__xludf.DUMMYFUNCTION("""COMPUTED_VALUE"""),"1534") -> 1534 | B20: =IFERROR(__xludf.DUMMYFUNCTION("""COMPUTED_VALUE"""),"Casa con dos apartaestudios en barrio Alamos Norte") -> Casa con dos apartaestudios en barrio Alamos Norte | C20: =IFERROR(__xludf.DUMMYFUNCTION("""COMPUTED_VALUE"""),"Casa rentable") -> Casa rentable | D20: =IFERROR(__xludf.DUMMYFUNCTION("""COMPUTED_VALUE"""),"Alamos Norte") -> Alamos Norte | E20: =IFERROR(__xludf.DUMMYFUNCTION("""COMPUTED_VALUE""")," ") | F20: =IFERROR(__xludf.DUMMYFUNCTION("""COMPUTED_VALUE"""),1.4E8) -> 140000000 | G20: =IFERROR(__xludf.DUMMYFUNCTION("""COMPUTED_VALUE"""),"$100'000.000 a $200'000.000") -> $100'000.000 a $200'000.000 | J20: =IFERROR(__xludf.DUMMYFUNCTION("""COMPUTED_VALUE"""),"Norte") -> Norte | L20: =IFERROR(__xludf.DUMMYFUNCTION("""COMPUTED_VALUE"""),2.0) -> 2 | N20: =IFERROR(__xludf.DUMMYFUNCTION("""COMPUTED_VALUE"""),2.0) -> 2 | O20: =IFERROR(__xludf.DUMMYFUNCTION("""COMPUTED_VALUE"""),0.0) -> 0 | P20: =IFERROR(__xludf.DUMMYFUNCTION("""COMPUTED_VALUE"""),2.0) -> 2 | Q20: =IFERROR(__xludf.DUMMYFUNCTION("""COMPUTED_VALUE"""),92.0) -> 92 | R20: =IFERROR(__xludf.DUMMYFUNCTION("""COMPUTED_VALUE"""),92.0) -> 92 | S20: =IFERROR(__xludf.DUMMYFUNCTION("""COMPUTED_VALUE"""),"Rentabilidad $1,000,000") -> Rentabilidad $1,000,000 | T20: =IFERROR(__xludf.DUMMYFUNCTION("""COMPUTED_VALUE"""),"Neiva") -> Neiva | U20: =IFERROR(__xludf.DUMMYFUNCTION("""COMPUTED_VALUE"""),"2") -> 2 | V20: =IFERROR(__xludf.DUMMYFUNCTION("""COMPUTED_VALUE"""),"Medianera") -> Medianera | X20: =IFERROR(__xludf.DUMMYFUNCTION("""COMPUTED_VALUE"""),2.0) -> 2 | Y20: =IFERROR(__xludf.DUMMYFUNCTION("""COMPUTED_VALUE"""),"No tiene") -> No tiene | Z20: =IFERROR(__xludf.DUMMYFUNCTION("""COMPUTED_VALUE"""),"No aplica") -> No aplica | AA20: =IFERROR(__xludf.DUMMYFUNCTION("""COMPUTED_VALUE"""),"12 años") -> 12 años | AF20: =IFERROR(__xludf.DUMMYFUNCTION("""COMPUTED_VALUE"""),"semi-integral") -> semi-integral | AH20: =IFERROR(__xludf.DUMMYFUNCTION("""COMPUTED_VALUE"""),"Inventario") -> Inventario | AJ20: =IFERROR(__xludf.DUMMYFUNCTION("""COMPUTED_VALUE"""),"C&C") -> C&C | AK20: =IFERROR(__xludf.DUMMYFUNCTION("""COMPUTED_VALUE"""),"No aplica") -> No aplica | AL20: =IFERROR(__xludf.DUMMYFUNCTION("""COMPUTED_VALUE"""),"TIENE FOTOS") -> TIENE FOTOS | AM20: =IFERROR(__xludf.DUMMYFUNCTION("""COMPUTED_VALUE"""),3.13351965E9) -> 3133519650 | AP20: =IFERROR(__xludf.DUMMYFUNCTION("""COMPUTED_VALUE"""),"CALLE 49 No. 20-17") -> CALLE 49 No. 20-17 | AS20: =IFERROR(__xludf.DUMMYFUNCTION("""COMPUTED_VALUE"""),1000000.0) -> 1000000 | AT20: =IFERROR(__xludf.DUMMYFUNCTION("""COMPUTED_VALUE"""),0.0) -> 0 | AU20: =IFERROR(__xludf.DUMMYFUNCTION("""COMPUTED_VALUE"""),0.0) -> 0 | AV20: =IFERROR(__xludf.DUMMYFUNCTION("""COMPUTED_VALUE"""),0.0) -> 0 | AW20: =IFERROR(__xludf.DUMMYFUNCTION("""COMPUTED_VALUE"""),"NO") -> NO | AX20: =IFERROR(__xludf.DUMMYFUNCTION("""COMPUTED_VALUE"""),0.0) -> 0 | AY20: =IFERROR(__xludf.DUMMYFUNCTION("""COMPUTED_VALUE"""),0.0) -> 0 | AZ20: =IFERROR(__xludf.DUMMYFUNCTION("""COMPUTED_VALUE"""),0.0) -> 0 | BA20: =IFERROR(__xludf.DUMMYFUNCTION("""COMPUTED_VALUE"""),"X") -> X | BB20: =IFERROR(__xludf.DUMMYFUNCTION("""COMPUTED_VALUE"""),0.0) -> 0
A21: =IFERROR(__xludf.DUMMYFUNCTION("""COMPUTED_VALUE"""),"239") -> 239 | C21: =IFERROR(__xludf.DUMMYFUNCTION("""COMPUTED_VALUE"""),"Casa rentable") -> Casa rentable | D21: =IFERROR(__xludf.DUMMYFUNCTION("""COMPUTED_VALUE"""),"Campo Nuñez") -> Campo Nuñez | F21: =IFERROR(__xludf.DUMMYFUNCTION("""COMPUTED_VALUE"""),6.2E8) -> 620000000 | G21: =IFERROR(__xludf.DUMMYFUNCTION("""COMPUTED_VALUE"""),"$500'000.000 a $1.000'000.000") -> $500'000.000 a $1.000'000.000 | J21: =IFERROR(__xludf.DUMMYFUNCTION("""COMPUTED_VALUE"""),"Centro") -> Centro | L21: =IFERROR(__xludf.DUMMYFUNCTION("""COMPUTED_VALUE"""),4.0) -> 4 | N21: =IFERROR(__xludf.DUMMYFUNCTION("""COMPUTED_VALUE"""),3.0) -> 3 | O21: =IFERROR(__xludf.DUMMYFUNCTION("""COMPUTED_VALUE"""),0.0) -> 0 | P21: =IFERROR(__xludf.DUMMYFUNCTION("""COMPUTED_VALUE"""),3.0) -> 3 | Q21: =IFERROR(__xludf.DUMMYFUNCTION("""COMPUTED_VALUE"""),334.0) -> 334 | R21: =IFERROR(__xludf.DUMMYFUNCTION("""COMPUTED_VALUE"""),170.0) -> 170 | S21: =IFERROR(__xludf.DUMMYFUNCTION("""COMPUTED_VALUE""")," ") | V21: =IFERROR(__xludf.DUMMYFUNCTION("""COMPUTED_VALUE"""),"Esquinera") -> Esquinera | X21: =IFERROR(__xludf.DUMMYFUNCTION("""COMPUTED_VALUE"""),3.0) -> 3 | Y21: =IFERROR(__xludf.DUMMYFUNCTION("""COMPUTED_VALUE"""),"No tiene") -> No tiene | Z21: =IFERROR(__xludf.DUMMYFUNCTION("""COMPUTED_VALUE"""),"No aplica") -> No aplica | AA21: =IFERROR(__xludf.DUMMYFUNCTION("""COMPUTED_VALUE"""),"No aplica") -> No aplica | AF21: =IFERROR(__xludf.DUMMYFUNCTION("""COMPUTED_VALUE"""),"semi-integral") -> semi-integral | AH21: =IFERROR(__xludf.DUMMYFUNCTION("""COMPUTED_VALUE"""),"Inventario") -> Inventario | AJ21: =IFERROR(__xludf.DUMMYFUNCTION("""COMPUTED_VALUE"""),"CAMPO NUÑEZ") -> CAMPO NUÑEZ | AL21: =IFERROR(__xludf.DUMMYFUNCTION("""COMPUTED_VALUE"""),"NO FOTOS + DESCRIPCION") -> NO FOTOS + DESCRIPCION | AM21: =IFERROR(__xludf.DUMMYFUNCTION("""COMPUTED_VALUE"""),"?????") -> ????? | AS21: =IFERROR(__xludf.DUMMYFUNCTION("""COMPUTED_VALUE"""),0.0) -> 0 | AT21: =IFERROR(__xludf.DUMMYFUNCTION("""COMPUTED_VALUE"""),0.0) -> 0 | AU21: =IFERROR(__xludf.DUMMYFUNCTION("""COMPUTED_VALUE"""),0.0) -> 0 | AV21: =IFERROR(__xludf.DUMMYFUNCTION("""COMPUTED_VALUE"""),0.0) -> 0 | AW21: =IFERROR(__xludf.DUMMYFUNCTION("""COMPUTED_VALUE"""),"NO") -> NO | AX21: =IFERROR(__xludf.DUMMYFUNCTION("""COMPUTED_VALUE"""),0.0) -> 0 | AY21: =IFERROR(__xludf.DUMMYFUNCTION("""COMPUTED_VALUE"""),0.0) -> 0 | AZ21: =IFERROR(__xludf.DUMMYFUNCTION("""COMPUTED_VALUE"""),0.0) -> 0 | BA21: =IFERROR(__xludf.DUMMYFUNCTION("""COMPUTED_VALUE"""),"X") -> X | BB21: =IFERROR(__xludf.DUMMYFUNCTION("""COMPUTED_VALUE"""),0.0) -> 0
A22: =IFERROR(__xludf.DUMMYFUNCTION("""COMPUTED_VALUE"""),"556") -> 556 | B22: =IFERROR(__xludf.DUMMYFUNCTION("""COMPUTED_VALUE"""),"Camponuñez.") -> Camponuñez. | D22: =IFERROR(__xludf.DUMMYFUNCTION("""COMPUTED_VALUE"""),"") | F22: =IFERROR(__xludf.DUMMYFUNCTION("""COMPUTED_VALUE"""),0.0) -> 0 | G22: =IFERROR(__xludf.DUMMYFUNCTION("""COMPUTED_VALUE"""),"$0 a $100'000.000") -> $0 a $100'000.000 | Q22: =IFERROR(__xludf.DUMMYFUNCTION("""COMPUTED_VALUE"""),0.0) -> 0 | R22: =IFERROR(__xludf.DUMMYFUNCTION("""COMPUTED_VALUE"""),0.0) -> 0 | S22: =IFERROR(__xludf.DUMMYFUNCTION("""COMPUTED_VALUE""")," ") | AA22: =IFERROR(__xludf.DUMMYFUNCTION("""COMPUTED_VALUE"""),"No aplica") -> No aplica | AF22: =IFERROR(__xludf.DUMMYFUNCTION("""COMPUTED_VALUE"""),"") | AH22: =IFERROR(__xludf.DUMMYFUNCTION("""COMPUTED_VALUE"""),"Inventario") -> Inventario | AJ22: =IFERROR(__xludf.DUMMYFUNCTION("""COMPUTED_VALUE"""),"CAMPO NUÑEZ - CASA + LOCAL") -> CAMPO NUÑEZ - CASA + LOCAL | AL22: =IFERROR(__xludf.DUMMYFUNCTION("""COMPUTED_VALUE"""),"NO FOTOS + DESCRIPCION") -> NO FOTOS + DESCRIPCION | AM22: =IFERROR(__xludf.DUMMYFUNCTION("""COMPUTED_VALUE"""),3.152454767E9) -> 3152454767 | AS22: =IFERROR(__xludf.DUMMYFUNCTION("""COMPUTED_VALUE"""),0.0) -> 0 | BA22: =IFERROR(__xludf.DUMMYFUNCTION("""COMPUTED_VALUE"""),"X") -> X | BC22: =IFERROR(__xludf.DUMMYFUNCTION("""COMPUTED_VALUE"""),"19 - PRUEBA v, 15 - SINDY MARCELA") -> 19 - PRUEBA v, 15 - SINDY MARCELA
A23: =IFERROR(__xludf.DUMMYFUNCTION("""COMPUTED_VALUE"""),"041") -> 041 | B23: =IFERROR(__xludf.DUMMYFUNCTION("""COMPUTED_VALUE"""),"Casa en barrio Los Cámbulos II") -> Casa en barrio Los Cámbulos II | C23: =IFERROR(__xludf.DUMMYFUNCTION("""COMPUTED_VALUE"""),"Casa") -> Casa | D23: =IFERROR(__xludf.DUMMYFUNCTION("""COMPUTED_VALUE"""),"Los Cámbulos II") -> Los Cámbulos II | E23: =IFERROR(__xludf.DUMMYFUNCTION("""COMPUTED_VALUE""")," ") | F23: =IFERROR(__xludf.DUMMYFUNCTION("""COMPUTED_VALUE"""),3.4E8) -> 340000000 | G23: =IFERROR(__xludf.DUMMYFUNCTION("""COMPUTED_VALUE"""),"$300'000.000 a $400'000.000") -> $300'000.000 a $400'000.000 | J23: =IFERROR(__xludf.DUMMYFUNCTION("""COMPUTED_VALUE"""),"Norte") -> Norte | K23: =IFERROR(__xludf.DUMMYFUNCTION("""COMPUTED_VALUE"""),"2") -> 2 | L23: =IFERROR(__xludf.DUMMYFUNCTION("""COMPUTED_VALUE"""),4.0) -> 4 | N23: =IFERROR(__xludf.DUMMYFUNCTION("""COMPUTED_VALUE"""),3.0) -> 3 | O23: =IFERROR(__xludf.DUMMYFUNCTION("""COMPUTED_VALUE"""),1.0) -> 1 | P23: =IFERROR(__xludf.DUMMYFUNCTION("""COMPUTED_VALUE"""),3.0) -> 3 | R23: =IFERROR(__xludf.DUMMYFUNCTION("""COMPUTED_VALUE"""),112.0) -> 112 | S23: =IFERROR(__xludf.DUMMYFUNCTION("""COMPUTED_VALUE"""),"Rentabilidad $1,200,000") -> Rentabilidad $1,200,000 | T23: =IFERROR(__xludf.DUMMYFUNCTION("""COMPUTED_VALUE"""),"Neiva") -> Neiva | U23: =IFERROR(__xludf.DUMMYFUNCTION("""COMPUTED_VALUE"""),"3") -> 3 | V23: =IFERROR(__xludf.DUMMYFUNCTION("""COMPUTED_VALUE"""),"Medianera") -> Medianera | X23: =IFERROR(__xludf.DUMMYFUNCTION("""COMPUTED_VALUE"""),0.0) -> 0 | Y23: =IFERROR(__xludf.DUMMYFUNCTION("""COMPUTED_VALUE"""),"No tiene") -> No tiene | Z23: =IFERROR(__xludf.DUMMYFUNCTION("""COMPUTED_VALUE"""),"No aplica") -> No aplica | AA23: =IFERROR(__xludf.DUMMYFUNCTION("""COMPUTED_VALUE"""),"24 años") -> 24 años | AF23: =IFERROR(__xludf.DUMMYFUNCTION("""COMPUTED_VALUE"""),"integral") -> integral | AH23: =IFERROR(__xludf.DUMMYFUNCTION("""COMPUTED_VALUE"""),"Inventario") -> Inventario | AJ23: =IFERROR(__xludf.DUMMYFUNCTION("""COMPUTED_VALUE"""),"Casa Blanca-Inventario Los Cambulos") -> Casa Blanca-Inventario Los Cambulos | AL23: =IFERROR(__xludf.DUMMYFUNCTION("""COMPUTED_VALUE"""),"NO FOTOS INT.") -> NO FOTOS INT. | AM23: =IFERROR(__xludf.DUMMYFUNCTION("""COMPUTED_VALUE"""),3.203296936E9) -> 3203296936 | AN23: =IFERROR(__xludf.DUMMYFUNCTION("""COMPUTED_VALUE"""),3.123874356E9) -> 3123874356 | AO23: =IFERROR(__xludf.DUMMYFUNCTION("""COMPUTED_VALUE"""),"MARCELA SANCHEZ-INMOBILIARIA CASA BLANCA") -> MARCELA SANCHEZ-INMOBILIARIA CASA BLANCA | AP23: =IFERROR(__xludf.DUMMYFUNCTION("""COMPUTED_VALUE"""),"No. 27-46") -> No. 27-46 | AS23: =IFERROR(__xludf.DUMMYFUNCTION("""COMPUTED_VALUE"""),1200000.0) -> 1200000 | AT23: =IFERROR(__xludf.DUMMYFUNCTION("""COMPUTED_VALUE"""),0.0) -> 0 | AU23: =IFERROR(__xludf.DUMMYFUNCTION("""COMPUTED_VALUE"""),0.0) -> 0 | AV23: =IFERROR(__xludf.DUMMYFUNCTION("""COMPUTED_VALUE"""),0.0) -> 0 | AW23: =IFERROR(__xludf.DUMMYFUNCTION("""COMPUTED_VALUE"""),"NO") -> NO | AX23: =IFERROR(__xludf.DUMMYFUNCTION("""COMPUTED_VALUE"""),0.0) -> 0 | AY23: =IFERROR(__xludf.DUMMYFUNCTION("""COMPUTED_VALUE"""),0.0) -> 0 | AZ23: =IFERROR(__xludf.DUMMYFUNCTION("""COMPUTED_VALUE"""),7.0) -> 7 | BA23: =IFERROR(__xludf.DUMMYFUNCTION("""COMPUTED_VALUE"""),"X") -> X | BB23: =IFERROR(__xludf.DUMMYFUNCTION("""COMPUTED_VALUE"""),16.0) -> 16
A24: =IFERROR(__xludf.DUMMYFUNCTION("""COMPUTED_VALUE"""),"718") -> 718 | B24: =IFERROR(__xludf.DUMMYFUNCTION("""COMPUTED_VALUE"""),"Casa + 3 Apartamentos en barrio Chapinero - Centro") -> Casa + 3 Apartamentos en barrio Chapinero - Centro | C24: =IFERROR(__xludf.DUMMYFUNCTION("""COMPUTED_VALUE"""),"Casa rentable") -> Casa rentable | D24: =IFERROR(__xludf.DUMMYFUNCTION("""COMPUTED_VALUE"""),"Chapinero") -> Chapinero | F24: =IFERROR(__xludf.DUMMYFUNCTION("""COMPUTED_VALUE"""),9.5E8) -> 950000000 | G24: =IFERROR(__xludf.DUMMYFUNCTION("""COMPUTED_VALUE"""),"$500'000.000 a $1.000'000.000") -> $500'000.000 a $1.000'000.000 | J24: =IFERROR(__xludf.DUMMYFUNCTION("""COMPUTED_VALUE"""),"Centro") -> Centro | K24: =IFERROR(__xludf.DUMMYFUNCTION("""COMPUTED_VALUE"""),"3") -> 3 | L24: =IFERROR(__xludf.DUMMYFUNCTION("""COMPUTED_VALUE"""),9.0) -> 9 | N24: =IFERROR(__xludf.DUMMYFUNCTION("""COMPUTED_VALUE"""),4.0) -> 4 | O24: =IFERROR(__xludf.DUMMYFUNCTION("""COMPUTED_VALUE"""),1.0) -> 1 | P24: =IFERROR(__xludf.DUMMYFUNCTION("""COMPUTED_VALUE"""),2.0) -> 2 | Q24: =IFERROR(__xludf.DUMMYFUNCTION("""COMPUTED_VALUE"""),333.0) -> 333 | R24: =IFERROR(__xludf.DUMMYFUNCTION("""COMPUTED_VALUE"""),150.0) -> 150 | S24: =IFERROR(__xludf.DUMMYFUNCTION("""COMPUTED_VALUE"""),"Rentabilidad $2,700,000") -> Rentabilidad $2,700,000 | T24: =IFERROR(__xludf.DUMMYFUNCTION("""COMPUTED_VALUE"""),"Neiva") -> Neiva | U24: =IFERROR(__xludf.DUMMYFUNCTION("""COMPUTED_VALUE"""),"2") -> 2 | V24: =IFERROR(__xludf.DUMMYFUNCTION("""COMPUTED_VALUE"""),"Medianera") -> Medianera | X24: =IFERROR(__xludf.DUMMYFUNCTION("""COMPUTED_VALUE"""),4.0) -> 4 | Y24: =IFERROR(__xludf.DUMMYFUNCTION("""COMPUTED_VALUE"""),"No tiene") -> No tiene | AA24: =IFERROR(__xludf.DUMMYFUNCTION("""COMPUTED_VALUE"""),"29 años") -> 29 años | AB24: =IFERROR(__xludf.DUMMYFUNCTION("""COMPUTED_VALUE"""),"https://photos.app.goo.gl/2VLZRoS5Y11KNUYm7") -> https://photos.app.goo.gl/2VLZRoS5Y11KNUYm7 | AC24: =IFERROR(__xludf.DUMMYFUNCTION("""COMPUTED_VALUE"""),"Primer piso (3 apartamentos Sala, comedor, 1- 3 habitaciones, cocina integral, 1 baño social, patio de ropa, área de lavado. 2- Sala, comedor, 3 habitaciones, la habitación principal con baño privado, área de lavado, 1 baño social. 3- Se encuentra en obr"&"a gris, ideal para adecuar según las necesidades. + + + Segundo piso: Sala, comedor, 3 habitaciones, 1 baño social, área de lavado, balcón. Excelente ubicación a dos cuadras de la panadería Go Go,restaurante El tinajón, sector altamente valorizado donde e"&"ncontraras jardín infantil, a menos de 5 minutos del centro de la ciudad. Rentabilidad aproximada $2.700.000.") -> Primer piso (3 apartamentos Sala, comedor, 1- 3 habitaciones, cocina integral, 1 baño social, patio de ropa, área de lavado. 2- Sala, comedor, 3 habitaciones, la habitación principal con baño privado, área de lavado, 1 baño social. 3- Se encuentra en obra gris, ideal para adecuar según las necesidades. + + + Segundo piso: Sala, comedor, 3 habitaciones, 1 baño social, área de lavado, balcón. Excelente ubicación a dos cuadras de la panadería Go Go,restaurante El tinajón, sector altamente valorizado donde encontraras jardín infantil, a menos de 5 minutos del centro de la ciudad. Rentabilidad aproximada $2.700.000. | AD24: =IFERROR(__xludf.DUMMYFUNCTION("""COMPUTED_VALUE"""),"Casa rentable bien ubicada y con proyeccíón para mayor rentabilidad.") -> Casa rentable bien ubicada y con proyeccíón para mayor rentabilidad. | AF24: =IFERROR(__xludf.DUMMYFUNCTION("""COMPUTED_VALUE"""),"integral") -> integral | AH24: =IFERROR(__xludf.DUMMYFUNCTION("""COMPUTED_VALUE"""),"Inventario") -> Inventario | AI24: =IFERROR(__xludf.DUMMYFUNCTION("""COMPUTED_VALUE"""),"Aliado") -> Aliado | AJ24: =IFERROR(__xludf.DUMMYFUNCTION("""COMPUTED_VALUE"""),"Casa Honor") -> Casa Honor | AK24: =IFERROR(__xludf.DUMMYFUNCTION("""COMPUTED_VALUE"""),"No aplica") -> No aplica | AL24: =IFERROR(__xludf.DUMMYFUNCTION("""COMPUTED_VALUE"""),"TIENE FOTOS") -> TIENE FOTOS | AM24: =IFERROR(__xludf.DUMMYFUNCTION("""COMPUTED_VALUE"""),3.136442894E9) -> 3136442894 | AO24: =IFERROR(__xludf.DUMMYFUNCTION("""COMPUTED_VALUE"""),"Prop. 3028035444") -> Prop. 3028035444 | AS24: =IFERROR(__xludf.DUMMYFUNCTION("""COMPUTED_VALUE"""),2700000.0) -> 2700000 | AT24: =IFERROR(__xludf.DUMMYFUNCTION("""COMPUTED_VALUE"""),0.0) -> 0 | AU24: =IFERROR(__xludf.DUMMYFUNCTION("""COMPUTED_VALUE"""),0.0) -> 0 | AV24: =IFERROR(__xludf.DUMMYFUNCTION("""COMPUTED_VALUE"""),0.0) -> 0 | AW24: =IFERROR(__xludf.DUMMYFUNCTION("""COMPUTED_VALUE"""),"NO") -> NO | AX24: =IFERROR(__xludf.DUMMYFUNCTION("""COMPUTED_VALUE"""),0.0) -> 0 | AY24: =IFERROR(__xludf.DUMMYFUNCTION("""COMPUTED_VALUE"""),"P") -> P | AZ24: =IFERROR(__xludf.DUMMYFUNCTION("""COMPUTED_VALUE"""),0.0) -> 0 | BA24: =IFERROR(__xludf.DUMMYFUNCTION("""COMPUTED_VALUE"""),"X") -> X | BB24: =IFERROR(__xludf.DUMMYFUNCTION("""COMPUTED_VALUE"""),0.0) -> 0 | BC24: =IFERROR(__xludf.DUMMYFUNCTION("""COMPUTED_VALUE"""),"12 - LEIDY YULIETH, 41 - NORMA MEDINA") -> 12 - LEIDY YULIETH, 41 - NORMA MEDINA | BF24: =IFERROR(__xludf.DUMMYFUNCTION("""COMPUTED_VALUE"""),"https://lh3.googleusercontent.com/pw/AP1GczMHcqtoM0uJYGrQG45Ia14RqoC7eWoMfidOzEc-k8OxblxMGqbTg2ZAJRIA1zMK4qZab2ym75H_7VZVy13fZY2vnChXIhnKcvlQU-pM7OYfn7KiQh5y=w1200|https://lh3.googleusercontent.com/pw/AP1GczMXwIw2ywytBKnrl_ghNcek8hgnhboCs-CY6UQYIHQR_2qjsT"&"onElNVjIQ-2SAtnaDXGm1n5WIuB4muAk1qOi6n7zcVNIsJ-ue1vBwsmYR9iquA2c52=w1200") -> https://lh3.googleusercontent.com/pw/AP1GczMHcqtoM0uJYGrQG45Ia14RqoC7eWoMfidOzEc-k8OxblxMGqbTg2ZAJRIA1zMK4qZab2ym75H_7VZVy13fZY2vnChXIhnKcvlQU-pM7OYfn7KiQh5y=w1200|https://lh3.googleusercontent.com/pw/AP1GczMXwIw2ywytBKnrl_ghNcek8hgnhboCs-CY6UQYIHQR_2qjsTonElNVjIQ-2SAtnaDXGm1n5WIuB4muAk1qOi6n7zcVNIsJ-ue1vBwsmYR9iquA2c52=w1200
A25: =IFERROR(__xludf.DUMMYFUNCTION("""COMPUTED_VALUE"""),"373") -> 373 | B25: =IFERROR(__xludf.DUMMYFUNCTION("""COMPUTED_VALUE"""),"Apartamento en edificio Quirinal - Centro") -> Apartamento en edificio Quirinal - Centro | C25: =IFERROR(__xludf.DUMMYFUNCTION("""COMPUTED_VALUE"""),"Apartamento") -> Apartamento | D25: =IFERROR(__xludf.DUMMYFUNCTION("""COMPUTED_VALUE"""),"Quirinal") -> Quirinal | F25: =IFERROR(__xludf.DUMMYFUNCTION("""COMPUTED_VALUE"""),3.35E8) -> 335000000 | G25: =IFERROR(__xludf.DUMMYFUNCTION("""COMPUTED_VALUE"""),"$300'000.000 a $400'000.000") -> $300'000.000 a $400'000.000 | J25: =IFERROR(__xludf.DUMMYFUNCTION("""COMPUTED_VALUE"""),"Centro") -> Centro | K25: =IFERROR(__xludf.DUMMYFUNCTION("""COMPUTED_VALUE"""),"3") -> 3 | L25: =IFERROR(__xludf.DUMMYFUNCTION("""COMPUTED_VALUE"""),3.0) -> 3 | N25: =IFERROR(__xludf.DUMMYFUNCTION("""COMPUTED_VALUE"""),3.0) -> 3 | O25: =IFERROR(__xludf.DUMMYFUNCTION("""COMPUTED_VALUE"""),1.0) -> 1 | P25: =IFERROR(__xludf.DUMMYFUNCTION("""COMPUTED_VALUE"""),1.0) -> 1 | Q25: =IFERROR(__xludf.DUMMYFUNCTION("""COMPUTED_VALUE"""),143.0) -> 143 | R25: =IFERROR(__xludf.DUMMYFUNCTION("""COMPUTED_VALUE"""),143.0) -> 143 | S25: =IFERROR(__xludf.DUMMYFUNCTION("""COMPUTED_VALUE""")," ") | T25: =IFERROR(__xludf.DUMMYFUNCTION("""COMPUTED_VALUE"""),"Neiva") -> Neiva | U25: =IFERROR(__xludf.DUMMYFUNCTION("""COMPUTED_VALUE"""),"5") -> 5 | X25: =IFERROR(__xludf.DUMMYFUNCTION("""COMPUTED_VALUE"""),3.0) -> 3 | Y25: =IFERROR(__xludf.DUMMYFUNCTION("""COMPUTED_VALUE"""),"No tiene") -> No tiene | Z25: =IFERROR(__xludf.DUMMYFUNCTION("""COMPUTED_VALUE"""),300000.0) -> 300000 | AA25: =IFERROR(__xludf.DUMMYFUNCTION("""COMPUTED_VALUE"""),"No aplica") -> No aplica | AB25: =IFERROR(__xludf.DUMMYFUNCTION("""COMPUTED_VALUE"""),"https://photos.app.goo.gl/8accad79tcZRBSST7") -> https://photos.app.goo.gl/8accad79tcZRBSST7 | AD25: =IFERROR(__xludf.DUMMYFUNCTION("""COMPUTED_VALUE"""),"Apartamento central y remodelado, ubicado en tercer piso. Con ascensor. Edificio de 6 pisos, 2 apartamentos por piso. Ubicado cerca del Sena, Av. La toma, Carrera 5ta. Buenos acabados. Escritura al día.") -> Apartamento central y remodelado, ubicado en tercer piso. Con ascensor. Edificio de 6 pisos, 2 apartamentos por piso. Ubicado cerca del Sena, Av. La toma, Carrera 5ta. Buenos acabados. Escritura al día. | AF25: =IFERROR(__xludf.DUMMYFUNCTION("""COMPUTED_VALUE"""),"integral") -> integral | AG25: =IFERROR(__xludf.DUMMYFUNCTION("""COMPUTED_VALUE"""),"SI") -> SI | AH25: =IFERROR(__xludf.DUMMYFUNCTION("""COMPUTED_VALUE"""),"Inventario") -> Inventario | AI25: =IFERROR(__xludf.DUMMYFUNCTION("""COMPUTED_VALUE"""),"Aliado") -> Aliado | AJ25: =IFERROR(__xludf.DUMMYFUNCTION("""COMPUTED_VALUE"""),"Comis. Sandra BBVA - 50%") -> Comis. Sandra BBVA - 50% | AK25: =IFERROR(__xludf.DUMMYFUNCTION("""COMPUTED_VALUE"""),"No aplica") -> No aplica | AL25: =IFERROR(__xludf.DUMMYFUNCTION("""COMPUTED_VALUE"""),"TIENE FOTOS") -> TIENE FOTOS | AM25: =IFERROR(__xludf.DUMMYFUNCTION("""COMPUTED_VALUE"""),3.138797028E9) -> 3138797028 | AN25: =IFERROR(__xludf.DUMMYFUNCTION("""COMPUTED_VALUE"""),0.0) -> 0 | AP25: =IFERROR(__xludf.DUMMYFUNCTION("""COMPUTED_VALUE"""),"CARRERA 5 - 3ER") -> CARRERA 5 - 3ER | AQ25: =IFERROR(__xludf.DUMMYFUNCTION("""COMPUTED_VALUE"""),2.934327) -> 2.934327 | AR25: =IFERROR(__xludf.DUMMYFUNCTION("""COMPUTED_VALUE"""),-75.2901673) -> -75.290167 | AS25: =IFERROR(__xludf.DUMMYFUNCTION("""COMPUTED_VALUE"""),0.0) -> 0 | AT25: =IFERROR(__xludf.DUMMYFUNCTION("""COMPUTED_VALUE"""),"SI") -> SI | AU25: =IFERROR(__xludf.DUMMYFUNCTION("""COMPUTED_VALUE"""),"SI") -> SI | AV25: =IFERROR(__xludf.DUMMYFUNCTION("""COMPUTED_VALUE"""),"SI") -> SI | AW25: =IFERROR(__xludf.DUMMYFUNCTION("""COMPUTED_VALUE"""),"NO") -> NO | AX25: =IFERROR(__xludf.DUMMYFUNCTION("""COMPUTED_VALUE"""),0.0) -> 0 | AY25: =IFERROR(__xludf.DUMMYFUNCTION("""COMPUTED_VALUE"""),"P") -> P | AZ25: =IFERROR(__xludf.DUMMYFUNCTION("""COMPUTED_VALUE"""),0.0) -> 0 | BA25: =IFERROR(__xludf.DUMMYFUNCTION("""COMPUTED_VALUE"""),"X") -> X | BB25: =IFERROR(__xludf.DUMMYFUNCTION("""COMPUTED_VALUE"""),0.0) -> 0 | BF25: =IFERROR(__xludf.DUMMYFUNCTION("""COMPUTED_VALUE"""),"https://lh3.googleusercontent.com/pw/AP1GczPD_HD_FyU0oyZT_SNj3l0Bt6dAm4-h-4752u9Tr0ruReSizSCz2z65DmKJhOB5bStldHhMXICCw2ncPDI6xXDYElhinchiKRk7mZz0II1bsu-HAGUb=w1200|https://lh3.googleusercontent.com/pw/AP1GczNGIVNVcMXahGPWcVyMeoCeDfqXQSbEAC65WZncVLJl3FFksi"&"PV4KmTFV-GBLun51l2DhGM6ONgvRotGzbsJ6nusNmLnGM4R_f0svORVpEXlt4vmxHJ=w1200|https://lh3.googleusercontent.com/pw/AP1GczOJGYIHwFxRjcqfyFQfoSpWX4YsAYUv9JbEhAD9h92x6ZJzqHNI6TIt_wMWABbyOjBDPxLHib6TjSHsvmdgrXMfwuF2-oouZFPt-Xu-mBhRb57XgrGv=w1200|https://lh3.google"&"usercontent.com/pw/AP1GczMCD1ru5I_bCImeOINajKWwB6YiBqc5QCqLD0Aa5yGYCjIxDBhn1KEVtCDZldU4I012U3QmBT_QUrkzTHA0Kw5ClvNJFK_5pvwPZMiE9cBdQL2RyOmk=w1200|https://lh3.googleusercontent.com/pw/AP1GczP2JfPYyBh7AKdxrs3j3W5vu-xMsRLm7ggnVIWBCAZZgz1JnkXvDwSw9NAJo4W00CLw"&"1ol3snQFLCgXp4bzqwBr1tbn_9jtobJvd8TzOYtuH3ntCN2b=w1200|https://lh3.googleusercontent.com/pw/AP1GczNe1_zr6D1GP5o8F2GVzwUxP7QJuP9IVlBngTmUP0yAlEe5GXdWMDBGYv84SdfGUqup9THtnKh0zup8V06JbKZuVh6ywvFkSeOnDvE8henr0HPurh6Q=w1200|https://lh3.googleusercontent.com/pw"&"/AP1GczMLxLzT6UXvMDguGZ-c0TEIj8cJ9hOGDFrOX0ZbEy2OuCMqUEMAKKsiFn261NoYLuIQJhmxjqZK7za_i5BIG6D7IEme0KCNeVzesXCcxgi9wEjuUaw8=w1200|https://lh3.googleusercontent.com/pw/AP1GczNqnhf4UQ1atyvhIqKT-g7GPK4BZpGenUIonpKdj93k6FGz409UATHZ70qF1mo9uraRv6Olpu9aU5bvUNGbwJ"&"KbtbrwCLONtn3S-PsDbFW6_RtKlLN_=w1200|https://lh3.googleusercontent.com/pw/AP1GczNRWBDqz2FRPYGmRgfaewlbFlMhG-Qa-AUVx2ku_qDA8IKBosVwr08VULGIzF_DekIbAk35vFOFRvFJ1cP8RztcZHBA61iAgK01qizPNNDhMt1jXYTE=w1200|https://lh3.googleusercontent.com/pw/AP1GczNCAV2tKoY4t"&"8n3erLNM6etkngPi0pqmo0CpDSaM8lpQcHUyW20cjTwSv1AeKxf4_hUXeSX7Eq8CBm9Ra6YBWcep7RkTQ7YhwnjzNQQv3PcfMPvW-07=w1200|https://lh3.googleusercontent.com/pw/AP1GczMwEGEQrkVpm2bnY_cgQcBA0j0DwBeHdG8eLc1IwmKnll_S7Ht-X5-XhGHz-O3gD9AHedIbLjLUgDN7PAarmXhHKS8vUyxrUAeFTPzF"&"-MHHr-vdyws9=w1200|https://lh3.googleusercontent.com/pw/AP1GczNCRqQC4Q1VxWy-9BL5x2oh0ndD-ZHGxjNVxR00pbcIMV1nfEMT3fT8kD7gigGQWdQxfjae9dn0RUOMUBtjBBVCWwggvk8qH1kxpQdtPY3b_6bUPBQC=w1200|https://lh3.googleusercontent.com/pw/AP1GczOTis9_RSRPBylIPkFrPlSpvUOku-E"&"v8TyCMRKN3dmW3AwtsRV8qbCnvDSmiLnM3JMmXCTSecfofDBjlnToL-N9E9d_kb0pXuyWCXPW4LfF1Eg-U2ya=w1200|https://lh3.googleusercontent.com/pw/AP1GczOM4JuNMwPR1NY3cyzH8yzjBNNEEUY6RlI5KXB8Tm4yJr5Nzto4LjOEPypy0OY8GwpP8G1LqBMfktWjS7kjCWpOBv-RmW0eOoCcT6PNikNy_WATlvNV=w1200"&"|https://lh3.googleusercontent.com/pw/AP1GczOCMARXwsVXV3Y8nzbfBtJcqrIzku33pmitkaP8Mk8n0tf0m2RNbr9EYNtAKJ_MTiEeVovWS_8utODNIL43YzHmZoRjYuLtH7xzpZJeP6DInRgaZe4M=w1200|https://lh3.googleusercontent.com/pw/AP1GczMA31H60Pp-QcgSqtWPR0abbsadRdx4MdoSM3glmiiroj04i"&"44PdixMWTyNLghgtGcseRRlZlFss8yYX2dxdso57Kpeo7v-1LujwWLwL2E3HTISm_Sl=w1200|https://lh3.googleusercontent.com/pw/AP1GczPasxHSGWC1Pz1V8sCdeIz6ppkSshMTH7OoSwHFl0CqtigzJ-CnTlGa_ngKUk16rHIHgqu2LLM2czBS6YNF4fC-ebnr_kDNzCadMJZrqwm1I-GUjPCP=w1200") -> https://lh3.googleusercontent.com/pw/AP1GczPD_HD_FyU0oyZT_SNj3l0Bt6dAm4-h-4752u9Tr0ruReSizSCz2z65DmKJhOB5bStldHhMXICCw2ncPDI6xXDYElhinchiKRk7mZz0II1bsu-HAGUb=w1200|https://lh3.googleusercontent.com/pw/AP1GczNGIVNVcMXahGPWcVyMeoCeDfqXQSbEAC65WZncVLJl3FFksiPV4KmTFV-GBLun51l2DhGM6ONgvRotGzbsJ6nusNmLnGM4R_f0svORVpEXlt4vmxHJ=w1200|https://lh3.googleusercontent.com/pw/AP1GczOJGYIHwFxRjcqfyFQfoSpWX4YsAYUv9JbEhAD9h92x6ZJzqHNI6TIt_wMWABbyOjBDPxLHib6TjSHsvmdgrXMfwuF2-oouZFPt-Xu-mBhRb57XgrGv=w1200|https://lh3.googleusercontent.com/pw/AP1GczMCD1ru5I_bCImeOINajKWwB6YiBqc5QCqLD0Aa5yGYCjIxDBhn1KEVtCDZldU4I012U3QmBT_QUrkzTHA0Kw5ClvNJFK_5pvwPZMiE9cBdQL2RyOmk=w1200|https://lh3.googleusercontent.com/pw/AP1GczP2JfPYyBh7AKdxrs3j3W5vu-xMsRLm7ggnVIWBCAZZgz1JnkXvDwSw9NAJo4W00CLw1ol3snQFLCgXp4bzqwBr1tbn_9jtobJvd8TzOYtuH3ntCN2b=w1200|https://lh3.googleusercontent.com/pw/AP1GczNe1_zr6D1GP5o8F2GVzwUxP7QJuP9IVlBngTmUP0yAlEe5GXdWMDBGYv84SdfGUqup9THtnKh0zup8V06JbKZuVh6ywvFkSeOnDvE8henr0HPurh6Q=w1200|https://lh3.googleusercontent.com/pw/AP1GczMLxLzT6UXvMDguGZ-c0TEIj8cJ9hOGDFrOX0ZbEy2OuCMqUEMAKKsiFn261NoYLuIQJhmxjqZK7za_i5BIG6D7IEme0KCNeVzesXCcxgi9wEjuUaw8=w1200|https://lh3.googleusercontent.com/pw/AP1GczNqnhf4UQ1atyvhIqKT-g7GPK4BZpGenUIonpKdj93k6FGz409UATHZ70qF1mo9uraRv6Olpu9aU5bvUNGbwJKbtbrwCLONtn3S-PsDbFW6_RtKlLN_=w1200|https://lh3.googleusercontent.com/pw/AP1GczNRWBDqz2FRPYGmRgfaewlbFlMhG-Qa-AUVx2ku_qDA8IKBosVwr08VULGIzF_DekIbAk35vFOFRvFJ1cP8RztcZHBA61iAgK01qizPNNDhMt1jXYTE=w1200|https://lh3.googleusercontent.com/pw/AP1GczNCAV2tKoY4t8n3erLNM6etkngPi0pqmo0CpDSaM8lpQcHUyW20cjTwSv1AeKxf4_hUXeSX7Eq8CBm9Ra6YBWcep7RkTQ7YhwnjzNQQv3PcfMPvW-07=w1200|https://lh3.googleusercontent.com/pw/AP1GczMwEGEQrkVpm2bnY_cgQcBA0j0DwBeHdG8eLc1IwmKnll_S7Ht-X5-XhGHz-O3gD9AHedIbLjLUgDN7PAarmXhHKS8vUyxrUAeFTPzF-MHHr-vdyws9=w1200|https://lh3.googleusercontent.com/pw/AP1GczNCRqQC4Q1VxWy-9BL5x2oh0ndD-ZHGxjNVxR00pbcIMV1nfEMT3fT8kD7gigGQWdQxfjae9dn0RUOMUBtjBBVCWwggvk8qH1kxpQdtPY3b_6bUPBQC=w1200|https://lh3.googleusercontent.com/pw/AP1GczOTis9_RSRPBylIPkFrPlSpvUOku-Ev8TyCMRKN3dmW3AwtsRV8qbCnvDSmiLnM3JMmXCTSecfofDBjlnToL-N9E9d_kb0pXuyWCXPW4LfF1Eg-U2ya=w1200|https://lh3.googleusercontent.com/pw/AP1GczOM4JuNMwPR1NY3cyzH8yzjBNNEEUY6RlI5KXB8Tm4yJr5Nzto4LjOEPypy0OY8GwpP8G1LqBMfktWjS7kjCWpOBv-RmW0eOoCcT6PNikNy_WATlvNV=w1200|https://lh3.googleusercontent.com/pw/AP1GczOCMARXwsVXV3Y8nzbfBtJcqrIzku33pmitkaP8Mk8n0tf0m2RNbr9EYNtAKJ_MTiEeVovWS_8utODNIL43YzHmZoRjYuLtH7xzpZJeP6DInRgaZe4M=w1200|https://lh3.googleusercontent.com/pw/AP1GczMA31H60Pp-QcgSqtWPR0abbsadRdx4MdoSM3glmiiroj04i44PdixMWTyNLghgtGcseRRlZlFss8yYX2dxdso57Kpeo7v-1LujwWLwL2E3HTISm_Sl=w1200|https://lh3.googleusercontent.com/pw/AP1GczPasxHSGWC1Pz1V8sCdeIz6ppkSshMTH7OoSwHFl0CqtigzJ-CnTlGa_ngKUk16rHIHgqu2LLM2czBS6YNF4fC-ebnr_kDNzCadMJZrqwm1I-GUjPCP=w1200
A26: =IFERROR(__xludf.DUMMYFUNCTION("""COMPUTED_VALUE"""),"279") -> 279 | B26: =IFERROR(__xludf.DUMMYFUNCTION("""COMPUTED_VALUE"""),"Casa en barrio Quirinal - IPS") -> Casa en barrio Quirinal - IPS | C26: =IFERROR(__xludf.DUMMYFUNCTION("""COMPUTED_VALUE"""),"Casa") -> Casa | D26: =IFERROR(__xludf.DUMMYFUNCTION("""COMPUTED_VALUE"""),"Quirinal") -> Quirinal | F26: =IFERROR(__xludf.DUMMYFUNCTION("""COMPUTED_VALUE"""),7.5E8) -> 750000000 | G26: =IFERROR(__xludf.DUMMYFUNCTION("""COMPUTED_VALUE"""),"$500'000.000 a $1.000'000.000") -> $500'000.000 a $1.000'000.000 | J26: =IFERROR(__xludf.DUMMYFUNCTION("""COMPUTED_VALUE"""),"Centro") -> Centro | L26: =IFERROR(__xludf.DUMMYFUNCTION("""COMPUTED_VALUE"""),6.0) -> 6 | N26: =IFERROR(__xludf.DUMMYFUNCTION("""COMPUTED_VALUE"""),3.0) -> 3 | O26: =IFERROR(__xludf.DUMMYFUNCTION("""COMPUTED_VALUE"""),1.0) -> 1 | P26: =IFERROR(__xludf.DUMMYFUNCTION("""COMPUTED_VALUE"""),1.0) -> 1 | Q26: =IFERROR(__xludf.DUMMYFUNCTION("""COMPUTED_VALUE"""),240.0) -> 240 | R26: =IFERROR(__xludf.DUMMYFUNCTION("""COMPUTED_VALUE"""),240.0) -> 240 | S26: =IFERROR(__xludf.DUMMYFUNCTION("""COMPUTED_VALUE""")," ") | T26: =IFERROR(__xludf.DUMMYFUNCTION("""COMPUTED_VALUE"""),"Neiva") -> Neiva | U26: =IFERROR(__xludf.DUMMYFUNCTION("""COMPUTED_VALUE"""),"4") -> 4 | V26: =IFERROR(__xludf.DUMMYFUNCTION("""COMPUTED_VALUE"""),"Medianera") -> Medianera | X26: =IFERROR(__xludf.DUMMYFUNCTION("""COMPUTED_VALUE"""),4.0) -> 4 | Y26: =IFERROR(__xludf.DUMMYFUNCTION("""COMPUTED_VALUE"""),"No tiene") -> No tiene | Z26: =IFERROR(__xludf.DUMMYFUNCTION("""COMPUTED_VALUE"""),"No aplica") -> No aplica | AA26: =IFERROR(__xludf.DUMMYFUNCTION("""COMPUTED_VALUE"""),"No aplica") -> No aplica | AB26: =IFERROR(__xludf.DUMMYFUNCTION("""COMPUTED_VALUE"""),"https://photos.app.goo.gl/kJppqsoaVfU6tNoB6") -> https://photos.app.goo.gl/kJppqsoaVfU6tNoB6 | AF26: =IFERROR(__xludf.DUMMYFUNCTION("""COMPUTED_VALUE"""),"semi-integral") -> semi-integral | AG26: =IFERROR(__xludf.DUMMYFUNCTION("""COMPUTED_VALUE"""),"SI") -> SI | AH26: =IFERROR(__xludf.DUMMYFUNCTION("""COMPUTED_VALUE"""),"Inventario") -> Inventario | AI26: =IFERROR(__xludf.DUMMYFUNCTION("""COMPUTED_VALUE"""),"Aliado") -> Aliado | AJ26: =IFERROR(__xludf.DUMMYFUNCTION("""COMPUTED_VALUE"""),"Comis. Santiago alto nivel 50%") -> Comis. Santiago alto nivel 50% | AK26: =IFERROR(__xludf.DUMMYFUNCTION("""COMPUTED_VALUE"""),"No aplica") -> No aplica | AL26: =IFERROR(__xludf.DUMMYFUNCTION("""COMPUTED_VALUE"""),"TIENE FOTOS") -> TIENE FOTOS | AM26: =IFERROR(__xludf.DUMMYFUNCTION("""COMPUTED_VALUE"""),3.166963569E9) -> 3166963569 | AN26: =IFERROR(__xludf.DUMMYFUNCTION("""COMPUTED_VALUE"""),0.0) -> 0 | AQ26: =IFERROR(__xludf.DUMMYFUNCTION("""COMPUTED_VALUE"""),2.9387055) -> 2.9387055 | AR26: =IFERROR(__xludf.DUMMYFUNCTION("""COMPUTED_VALUE"""),-75.2863258) -> -75.286326 | AS26: =IFERROR(__xludf.DUMMYFUNCTION("""COMPUTED_VALUE"""),0.0) -> 0 | AT26: =IFERROR(__xludf.DUMMYFUNCTION("""COMPUTED_VALUE"""),0.0) -> 0 | AU26: =IFERROR(__xludf.DUMMYFUNCTION("""COMPUTED_VALUE"""),0.0) -> 0 | AV26: =IFERROR(__xludf.DUMMYFUNCTION("""COMPUTED_VALUE"""),0.0) -> 0 | AW26: =IFERROR(__xludf.DUMMYFUNCTION("""COMPUTED_VALUE"""),"SI") -> SI | AX26: =IFERROR(__xludf.DUMMYFUNCTION("""COMPUTED_VALUE"""),0.0) -> 0 | AY26: =IFERROR(__xludf.DUMMYFUNCTION("""COMPUTED_VALUE"""),"p") -> p | AZ26: =IFERROR(__xludf.DUMMYFUNCTION("""COMPUTED_VALUE"""),0.0) -> 0 | BA26: =IFERROR(__xludf.DUMMYFUNCTION("""COMPUTED_VALUE"""),"X") -> X | BB26: =IFERROR(__xludf.DUMMYFUNCTION("""COMPUTED_VALUE"""),0.0) -> 0 | BC26: =IFERROR(__xludf.DUMMYFUNCTION("""COMPUTED_VALUE"""),"35 - LUIS ANGEL VARGAS") -> 35 - LUIS ANGEL VARGAS | BF26: =IFERROR(__xludf.DUMMYFUNCTION("""COMPUTED_VALUE"""),"https://lh3.googleusercontent.com/pw/AP1GczPbR1W_jWsyP1Mc-YLcP-qk8CZxjuvr4Cr1cLaVGp5aDYpz3ZmgT5tXsw1MUDg-keh3FDjLqvkox3rPgb2ICo0PCn0IGQfF4hTMc4R3w2sRB4JJzfnT=w1200|https://lh3.googleusercontent.com/pw/AP1GczNvxKIMGC0HZaU1Ont8AzkZ3IA_ANaqmfhFkDSlyaHciGqada"&"_SSGR3hetGgcNBEcNQPQuojkPzFIuojocp9MpUxhaDdc35tvvjOA3LdZJRqTCmCpil=w1200|https://lh3.googleusercontent.com/pw/AP1GczNhk6mo0raM3dovaMa3MhBESiOqNhf6P5ieGBdnQoyFbFL52hX33-qJN97-BqgF0eyviFSRz_P-OITGbCChSOwphI-URllvTZqjuyzfjtr0oHYIgh3m=w1200|https://lh3.google"&"usercontent.com/pw/AP1GczN_R-r3S-OjC0BEkCDgHJnNvAXrTKt6MlXjgSgwW68wCxVWJ8IFuQsdgxxM1St8GCVxYKrudcVR9kcdeRbi82xjF1x38oTErGKztUzGM_PZFWOyg7-2=w1200|https://lh3.googleusercontent.com/pw/AP1GczP6NKLLVcUKWo4W54C5DmqUoefPlokx3cU37BJbZCw1w6iIauukWgphZGtZO_XJRJwR"&"oinCI5on_pYCERKWflCkAVTvdRdVc-RFhBK6VfLVwlwytoUD=w1200|https://lh3.googleusercontent.com/pw/AP1GczMrzqNEFtWbT47tdmO86P2vcRRhimoBvjRfpi7qjyCqUXkvXqmFjc_LsQdF-uqCWDBGl6FNv1UGThG9uJzjR4KRuK8qWqNRXszZp_jKL00cZpuQZ5ZH=w1200") -> https://lh3.googleusercontent.com/pw/AP1GczPbR1W_jWsyP1Mc-YLcP-qk8CZxjuvr4Cr1cLaVGp5aDYpz3ZmgT5tXsw1MUDg-keh3FDjLqvkox3rPgb2ICo0PCn0IGQfF4hTMc4R3w2sRB4JJzfnT=w1200|https://lh3.googleusercontent.com/pw/AP1GczNvxKIMGC0HZaU1Ont8AzkZ3IA_ANaqmfhFkDSlyaHciGqada_SSGR3hetGgcNBEcNQPQuojkPzFIuojocp9MpUxhaDdc35tvvjOA3LdZJRqTCmCpil=w1200|https://lh3.googleusercontent.com/pw/AP1GczNhk6mo0raM3dovaMa3MhBESiOqNhf6P5ieGBdnQoyFbFL52hX33-qJN97-BqgF0eyviFSRz_P-OITGbCChSOwphI-URllvTZqjuyzfjtr0oHYIgh3m=w1200|https://lh3.googleusercontent.com/pw/AP1GczN_R-r3S-OjC0BEkCDgHJnNvAXrTKt6MlXjgSgwW68wCxVWJ8IFuQsdgxxM1St8GCVxYKrudcVR9kcdeRbi82xjF1x38oTErGKztUzGM_PZFWOyg7-2=w1200|https://lh3.googleusercontent.com/pw/AP1GczP6NKLLVcUKWo4W54C5DmqUoefPlokx3cU37BJbZCw1w6iIauukWgphZGtZO_XJRJwRoinCI5on_pYCERKWflCkAVTvdRdVc-RFhBK6VfLVwlwytoUD=w1200|https://lh3.googleusercontent.com/pw/AP1GczMrzqNEFtWbT47tdmO86P2vcRRhimoBvjRfpi7qjyCqUXkvXqmFjc_LsQdF-uqCWDBGl6FNv1UGThG9uJzjR4KRuK8qWqNRXszZp_jKL00cZpuQZ5ZH=w1200
